Workbook
Name データタイプ: '99_マスタ'!#REF!
Name 概念: '99_マスタ'!#REF!
Name 業務カテゴリ: '99_マスタ'!#REF!
Name 指標タイプ: '99_マスタ'!#REF!
Name 定義状態: '99_マスタ'!#REF!
Name 優先度: '99_マスタ'!#REF!

Sheet ★指標_用語辞書
B2: No | C2: 経営ダッシュボード | D2: 確認部門 | E2: 分科① | F2: 分科② | G2: 分科③ | H2: 分科④ | I2: 分科⑤ | J2: 分科⑥ | K2: 指標大分類 | L2: 指標タイプ Lv.1 | M2: 指標タイプ Lv.2 | N2: 指標タイプ Lv.3 | O2: 今後の正式名称 | P2: 現時点の資料での出現用語 | Q2: 略称/同義語 | R2: 定義 | S2: 算出式 / 構造 | T2: 単位 | U2: 使用シーン / 主な帳票 | Z2: 出典 | AH2: 要修正フラグ | AI2: 修正後 | AL2: e
U3: 営業 | V3: マーケ | W3: 生産 | X3: SCM | Y3: 経営戦略 ・収益企画 | Z3: 営業 | AA3: マーケ | AB3: 生産 | AC3: SCM | AD3: 経営戦略 ・収益企画 | AE3: 備考 | AF3: 確認対象部門 | AG3: 収益企画部担当者 | AH3: ドラフトに誤りがある場合1を記載 | AI3: 定義 | AJ3: 算出式 / 構造 | AK3: 単位 | AL3: e
B4: =ROW()-3 -> 1 | C4: ○ | K4: A_指標 | L4: 01_財務指標 | M4: 01_PL | N4: 売上高 | O4: 総売上高 | P4: 総売上高 | Q4: 総売 | R4: 控除を行っていない売上の合計額。ロッテの場合は仕切り価格販売の積み上げ | S4: 販売数量×単価（仕切価格） | T4: 円 | U4: 全国営業会議, 営業政策, 予算表 | V4: — | W4: — | X4: 商品規格適正化検討、ロッテ業績 | Y4: 個別決算 | Z4: 営政, 全営 | AA4: — | AB4: — | AC4: SCM会議、ロッテ業績簡易版 | AD4: 2月個別決算 | AF4: 収益企画 | AH4: 1 | AI4: 控除を行っていない売上の合計額。SAPで計上された売上の合計額。 | AJ4: 販売数量×単価（実際に販売先に販売した単価）の積み上げ | AK4: 円 | AL4: e
B5: =ROW()-3 -> 2 | K5: A_指標 | L5: 01_財務指標 | M5: 01_PL | N5: 売上高 | O5: 総売上高 | P5: 売上（控除前） | Q5: ー | R5: 売上控除項目（年契リベート・販促協賛金等の取引先への割戻し）を差し引く前の売上高。事業損益表において各種比率（特売費率・販売費計率等）の分母として使用される基準売上。控除後の純売上高とは異なり、割戻し前の総額ベースの売上を示す | S5: 純売上高 ＋ 売上控除額 | T5: 円 | U5: 事業損益 | V5: — | W5: — | X5: — | Y5: — | Z5: 全営 | AA5: — | AB5: — | AC5: — | AD5: — | AL5: e
B6: =ROW()-3 -> 3 | C6: ○ | K6: A_指標 | L6: 01_財務指標 | M6: 01_PL | N6: 売上高 | O6: 純売上高 | P6: 純売上高 | Q6: 純売ベース、純売 | R6: 総売上から返品・値引等を控除した売上。営業利益の率計算の分母として使用される。 | S6: 総売上 − 値引・返品・販売費（一部） | T6: 円 | U6: 品目別営業利益（純売ベース）, 営業会議資料 | V6: 新商品マーケット分析 | W6: — | X6: — | Y6: 個別決算 | Z6: 全営 | AA6: アジア恋ナレッジ | AB6: — | AC6: — | AD6: 2月個別決算、本部KPI確認 | AF6: 収益企画 | AH6: 1 | AI6: 総売上高から特売費等の控除対象経費を差し引いた売上。 | AJ6: 総売上高 − 売上控除 | AK6: 円 | AL6: e
B7: =ROW()-3 -> 4 | C7: ○ | K7: A_指標 | L7: 01_財務指標 | M7: 01_PL | N7: 売上高 | O7: 純売上高 | P7: 売上 | Q7: 売上高 | R7: 純売上高を売上高として記載 | T7: 円 | U7: — | V7: — | W7: — | X7: — | Y7: KK定例会長報告 | Z7: — | AA7: — | AB7: — | AC7: — | AD7: KK定例会長報告 | AL7: e
B8: =ROW()-3 -> 5 | K8: A_指標 | L8: 01_財務指標 | M8: 01_PL | N8: 売上高 | O8: 海外事業計（現地会計基準） | P8: 海外事業計（現地会計基準） | Q8: 海外事業計 | R8: ㈱ロッテの資料では、海外現法（アジア計＋ウェデル計）の純売上高・営業利益を現地の会計基準で集計した合計。社内レートで円換算して表示。 | S8: アジア計（タイ・インドネシア・ベトナム・台湾）+ ウェデル計（ウェデル・ウェデルカフェ） | T8: 円 | U8: — | V8: — | W8: — | X8: — | Y8: 個別決算報告（海外現法） | Z8: — | AA8: — | AB8: — | AC8: — | AD8: 2月個別決算 | AL8: e
B9: =ROW()-3 -> 6 | C9: ○ | K9: A_指標 | L9: 01_財務指標 | M9: 01_PL | N9: 売上高 | O9: 連結売上高 | P9: 連結売上高 | Q9: 連結 | R9: ㈱ロッテおよびグループ会社を連結した売上高。経理の連結決算で使用される概念で、単体（個別）売上とは異なる。 | S9: ・単体売上高 + グループ会社売上 − 内部取引消去 ・単体売上高＋グループ会社売上ー連結修正 | T9: 円 | U9: — | V9: — | W9: — | X9: — | Y9: 個別決算報告（参照概念）、KK定例会長報告（連結決算速報：国内計・海外計・WEDEL等） | Z9: — | AA9: — | AB9: — | AC9: — | AD9: KK定例会長報告 | AF9: 収益企画 経理 | AH9: 1 | AI9: ㈱ロッテおよびグループ会社を連結した売上高。経理の連結決算で使用される概念で、単体（個別）売上とは異なる。 | AJ9: 単体売上高＋グループ会社売上ー連結修正ー為替差額 | AK9: 円 | AL9: e
B10: =ROW()-3 -> 7 | K10: A_指標 | L10: 01_財務指標 | M10: 01_PL | N10: 売上控除 | O10: フィ | P10: フィ | Q10: 基本フィ | R10: 卸店の機能に対する割戻金。DBフィ／社会課題取組フィ／パートナーフィの3区分。 | S10: 売上規模ベース＋機能評価による加算 | T10: %, 円 | U10: 卸取引制度, 基本フィ覚書 | V10: — | W10: — | X10: — | Y10: — | Z10: 菓初, 推進M | AA10: — | AB10: — | AC10: — | AD10: — | AL10: e
B11: =ROW()-3 -> 8 | C11: ○ | K11: A_指標 | L11: 01_財務指標 | M11: 01_PL | N11: 売上控除 | O11: 売上控除 | P11: 売上控除 | Q11: 控除 | R11: 総売上高から差し引かれる控除項目の合計。主に特売費（控除対象）が含まれる。純売上高＝総売上高−売上控除。 | S11: 総売上高 − 純売上高 | T11: 円 | U11: — | V11: — | W11: — | X11: — | Y11: 損益計算書（P/L） | Z11: — | AA11: — | AB11: — | AC11: — | AD11: 2月個別決算, 3月販売実績 | AF11: 収益企画 | AH11: 1 | AI11: 総売上高から差し引かれる控除項目の合計。主に特売費（控除対象）が含まれる。純売上高＝総売上高−売上控除。 | AJ11: フィ＋特売費（控除対象）＋拡売費（控除対象）＋販売店手数料（控除対象）＋経費出荷＋売上控除（輸出）＋手数料（直接取引） | AK11: 円 | AL11: e
B12: =ROW()-3 -> 9 | K12: A_指標 | L12: 01_財務指標 | M12: 01_PL | N12: 売上控除 | O12: センターフィ | P12: センターフィ | Q12: ー | R12: 特売費の種類の一つ。XXX（どのような特売費か要確認） | T12: ー | U12: — | V12: — | W12: — | X12: SCM会議（特売費適正化） | Y12: — | Z12: — | AA12: — | AB12: — | AC12: SCM会議 | AD12: — | AL12: e
B13: =ROW()-3 -> 10 | C13: ○ | K13: A_指標 | L13: 01_財務指標 | M13: 01_PL | N13: 売上控除 | O13: 特売費 | P13: 特売費 | Q13: — | R13: 特売実施で発生する経費全般。控除対象/控除対象外で区別。 | S13: 値差補填 + 特売条件 + 特売拡売費 等 | T13: 円 | U13: Biz, 特売費分析 | V13: — | W13: — | X13: SCM会議（特売費コントロール・値差上限導入検討） | Y13: — | Z13: 営政, 全営 | AA13: — | AB13: — | AC13: SCM会議, 第3回SCM議事録, 第2回SCM議事録 | AD13: — | AF13: 収益企画 | AH13: 1 | AI13: 特売実施で発生する経費全般。控除対象/控除対象外で区別。 | AJ13: 特売費（控除対象）＋特売費（対象外） | AK13: 円 | AL13: e
B14: =ROW()-3 -> 11 | C14: ○ | K14: A_指標 | L14: 01_財務指標 | M14: 01_PL | N14: 売上控除 | O14: 特売費率 | P14: 特売費率 | Q14: — | R14: 売上に対する特売費の比率。営業利益管理の主要KPI。 | S14: 特売費 ÷ 総売上 × 100 | T14: % | U14: 営業政策, 全営の特売費分析 | V14: 損益概況 | W14: — | X14: SCM会議 | Y14: 収益企画社長報告（PLツリー：品目別特売費率管理） | Z14: 営政, 全営 | AA14: 損益共有MTG | AB14: — | AC14: 第2回SCM議事録 | AD14: KK定例会長報告 | AF14: 収益企画 | AH14: 1 | AI14: 売上に対する特売費の比率。営業部門における主要KPI。分母が総売上高の場合と純売上高の場合がある。 | AJ14: 特売費 ÷ 総売上高 × 100 または 特売費 ÷ 純売上高 × 100 | AK14: % | AL14: e
B15: =ROW()-3 -> 12 | K15: A_指標 | L15: 01_財務指標 | M15: 01_PL | N15: 売上控除 | O15: 特売経費率 | P15: 特売経費率 | Q15: 特売費率（総売比） | R15: 売上に占める特売費の割合。品目別・統括支店別・ブランド別に管理し、予算比・前年比で分析する。費用の使用効率を示す指標で、売上増加と特売費削減の両立が目標。 | S15: 特売経費率 = 特売費 ÷ 売上（総売） × 100 | T15: % | U15: 特売費分析, 月次全国営業会議, 営業政策 | V15: — | W15: — | X15: — | Y15: — | Z15: 全営, 営政 | AA15: — | AB15: — | AC15: — | AD15: — | AL15: e
B16: =ROW()-3 -> 13 | C16: ○ | K16: A_指標 | L16: 01_財務指標 | M16: 01_PL | N16: 売上原価 | O16: 売上原価 | P16: 売上原価 | R16: PLの売上原価 | S16: ・原価（変動）＋原価（固定） ・原材料費＋包材費＋外注加工費＋直接労務費＋機械費（変動）＋機械費（固定）＋間接費＋廃棄損＋売上原価調整 | AL16: e
B17: =ROW()-3 -> 14 | K17: A_指標 | L17: 01_財務指標 | M17: 01_PL | N17: 売上原価 | O17: 原価（変動） | P17: 原価（変動） | R17: PLの売上原価の構成要素の１つ | S17: 原材料費＋包材費＋外注加工費＋直接労務費＋機械費（変動） | AL17: e
B18: =ROW()-3 -> 15 | K18: A_指標 | L18: 01_財務指標 | M18: 01_PL | N18: 売上原価 | O18: 原価（固定） | P18: 原価（固定） | R18: PLの売上原価の構成要素の１つ | S18: 機械費（固定）＋間接費＋廃棄損＋売上原価調整 | AL18: e
B19: =ROW()-3 -> 16 | C19: ○ | K19: A_指標 | L19: 01_財務指標 | M19: 01_PL | N19: 売上原価 | O19: 原料費 | P19: 原材料費 | R19: PLの売上原価の構成要素の１つ。原価（変動）の要素の１つ | AH19: 1 | AK19: 円 | AL19: e
B20: =ROW()-3 -> 17 | C20: ○ | K20: A_指標 | L20: 01_財務指標 | M20: 01_PL | N20: 売上原価 | O20: 包材費 | P20: 包材費 | R20: PLの売上原価の構成要素の１つ。原価（変動）の要素の１つ | AH20: 1 | AK20: 円 | AL20: e
C21: ○ | K21: A_指標 | L21: 01_財務指標 | M21: 01_PL | N21: 売上原価 | O21: 原材料費 | AH21: 1 | AJ21: 原料費＋包材費 | AK21: 円
B22: =ROW()-3 -> 19 | C22: ○ | K22: A_指標 | L22: 01_財務指標 | M22: 01_PL | N22: 売上原価 | O22: 外注加工費 | P22: 外注加工費 | R22: PLの売上原価の構成要素の１つ。原価（変動）の要素の１つ | AH22: 1 | AK22: 円 | AL22: e
B23: =ROW()-3 -> 20 | C23: ○ | K23: A_指標 | L23: 01_財務指標 | M23: 01_PL | N23: 売上原価 | O23: 直接労務費 | P23: 直接労務費 | R23: PLの売上原価の構成要素の１つ。原価（変動）の要素の１つ | AH23: 1 | AK23: 円 | AL23: e
B24: =ROW()-3 -> 21 | C24: ○ | K24: A_指標 | L24: 01_財務指標 | M24: 01_PL | N24: 売上原価 | O24: 機械費（変動） | P24: 機械費（変動） | R24: PLの売上原価の構成要素の１つ。原価（変動）の要素の１つ | AH24: 1 | AK24: 円 | AL24: e
B25: =ROW()-3 -> 22 | C25: ○ | K25: A_指標 | L25: 01_財務指標 | M25: 01_PL | N25: 売上原価 | O25: 機械費（固定） | P25: 機械費（固定） | R25: PLの売上原価の構成要素の１つ。原価（固定）の要素の１つ | AH25: 1 | AK25: 円 | AL25: e
B26: =ROW()-3 -> 23 | C26: ○ | K26: A_指標 | L26: 01_財務指標 | M26: 01_PL | N26: 売上原価 | O26: 間接費 | P26: 間接費 | R26: PLの売上原価の構成要素の１つ。原価（固定）の要素の１つ | AH26: 1 | AK26: 円 | AL26: e
B27: =ROW()-3 -> 24 | C27: ○ | K27: A_指標 | L27: 01_財務指標 | M27: 01_PL | N27: 売上原価 | O27: 廃棄損 | P27: 廃棄損 | R27: PLの売上原価の構成要素の１つ。原価（固定）の要素の１つ | AH27: 1 | AK27: 円 | AL27: e
B28: =ROW()-3 -> 25 | C28: ○ | K28: A_指標 | L28: 01_財務指標 | M28: 01_PL | N28: 売上原価 | O28: 売上原価調整 | P28: 売上原価調整 | R28: PLの売上原価の構成要素の１つ。原価（固定）の要素の１つ | AH28: 1 | AK28: 円 | AL28: e
B29: =ROW()-3 -> 26 | C29: ○ | K29: A_指標 | L29: 01_財務指標 | M29: 01_PL | N29: 売上原価 | O29: 売上原価率 | P29: 売上原価率 | Q29: 原価率 | R29: 純売上高に対する売上原価の比率。製造コスト効率を示す主要管理指標。 | S29: 売上原価 ÷ 純売上高 × 100 | T29: % | U29: — | V29: — | W29: 生産本部月次管理（原価率実績・予算差管理） | X29: — | Y29: KK定例会長報告 | Z29: — | AA29: — | AB29: 会長報告生産3月 | AC29: — | AD29: KK定例会長報告,2月個別決算 | AE29: ・KK定例会長報告では純売上高に対する売上原価率を算出、個別決算の収益性分析では総売上高に対する売上原価率を算出 | AF29: 収益企画 | AH29: 1 | AI29: 売上に対する売上原価の比率。製造コスト効率を示す主要管理指標。分母が総売上高の場合と純売上高の場合がある。 | AJ29: 売上原価 ÷ 総売上高 × 100 または 売上原価 ÷ 純売上高 × 100 | AK29: % | AL29: e
B30: =ROW()-3 -> 27 | C30: ○ | K30: A_指標 | L30: 01_財務指標 | M30: 01_PL | N30: 売上原価 | O30: 原料費率 | P30: 原料費率 | Q30: — | R30: 売上に対する原料費（原材料費）の比率。カカオ豆等の原料相場の影響を直接受ける主要原価KPI。 | S30: 原料費 ÷ 総売上高（または純売上高）× 100 | T30: % | U30: — | V30: 損益概況 | W30: 生産本部月次管理 | X30: — | Y30: 収益企画社長報告 | Z30: — | AA30: 損益共有MTG | AB30: SCM会議 | AC30: — | AD30: 収益企画社長報告 | AF30: 収益企画 | AH30: 1 | AI30: 売上に対する原料費の比率。分母が総売上高の場合と純売上高の場合がある。 | AJ30: 原料費 ÷ 総売上高 × 100 または 原料費 ÷ 純売上高 × 100 | AK30: ％ | AL30: e
B31: =ROW()-3 -> 28 | C31: ○ | K31: A_指標 | L31: 01_財務指標 | M31: 01_PL | N31: 販管費 | O31: 販管費 | P31: 販管費 | Q31: — | R31: 販売費及び一般管理費の合計。広告宣伝費・運賃・保管料・人件費・一般管理費等を含む。 | S31: 販売費 + 広告宣伝費 + 運賃・保管料 + 人件費 + 一般管理費 | T31: 円 | U31: — | V31: — | W31: — | X31: — | Y31: 損益計算書（P/L） | Z31: — | AA31: — | AB31: — | AC31: — | AD31: 2月個別決算 | AH31: 1 | AI31: 販売費及び一般管理費の合計。広告宣伝費・運賃・保管料・人件費・一般管理費等を含む。 | AJ31: 販売費（控除対象外）+ 広告宣伝費 + 運賃・保管料 + 人件費 + 一般管理費 | AK31: 円 | AL31: e
B32: =ROW()-3 -> 29 | C32: ○ | K32: A_指標 | L32: 01_財務指標 | M32: 01_PL | N32: 販管費 | O32: 販売費 | P32: 販売費 | Q32: ー | R32: 特売費・拡売費等販売に関わる費用 | S32: 注文獲得費（特売費＋拡売費）＋注文獲得促進費控除外（見本費（旧販社分）＋市場対策費＋自動販売機費＋自転車費（販促）＋販売店指導費＋販売店手数料＋その他（販促）） | T32: 円 | U32: — | V32: — | W32: — | X32: — | Y32: 損益計算書（P/L） | Z32: — | AA32: — | AB32: — | AC32: — | AD32: 2月個別決算 | AH32: 1 | AI32: 特売費・拡売費等販売に関わる費用 | AJ32: 注文獲得費（特売費＋拡売費）＋注文獲得促進費控除外（見本費（旧販社分）＋市場対策費＋自動販売機費＋自転車費（販促）＋販売店指導費＋販売店手数料＋その他（販促）） | AK32: 円 | AL32: e
B33: =ROW()-3 -> 30 | C33: ○ | K33: A_指標 | L33: 01_財務指標 | M33: 01_PL | N33: 販管費 | O33: 販売費率（売上控除＋控除対象外） | P33: 販売費率（売上控除＋控除対象外） | Q33: ー | R33: 総売上に対する販売費の比率。 | S33: 販売費 ÷ 総売上高 × 100 | T33: ％ | U33: — | V33: — | W33: — | X33: — | Y33: 収益性分析 | Z33: — | AA33: — | AB33: — | AC33: — | AD33: 2月個別決算 | AF33: 収益企画 | AH33: 1 | AI33: 売上に対する販売費の比率。分母が総売上高の場合と純売上高の場合がある。 | AJ33: 販売費 ÷ 総売上高 × 100 または 販売費 ÷ 純売上高 × 100 | AK33: ％ | AL33: e
B34: =ROW()-3 -> 31 | C34: ○ | K34: A_指標 | L34: 01_財務指標 | M34: 01_PL | N34: 販管費 | O34: 注文獲得費 | P34: 注文獲得費 | R34: PLの販売費の構成要素の１つ | S34: 特売費 （控除対象外）＋拡売費（控除対象外）＋注文獲得費 | T34: 円 | AH34: 1 | AK34: 円 | AL34: e
B35: =ROW()-3 -> 32 | C35: ○ | K35: A_指標 | L35: 01_財務指標 | M35: 01_PL | N35: 販管費 | O35: 拡売費（控除対象外） | P35: 拡売費（控除対象外） | Q35: 注文獲得費 | R35: PLの注文獲得費の構成要素の１つ。ディスプレイ・資材・本部対策など、小売店に支払われないキャンペーン経費。卸店への割戻に充当される本部インセンティブも含む。 | S35: 資材費 + ディスプレイ費 + 本部対策 等 | T35: 円 | U35: 予算編成会議, アクションプラン | V35: — | W35: — | X35: — | Y35: — | Z35: 推進M, 営政 | AA35: — | AB35: — | AC35: — | AD35: — | AH35: 1 | AL35: e
B36: =ROW()-3 -> 33 | C36: ○ | K36: A_指標 | L36: 01_財務指標 | M36: 01_PL | N36: 販管費 | O36: 注文獲得費調整 | P36: 注文獲得費調整 | R36: PLの注文獲得費の構成要素の１つ。 | T36: 円 | AL36: e
B37: =ROW()-3 -> 34 | C37: ○ | K37: A_指標 | L37: 01_財務指標 | M37: 01_PL | N37: 販管費 | O37: 広告宣伝費 | P37: 広告宣伝費 | Q37: — | R37: 広告・宣伝に関する費用 | S37: 宣伝費媒体＋宣伝費その他（ディスプレイ・専門誌・オウンドメディアアド） | T37: 円 | U37: — | V37: — | W37: — | X37: — | Y37: 損益計算書（P/L) | Z37: — | AA37: — | AB37: — | AC37: — | AD37: 2月個別決算 | AH37: 1 | AJ37: 宣伝費媒体＋宣伝費その他 | AK37: 円 | AL37: e
B38: =ROW()-3 -> 35 | C38: ○ | K38: A_指標 | L38: 01_財務指標 | M38: 01_PL | N38: 販管費 | O38: 広告宣伝費率 | P38: 広告宣伝費率 | Q38: — | R38: 総売上高に対する広告宣伝費の割合 | S38: 広告宣伝費計 ÷ 総売上高 | T38: ％ | U38: — | V38: — | W38: — | X38: — | Y38: 収益性分析 | Z38: — | AA38: — | AB38: — | AC38: — | AD38: 2月個別決算 | AE38: ・％と金額どちらが指標になるかは要確認 | AF38: 収益企画 | AH38: 1 | AI38: 売上に対する広告宣伝費の比率。分母が総売上高の場合と純売上高の場合がある。 | AJ38: 広告宣伝費 ÷ 総売上高 × 100 または 広告宣伝費 ÷ 純売上高 × 100 | AK38: ％ | AL38: e
B39: =ROW()-3 -> 36 | C39: ○ | K39: A_指標 | L39: 01_財務指標 | M39: 01_PL | N39: 販管費 | O39: 宣伝費媒体 | P39: 宣伝費媒体 | Q39: ー | R39: テレビ・デジタル・新聞・雑誌等の広告媒体に出稿するための費用。宣伝費全体のうち、制作費（クリエイティブ制作コスト）を除いた媒体掲載・放映に要するコスト。PLツリー上では販売関連費の構成要素として計上される。 | T39: 円 | U39: — | V39: 損益概況 | W39: — | X39: — | Y39: — | Z39: — | AA39: 損益共有MTG | AB39: — | AC39: — | AD39: — | AH39: 1 | AL39: e
B40: =ROW()-3 -> 37 | C40: ○ | K40: A_指標 | L40: 01_財務指標 | M40: 01_PL | N40: 販管費 | O40: 運賃・保管料 | P40: 運賃・保管料 | Q40: SCM費、物流費 | R40: SCMが管轄する一次輸送費、二次配送費、保管・荷役料にその他物流費を加算したKPI | S40: 一次輸送費＋二次配送費＋保管・荷役料＋その他物流費 | T40: 円 | U40: — | V40: — | W40: — | X40: SCM会議（年度KPI） | Y40: — | Z40: — | AA40: — | AB40: — | AC40: SCM会議 | AD40: — | AF40: SCM | AH40: 1 | AI40: ㈱ロッテが管轄する一次輸送費、二次輸送費、保管・荷役料にその他物流費を加算した費用。SCM部門の主要KPI。（SCM本部管轄分のみでも別管理している） | AJ40: 一次輸送費＋二次配送費＋保管・荷役料＋その他物流費 | AK40: 円 | AL40: e
B41: =ROW()-3 -> 38 | C41: ○ | K41: A_指標 | L41: 01_財務指標 | M41: 01_PL | N41: 販管費 | O41: 運賃保管料率 | P41: 運賃保管料率 | Q41: 物流費率 | R41: 売上（総売高）に対する運賃・保管料の比率。物流コスト効率の管理KPI。 | S41: （運賃 + 保管料） ÷ 総売上高 × 100 | T41: % | U41: 全国営業会議（物流費効率化KPI） | V41: — | W41: — | X41: SCM本部会議（物流費率管理） | Y41: 収益性分析、KK定例会長報告、収益企画社長報告 | Z41: 営政, 全営 | AA41: — | AB41: — | AC41: SCM本部会議全体 | AD41: 2月個別決算、KK定例会長報告, 収益企画社長報告 | AF41: SCM | AH41: 1 | AI41: 売上に対する運賃保管料の比率。分母が総売上高の場合と純売上高の場合がある。 | AJ41: 運賃保管料 ÷ 総売上高 × 100 または 運賃保管料 ÷ 純売上高 × 100 | AK41: ％ | AL41: e
B42: =ROW()-3 -> 39 | C42: ○ | K42: A_指標 | L42: 01_財務指標 | M42: 01_PL | N42: 販管費 | O42: 保管料 | P42: 保管料 | Q42: — | R42: 工場・倉庫での商品保管に対して倉庫業者に支払う費用。在庫数量と単価の積で算出される。月次の物流費報告において一次輸送・二次配送等と並んで管理される。 | S42: 在庫数量 × 保管単価（円/ケース） | T42: 円 | U42: — | V42: — | W42: — | X42: 月次物流費報告（物流企画一課・二課）、在庫状況との連動管理 | Y42: — | Z42: — | AA42: — | AB42: — | AC42: 物流企画一課, 物流企画二課、SCM会議 | AD42: — | AH42: 1 | AI42: 保管料の算出根拠には、保管単価/ケース 以外にも、物流パートナーとの契約によって何パターンかある。また、荷役料は入出庫料として支払われる。 ※№.37の運賃・保管料の「保管料」は保管料＋荷役料の意味があるが、呼称として「保管料」の場合保管料のみで荷役料は含まれない場合もあるので、どちらとするかは定義付けが必要かと存じます。 | AJ42: 保管単価/ケース、保管単価/パレット、保管単価/坪、保管単価/従量従価率 荷役単価/ケース | AK42: 円 | AL42: e
B43: =ROW()-3 -> 40 | C43: ○ | K43: A_指標 | L43: 01_財務指標 | M43: 01_PL | N43: 販管費 | O43: 人件費 | P43: 人件費 | Q43: — | R43: 自社社員の給与・賞与・退職給付費用・法定福利費、および派遣社員等臨時社員に対する人件費（雑給） | S43: 自社社員人件費（給与＋賞与＋退職給付費用＋法定福利費）＋雑給 | T43: 円 | U43: — | V43: — | W43: — | X43: — | Y43: 人件費明細 | Z43: — | AA43: — | AB43: — | AC43: — | AD43: 2月個別決算 | AE43: ・労務費が対象かは要確認 | AK43: 円 | AL43: e
B44: =ROW()-3 -> 41 | C44: ○ | K44: A_指標 | L44: 01_財務指標 | M44: 01_PL | N44: 販管費 | O44: 人件費率(総売比) | P44: 人件費率(総売比) | Q44: — | R44: 総売上高に対する総人件費の割合 | S44: 総人件費 ÷ 総売上高 | T44: ％ | U44: — | V44: — | W44: — | X44: — | Y44: 収益性分析 | Z44: — | AA44: — | AB44: — | AC44: — | AD44: 2月個別決算 | AE44: ・目的によって分母が純売か総売か変わる ・％と金額どちらが指標になるかは要確認 | AH44: 1 | AI44: 総売上高に対する人件費の比率。 | AJ44: 人件費 ÷ 総売上高 × 100 | AK44: ％ | AL44: e
B45: =ROW()-3 -> 42 | C45: ○ | K45: A_指標 | L45: 01_財務指標 | M45: 01_PL | N45: 販管費 | O45: 人件費率(純売比) | P45: 人件費率(純売比) | Q45: — | R45: 純売上高に対する総人件費の割合 | S45: 総人件費 ÷ 純売上高 | T45: ％ | U45: — | V45: — | W45: — | X45: — | Y45: KK定例会長報告 | Z45: — | AA45: — | AB45: — | AC45: — | AD45: KK定例会長報告 | AE45: ・目的によって分母が純売か総売か変わる | AH45: 1 | AI45: 純売上高に対する人件費の比率。 | AJ45: 人件費 ÷ 純売上高 × 100 | AK45: ％ | AL45: e
B46: =ROW()-3 -> 43 | C46: ○ | K46: A_指標 | L46: 01_財務指標 | M46: 01_PL | N46: 販管費 | O46: 一般管理費 | P46: 一般管理費 | Q46: ー | R46: 売上原価に含まれない、会社運営にかかわる費用 | S46: 商標権使用料＋福利厚生費＋消耗品費＋修繕費＋通信費＋旅費交通費＋保険料＋租税公課＋賃借料＋接待交際費＋寄付金＋減価償却費＋電力費＋水道燃料費＋研究費＋社員募集費＋社員教育費＋調査費＋支払手数料＋雑費 | T46: 円 | U46: — | V46: — | W46: — | X46: — | Y46: 一般管理費明細、損益計算書（P/L） | Z46: — | AA46: — | AB46: — | AC46: — | AD46: 2月個別決算 | AH46: 1 | AJ46: 商標権使用料＋福利厚生費＋消耗品費＋修繕費＋通信費＋旅費交通費＋保険料＋租税公課＋酒税＋賃借料＋接待交際費＋寄付金＋減価償却費＋電力費＋水道燃料費＋研究費＋社員募集費＋社員教育費＋調査費＋支払手数料＋雑費 | AK46: 円 | AL46: e
B47: =ROW()-3 -> 44 | C47: ○ | K47: A_指標 | L47: 01_財務指標 | M47: 01_PL | N47: 販管費 | O47: 一般管理費率 | P47: 一般管理費率 | Q47: — | R47: 総売上高に対する一般管理費の割合 | S47: 一般管理費計 ÷ 総売上高 | T47: ％ | U47: — | V47: — | W47: — | X47: — | Y47: 収益性分析 | Z47: — | AA47: — | AB47: — | AC47: — | AD47: 2月個別決算 | AE47: ・％と金額どちらが指標になるかは要確認 | AH47: 1 | AI47: 売上に対する一般管理費の比率。分母が総売上高の場合と純売上高の場合がある。 | AJ47: 一般管理費 ÷ 総売上高 × 100 または 一般管理費 ÷ 純売上高 × 100 | AK47: ％ | AL47: e
B48: =ROW()-3 -> 45 | C48: ○ | K48: A_指標 | L48: 01_財務指標 | M48: 01_PL | N48: 販管費 | O48: 減価償却費 | P48: 減価償却費 | Q48: ー | R48: 有形固定資産（製造設備・機械・建物等）および無形固定資産の取得原価を耐用年数にわたって費用配分した金額。キャッシュの支出を伴わない非現金費用であり、PLツリー上では固定費の構成要素として原価関連・販管費に計上される。 | T48: 円 | U48: — | V48: 損益概況 | W48: — | X48: — | Y48: — | Z48: — | AA48: 損益共有MTG | AB48: — | AC48: — | AD48: — | AL48: e
B49: =ROW()-3 -> 46 | C49: ○ | K49: A_指標 | L49: 01_財務指標 | M49: 01_PL | N49: 利益・損失 | O49: 粗利 | P49: 粗利 | Q49: 売上総利益 | R49: 純売上高から売上原価（製造にかかる原材料費や工場の人件費など）を差し引いた利益。いわゆる「粗利」。 | S49: 純売上高 − 売上原価 | T49: 円 | U49: — | V49: — | W49: — | X49: ロッテ業績超簡易版 | Y49: 損益計算書（P/L）、本部KPI | Z49: — | AA49: — | AB49: — | AC49: ロッテ業績超簡易版 | AD49: 2月個別決算、本部KPI確認 | AH49: 1 | AI49: 純売上高から売上原価を差し引いた利益。いわゆる「粗利」。 | AJ49: 純売上高 − 売上原価 | AK49: 円 | AL49: e
B50: =ROW()-3 -> 47 | C50: ○ | K50: A_指標 | L50: 01_財務指標 | M50: 01_PL | N50: 利益・損失 | O50: EBITDA | P50: EBITDA | Q50: — | R50: 営業利益に売上原価と一般管理費内の減価償却費を加えた数値 | S50: 営業利益＋減価償却費（売上原価内＋一般管理費内） | T50: 円 | U50: — | V50: — | W50: — | X50: — | Y50: KK定例会長報告 | Z50: — | AA50: — | AB50: — | AC50: — | AD50: KK定例会長報告 | AE50: ・一般的なEBITDAは「経常利益＋支払利息＋減価償却費」とは異なりより保守的な算出式を利用 | AL50: e
B51: =ROW()-3 -> 48 | C51: ○ | K51: A_指標 | L51: 01_財務指標 | M51: 01_PL | N51: 利益・損失 | O51: 営業利益 | P51: 営業利益 | Q51: ー | R51: 売上総利益から物流費・人件費（工場以外）・広告宣伝費・その他一般管理費を引いた金額 | S51: 売上総利益 － （物流費＋人件費（工場以外）＋広告宣伝費＋その他一般経費） | T51: 円 | U51: — | V51: — | W51: — | X51: ロッテ業績超簡易版 | Y51: — | Z51: — | AA51: — | AB51: — | AC51: ロッテ業績超簡易版 | AD51: — | AH51: 1 | AI51: 売上総利益か販管費を引いた金額 | AJ51: 売上総利益 － 販管費 | AK51: 円 | AL51: e
B52: =ROW()-3 -> 49 | C52: ○ | K52: A_指標 | L52: 01_財務指標 | M52: 01_PL | N52: 利益・損失 | O52: 営業利益 | P52: 営業利益 | Q52: OP | R52: 売上から売上原価・販管費を控除した本業の利益。事業ベースの最終利益指標。 | S52: 純売 − 売上原価 − 販管費 | T52: 円 | U52: 営業政策, 月次品目別営業利益 | V52: 営業利益増減分析 | W52: — | X52: — | Y52: 収益企画社長報告、KK定例会長報告、個別決算、本部KPI | Z52: 営政, 全営 | AA52: プランニング実績,損益共有MTG | AB52: — | AC52: — | AD52: 収益企画社長報告, KK定例会長報告、2月個別決算、本部KPI確認 | AH52: 1 | AI52: 削除 | AL52: e
B53: =ROW()-3 -> 50 | C53: ○ | K53: A_指標 | L53: 01_財務指標 | M53: 01_PL | N53: 利益・損失 | O53: 営業利益率 | P53: 営業利益率 | Q53: ー | R53: 総売上に占める営業利益の割合 | S53: 営業利益 ÷ 総売上 | T53: ％ | U53: — | V53: — | W53: — | X53: — | Y53: 収益性分析 | Z53: — | AA53: — | AB53: — | AC53: — | AD53: 2月個別決算 | AE53: ・％と金額どちらが指標になるかは要確認 | AH53: 1 | AI53: 売上に対する営業利益の比率。分母が総売上高の場合と純売上高の場合がある。 | AJ53: 営業利益 ÷ 総売上高 × 100 または 営業利益 ÷ 純売上高 × 100 | AK53: ％ | AL53: e
B54: =ROW()-3 -> 51 | C54: ○ | K54: A_指標 | L54: 01_財務指標 | M54: 01_PL | N54: 利益・損失 | O54: 営業外収益 | P54: 営業外収益 | Q54: — | R54: 本業以外から得られる収益。受取利息・受取配当金・賃貸収入・為替差益・その他雑収入等を含む。 | S54: 受取利息 + 受取配当金 + 賃貸収入 + 為替差益 + 雑収入 | T54: 円 | U54: — | V54: — | W54: — | X54: — | Y54: 損益計算書（P/L） | Z54: — | AA54: — | AB54: — | AC54: — | AD54: 2月個別決算 | AH54: 1 | AK54: 円 | AL54: e
B55: =ROW()-3 -> 52 | C55: ○ | K55: A_指標 | L55: 01_財務指標 | M55: 01_PL | N55: 利益・損失 | O55: 営業外費用 | P55: 営業外費用 | Q55: — | R55: 本業以外で発生する費用。支払利息・売上割引・賃貸原価・為替差損等を含む。 | S55: 支払利息 +売上割引＋賃貸原価＋支払手数料＋ 為替差損 + その他雑損失 | T55: 円 | U55: — | V55: — | W55: — | X55: — | Y55: 損益計算書（P/L） | Z55: — | AA55: — | AB55: — | AC55: — | AD55: 2月個別決算 | AH55: 1 | AK55: 円 | AL55: e
B56: =ROW()-3 -> 53 | K56: A_指標 | L56: 01_財務指標 | M56: 01_PL | N56: 利益・損失 | O56: 総売比利益率 | P56: 総売比利益率 | Q56: — | R56: 総売上に対する営業利益率。営業政策表で多用される独自表現。 | S56: 営業利益 ÷ 総売上高 × 100 | T56: % | U56: 営業政策の予算表 | V56: — | W56: — | X56: — | Y56: — | Z56: 営政 | AA56: — | AB56: — | AC56: — | AD56: — | AL56: e
B57: =ROW()-3 -> 54 | C57: ○ | K57: A_指標 | L57: 01_財務指標 | M57: 01_PL | N57: 利益・損失 | O57: 経常利益 | P57: 経常利益 | Q57: — | R57: 営業利益に営業外損益（金利・為替等）を加減した利益。 | S57: 営業利益 ± 営業外損益 | T57: 円 | U57: 月次営業利益（全営） | V57: — | W57: — | X57: — | Y57: KK定例会長報告、損益計算書 | Z57: 全営 | AA57: — | AB57: — | AC57: — | AD57: KK定例会長報告、2月個別決算 | AH57: 1 | AJ57: 営業利益＋営業外収益－営業外費用 | AK57: 円 | AL57: e
B58: =ROW()-3 -> 55 | C58: ○ | K58: A_指標 | L58: 01_財務指標 | M58: 01_PL | N58: 利益・損失 | O58: 限界利益 | P58: 限界利益 | Q58: — | R58: 売上から変動費を引いた利益。商品別販売戦略の主軸KPI（限界利益率）。 | S58: 売上 − 変動費 | T58: 円 | U58: 商品別限界利益率分析（営業政策に多数登場） | V58: 損益概況 | W58: — | X58: SCM会議（商品別限界利益率分析・VC改革検討）, S&OP分析（SCM効率化KGI） | Y58: KK定例会長報告,収益企画社長報告（PLツリー） | Z58: 営政, 全営 | AA58: プランニング実績,損益共有MTG | AB58: — | AC58: SCM会議, 第3回SCM議事録, 第1回SCM議事録, 第2回SCM議事録, S&OP事例 | AD58: KK定例会長報告,収益企画社長報告 | AE58: 2025/5/12 SCM会議議事録にて、「営業利益から固定費を除いた限界利益率は～」というご発言があり別定義がないかはご確認いただきたい | AH58: 1 | AI58: 総売上高から変動費を引いた利益。 | AJ58: 総売上高 − 変動費 | AK58: 円 | AL58: e
B59: =ROW()-3 -> 56 | C59: ○ | K59: A_指標 | L59: 01_財務指標 | M59: 01_PL | N59: 利益・損失 | O59: 限界利益率 | P59: 限界利益率 | Q59: ー | R59: 総売上高に占める限界利益の割合 | S59: 限界利益 ÷ 総売上 × 100 | T59: % | U59: — | V59: — | W59: — | X59: SCM会議（商品別限界利益率分析・VC改革検討） | Y59: 本部KPI | Z59: — | AA59: — | AB59: — | AC59: 第1回SCM議事録 | AD59: 本部KPI確認 | AH59: 1 | AI59: 売上に対する限界利益の比率。分母が総売上高の場合と純売上高の場合がある。 | AJ59: 限界利益 ÷ 総売上高 × 100 または 限界利益 ÷ 純売上高 × 100 | AL59: e
K60: A_指標 | L60: 01_財務指標 | M60: 01_PL | N60: 利益・損失 | O60: 変動費 | AH60: 1 | AK60: 円
K61: A_指標 | L61: 01_財務指標 | M61: 01_PL | N61: 利益・損失 | O61: 固定費 | AH61: 1 | AK61: 円
B62: =ROW()-3 -> 59 | C62: ○ | K62: A_指標 | L62: 01_財務指標 | M62: 02_BS | N62: 資産 | O62: 棚卸資産 | P62: 棚卸資産 | Q62: 在庫金額 | R62: 製品・商品・仕掛品・原材料の合計在庫金額（財務BS上の表示）。 | S62: 製品在庫 + 商品在庫 + 仕掛品 + 原材料 | T62: 円 | U62: — | V62: — | W62: — | X62: — | Y62: KK定例会長報告 | Z62: — | AA62: — | AB62: — | AC62: — | AD62: KK定例会長報告 | AF62: 経理 | AL62: e
B63: =ROW()-3 -> 60 | C63: ○ | K63: A_指標 | L63: 01_財務指標 | M63: 02_BS | N63: 資産 | O63: 売上債権 | P63: 売上債権 | Q63: 売掛金・受取手形 | R63: 売掛金と受取手形の合計。回収前の売上残高。懸念債権を含む金額。 | S63: 売掛金 + 受取手形 | T63: 円 | U63: — | V63: — | W63: — | X63: — | Y63: KK定例会長報告 | Z63: — | AA63: — | AB63: — | AC63: — | AD63: KK定例会長報告 | AE63: ・懸念債権を含む | AF63: 経理 | AL63: e
B64: =ROW()-3 -> 61 | C64: ○ | K64: A_指標 | L64: 01_財務指標 | M64: 02_BS | N64: 資産 | O64: 債権回転日数 | P64: 債権回転日数 | Q64: — | R64: 売上債権が何日で回収されるかを示す指標。日数が短いほど資金回収が早い。 | S64: 売上債権 ÷ 売上高 × 365（または月末残÷月次売上×30） | T64: 日 | U64: — | V64: — | W64: — | X64: — | Y64: KK定例会長報告 | Z64: — | AA64: — | AB64: — | AC64: — | AD64: KK定例会長報告 | AE64: ・KK定例会長報告上で、売上債権÷売上高×365で計算すると表情の債権回転日数とは不一致となる為、数式再確認が必要 | AF64: 経理 | AH64: 1 | AJ64: 売上債権÷当月単月の純売上（税込）×当月日数 税は菓子・アイスは純売上×1.08、ウエルネスは純売上×1.1 | AK64: 日 | AL64: e
B65: =ROW()-3 -> 62 | C65: ○ | K65: A_指標 | L65: 01_財務指標 | M65: 02_BS | N65: 負債 | O65: 負債比率 | P65: 負債比率 | Q65: — | R65: 純資産に対する負債（流動負債・固定負債） | S65: （流動負債＋固定負債）/純資産 | T65: ％ | U65: — | V65: — | W65: — | X65: — | Y65: KK定例会長報告 | Z65: — | AA65: — | AB65: — | AC65: — | AD65: KK定例会長報告 | AF65: 経理 | AL65: e
B66: =ROW()-3 -> 63 | C66: ○ | K66: A_指標 | L66: 01_財務指標 | M66: 02_BS | N66: 負債 | O66: 流動比率 | P66: 流動比率 | Q66: — | R66: 流動負債に対する流動資産の割合 | S66: 流動資産/流動負債 | T66: ％ | U66: — | V66: — | W66: — | X66: — | Y66: KK定例会長報告 | Z66: — | AA66: — | AB66: — | AC66: — | AD66: KK定例会長報告 | AF66: 経理 | AL66: e
B67: =ROW()-3 -> 64 | C67: ○ | K67: A_指標 | L67: 01_財務指標 | M67: 02_BS | N67: 負債 | O67: 借入金 | P67: 借入金 | Q67: — | R67: 金融機関、グループ会社等からの借入金額 | T67: 円 | U67: — | V67: — | W67: — | X67: — | Y67: KK定例会長報告 | Z67: — | AA67: — | AB67: — | AC67: — | AD67: KK定例会長報告 | AF67: 経理 | AH67: 1 | AI67: 削除 | AL67: e
B68: =ROW()-3 -> 65 | K68: A_指標 | L68: 01_財務指標 | M68: 02_BS | N68: 負債 | O68: DEレシオ | P68: DEレシオ | Q68: — | R68: 純資産に対する借入金の割合 | S68: （短期借入金＋長期借入金）/純資産 | T68: ％ | U68: — | V68: — | W68: — | X68: — | Y68: KK定例会長報告 | Z68: — | AA68: — | AB68: — | AC68: — | AD68: KK定例会長報告 | AL68: e
B69: =ROW()-3 -> 66 | K69: A_指標 | L69: 01_財務指標 | M69: 02_BS | N69: 負債 | O69: ネットDEレシオ | P69: ネットDEレシオ | Q69: — | R69: 純資産に対する実借入金の割合 | S69: （短期借入金＋長期借入金）ー現預金／純資産 | T69: ％ | U69: — | V69: — | W69: — | X69: — | Y69: KK定例会長報告 | Z69: — | AA69: — | AB69: — | AC69: — | AD69: KK定例会長報告 | AL69: e
B70: =ROW()-3 -> 67 | K70: A_指標 | L70: 01_財務指標 | M70: 02_BS | N70: 負債 | O70: 債務保証 | P70: 債務保証 | Q70: — | R70: ㈱ロッテが海外子会社（ベトナム・インドネシア・タイ・台湾）および国内関連会社（Dari K）の金融機関からの借入に対して保証人となる信用供与。借入金残高を上回る保証枠を設定しており、差引（保証額−借入残高）が未使用枠にあたる。みずほ・三菱UFJ・三井住友等の複数銀行に分散して設定される。 | T70: 円 | U70: — | V70: — | W70: — | X70: — | Y70: KK定例会長報告 | Z70: — | AA70: — | AB70: — | AC70: — | AD70: KK定例会長報告 | AL70: e
B71: =ROW()-3 -> 68 | K71: A_指標 | L71: 01_財務指標 | M71: 02_BS | N71: 負債 | O71: 実借入額 | P71: 実借入額 | Q71: — | R71: 借入金から現預金残高を除いた額 | S71: 借入金-現預金 | T71: 円 | U71: — | V71: — | W71: — | X71: — | Y71: KK定例会長報告 | Z71: — | AA71: — | AB71: — | AC71: — | AD71: KK定例会長報告 | AL71: e
B72: =ROW()-3 -> 69 | K72: A_指標 | L72: 02_業績管理・オペレーション指標 | M72: 01_商品開発 | N72: 利益項目 | O72: 品目別営業利益（純売ベース） | P72: 品目別営業利益（純売ベース） | Q72: 品目別営利 | R72: 純売上（返品・値引控除後の売上）を分母としてブランド・品目ごとに算出した営業利益。営業利益の率計算に用いる。品目間の収益性比較や予算管理の基準となる。 | S72: 品目別営業利益率 = 品目別営業利益 ÷ 品目別純売上 × 100 | T72: 円, % | U72: 品目別営業利益帳票, 月次全国営業会議資料 | V72: — | W72: — | X72: — | Y72: — | Z72: 全営, 営政 | AA72: — | AB72: — | AC72: — | AD72: — | AL72: e
B73: =ROW()-3 -> 70 | K73: A_指標 | L73: 02_業績管理・オペレーション指標 | M73: 01_商品開発 | N73: その他 | O73: 研究開発業務構成比 | P73: 研究開発業務構成比 | Q73: ー | S73: 研究開発業務時間 ÷ 総労働時間 × 100 | T73: ％ | U73: — | V73: — | W73: — | X73: — | Y73: 本部KPI | Z73: — | AA73: — | AB73: — | AC73: — | AD73: 本部KPI確認 | AL73: e
B74: =ROW()-3 -> 71 | K74: A_指標 | L74: 02_業績管理・オペレーション指標 | M74: 02_生販在 | N74: 生産 | O74: 生産 | P74: 生産 | Q74: ー | R74: 生販在計画表における、生産量 | T74: CS | U74: — | V74: — | W74: — | X74: 生販在計画表 | Y74: — | Z74: — | AA74: — | AB74: — | AC74: 月末キャン | AD74: — | AL74: e
B75: =ROW()-3 -> 72 | K75: A_指標 | L75: 02_業績管理・オペレーション指標 | M75: 02_生販在 | N75: 生産 | O75: 生産回答 | P75: 生産回答 | Q75: — | R75: 月次工程表において、生産部門が需給部门からの生産要請に対して回答した生産予定数量。「計画」と区別して使われ、ライン・品番ごとに設定される。 | T75: CS | U75: — | V75: — | W75: 包装工程1課（生産計画表） | X75: — | Y75: — | Z75: — | AA75: — | AB75: 包装工程1課 | AC75: — | AD75: — | AL75: e
B76: =ROW()-3 -> 73 | K76: A_指標 | L76: 02_業績管理・オペレーション指標 | M76: 02_生販在 | N76: 生産 | O76: 生産実績 | P76: 生産実績 | Q76: — | R76: 月次工程表において、生産部門が生産した実績 | T76: CS | U76: — | V76: — | W76: 包装工程1課（生産計画表） | X76: — | Y76: — | Z76: — | AA76: — | AB76: 包装工程1課 | AC76: — | AD76: — | AL76: e
B77: =ROW()-3 -> 74 | K77: A_指標 | L77: 02_業績管理・オペレーション指標 | M77: 02_生販在 | N77: 生産 | O77: 使用 | P77: 使用 | Q77: ー | R77: 生産計画書において、当月の生産に実際に投入・消費された半製品の数量。前月繰越と翌月繰越の差分として算出され、当月の実消費量を示す。 | S77: 前月繰越 − 翌月繰越 | T77: ㎏ | U77: — | V77: — | W77: — | X77: 生産計画 | Y77: — | Z77: — | AA77: — | AB77: — | AC77: 菓子アイス月間 | AD77: — | AL77: e
B78: =ROW()-3 -> 75 | K78: A_指標 | L78: 02_業績管理・オペレーション指標 | M78: 02_生販在 | N78: 生産 | O78: ケース数 | P78: ケース数 | Q78: ー | R78: 品目の数量の単位で、個数をケース換算しCS数単位で表した数量。 | S78: 数量 ÷ 入り数 | T78: CS | U78: — | V78: — | W78: — | X78: 生産計画 | Y78: — | Z78: — | AA78: — | AB78: — | AC78: 菓子アイス月間 | AD78: — | AL78: e
B79: =ROW()-3 -> 76 | C79: ○ | K79: A_指標 | L79: 02_業績管理・オペレーション指標 | M79: 02_生販在 | N79: 販売 | O79: 売上 | P79: 売上 | Q79: メーカー別売上、販売額 | R79: メーカー別の推定売上高。海外売上および内部取引を控除した国内市販用の販売金額。各月の着地（実績確定）ベースで集計され、月次および年度累計（4月〜3月）で管理される。 | S79: 推定売上高 − 海外売上 − 内部取引額 | T79: 円 | U79: — | V79: マーケットシェア分析 | W79: — | X79: — | Y79: — | Z79: — | AA79: プランニング実績,損益共有MTG,マーケ生販会議 | AB79: — | AC79: — | AD79: — | AF79: マーケ | AL79: e
B80: =ROW()-3 -> 77 | K80: A_指標 | L80: 02_業績管理・オペレーション指標 | M80: 02_生販在 | N80: 販売 | O80: 営業概況 | P80: 営業概況 | Q80: ー | R80: 販売振り返りMTGで使用される営業の売上 | T80: 円 | U80: — | V80: — | W80: — | X80: 販売実績・見込みすり合わせ | Y80: — | Z80: — | AA80: — | AB80: — | AC80: 振返アイス,振返ガム,振返チョコ,振返キャン,振返ビス | AD80: — | AE80: ・営業概況は売上高金額のようだが、それが総売上高なのか純売上高なのか要確認 | AL80: e
B81: =ROW()-3 -> 78 | K81: A_指標 | L81: 02_業績管理・オペレーション指標 | M81: 02_生販在 | N81: 販売 | O81: 概況精度 | P81: 概況精度 | Q81: ー | R81: 統括支店が提出した概況（需要予測）の精度を示す指標。倉入実績をAnaplan倉入計画と比較し、概況提出締切日時点での「1ヵ月前」の計画値がどれだけ実績に近かったかを測る。組織評価における評価指標の一つで、菓子・アイスそれぞれウェイト10%（合計20%）で配点される。広域流通のみ「店出実績/Anaplan店出計画」を基準として算出。 | S81: 倉入実績 ÷ Anaplan倉入計画（概況提出締切日時点の1ヵ月前計画値）※広域流通は店出実績 ÷ Anaplan店出計画 | T81: 倍 | U81: 支店別評価 | V81: — | W81: — | X81: — | Y81: — | Z81: 全営 | AA81: — | AB81: — | AC81: — | AD81: — | AL81: e
B82: =ROW()-3 -> 79 | K82: A_指標 | L82: 02_業績管理・オペレーション指標 | M82: 02_生販在 | N82: 販売 | O82: 出荷実績 | P82: 出荷実績 | Q82: ー | R82: 当該年度累計における製品の出荷金額の確定値。予算・前年実績と対比する形で管理され、カテゴリ（ガム・チョコレート・キャンディ・ビスケット・市販用アイス・業務用アイス）別および菓子計・アイス計・菓子アイス計の集計単位で把握される。 | T82: 円 | U82: — | V82: マーケットシェア分析 | W82: — | X82: — | Y82: — | Z82: — | AA82: プランニング実績 | AB82: — | AC82: — | AD82: — | AE82: ・売上との違い要確認 | AL82: e
B83: =ROW()-3 -> 80 | C83: ○ | K83: A_指標 | L83: 02_業績管理・オペレーション指標 | M83: 02_生販在 | N83: 販売 | O83: 販売 | P83: 販売 | Q83: ー | R83: 生販在計画表における、販売量 | T83: CS | U83: — | V83: — | W83: — | X83: 生販在計画表 | Y83: — | Z83: — | AA83: — | AB83: — | AC83: 月末キャン | AD83: — | AE83: ・何を基準として”販売”と、みなしているのか（出荷？どこ向け？）要確認 | AF83: SCM | AH83: 1 | AI83: ロッテから得意先に出荷し、売掛金が発生する売上。 生販在計画表における、販売金額及び数量の計画 | AJ83: 仕切(卸出荷)単価(pc)×数量(pc)、 数量(CS) | AK83: 円、CS | AL83: e
B84: =ROW()-3 -> 81 | K84: A_指標 | L84: 02_業績管理・オペレーション指標 | M84: 02_生販在 | N84: 販売 | O84: チャンスロス | P84: チャンスロス | Q84: 販売機会損失 | R84: 欠品や在庫不足により本来得られたはずの売上が失われること。SCM部門の主要KPIである欠品率と連動して管理される。 | T84: 円 | U84: — | V84: — | W84: — | X84: SCM本部KPI（チャンスロス削減） | Y84: 経営会議（SCM本部KPI） | Z84: — | AA84: — | AB84: — | AC84: SCM本部会議全体 | AD84: 本部KPI確認 | AL84: e
B85: =ROW()-3 -> 82 | K85: A_指標 | L85: 02_業績管理・オペレーション指標 | M85: 02_生販在 | N85: 販売 | O85: 1か月前見込比 | P85: 1か月前見込比 | Q85: — | R85: 販売振り返りミーティングで使用する精度指標。1か月前に立案されたSCM見込みまたは営業概況に対する当月実績の比率。 | S85: 当月実績 ÷ 1か月前見込み × 100 | T85: % | U85: — | V85: — | W85: — | X85: 各カテゴリ振り返りMTG（アイス・ガム・チョコ・ビス・キャン） | Y85: — | Z85: — | AA85: — | AB85: — | AC85: 振返アイス, 振返ガム, 振返キャン, 振返チョコ, 振返ビス | AD85: — | AL85: e
B86: =ROW()-3 -> 83 | C86: ○ | K86: A_指標 | L86: 02_業績管理・オペレーション指標 | M86: 02_生販在 | N86: 販売 | O86: SCM見込み | P86: SCM見込み | Q86: SCM見込 | R86: SCM需給部が独自に立案する販売見込み。生販会議資料・振り返りミーティングで営業見込みと並べて比較される。生産計画の基礎となる。 | T86: 円, CS | U86: — | V86: — | W86: — | X86: 生販会議（販売振り返り・次月見込）、各カテゴリ振り返りMTG, SCM本部会議（販売見込み・前回生販会議振り返り） | Y86: — | Z86: — | AA86: — | AB86: — | AC86: 生販会議, 振返アイス, 振返ガム, 振返キャン, 振返チョコ, 振返ビス, SCM本部会議全体, SCM会議 | AD86: — | AF86: SCM | AL86: e
B87: =ROW()-3 -> 84 | K87: A_指標 | L87: 02_業績管理・オペレーション指標 | M87: 02_生販在 | N87: 販売 | O87: 要求 | P87: 要求 | Q87: ー | R87: 各エリアの営業担当が当該期間に販売目標として本社に申請した出荷数量。エリア別・品番別（通常・大袋）に設定され、生産・在庫計画の基準値となる。実際の出荷計（出荷計）と対比することで進捗（出荷率）を把握する。 | T87: CS | U87: 販売進捗 | V87: — | W87: — | X87: — | Y87: — | Z87: 全営 | AA87: — | AB87: — | AC87: — | AD87: — | AL87: e
B88: =ROW()-3 -> 85 | K88: A_指標 | L88: 02_業績管理・オペレーション指標 | M88: 02_生販在 | N88: 販売 | O88: 一斉出荷 | P88: 一斉出荷 | Q88: 一斉, 一斉要求 | R88: 新商品の発売日（または初回発送日）に合わせて行う最初の出荷とその際の要求数量。「一斉出荷率」は一斉要求に対する一斉出荷の充足率で、初回供給力を示すKPI。 | S88: 一斉出荷率 ＝ 一斉出荷金額（またはケース数） ÷ 一斉要求金額（またはケース数） × 100 | T88: %、円、CS | U88: — | V88: — | W88: — | X88: SCM本部会議（新商品要求精度確認）、Anaplan精度検証、新商品要求精度確認ツール | Y88: — | Z88: — | AA88: — | AB88: — | AC88: SCM本部会議全体, Anaplan精度検証 | AD88: — | AL88: e
B89: =ROW()-3 -> 86 | K89: A_指標 | L89: 02_業績管理・オペレーション指標 | M89: 02_生販在 | N89: 販売 | O89: 月間出荷 | P89: 月間出荷 | Q89: 月間, 月間要求 | R89: 対象月末までの累計出荷数量・金額とその累計要求数量。「月間出荷率」は月間要求に対する月間出荷の充足率で、月間の供給完遂度を示すKPI。 | S89: 月間出荷率 ＝ 月間出荷金額（またはケース数） ÷ 月間要求金額（またはケース数） × 100 | T89: %、円、CS | U89: — | V89: 新商品マーケット分析 | W89: — | X89: SCM本部会議（新商品要求精度確認）、Anaplan精度検証、新商品要求精度確認ツール | Y89: — | Z89: — | AA89: アジア恋ナレッジ | AB89: — | AC89: SCM本部会議全体, Anaplan精度検証 | AD89: — | AL89: e
B90: =ROW()-3 -> 87 | K90: A_指標 | L90: 02_業績管理・オペレーション指標 | M90: 02_生販在 | N90: 在庫 | O90: 前月繰越 | P90: 前月繰越 | Q90: ー | R90: 生産計画書において、前月末時点で使用されずに繰り越された半製品の在庫量。当月の使用可能数量を把握するための起点値として管理される。 | T90: ㎏ | U90: — | V90: — | W90: — | X90: 生産計画 | Y90: — | Z90: — | AA90: — | AB90: — | AC90: 菓子アイス月間 | AD90: — | AL90: e
B91: =ROW()-3 -> 88 | K91: A_指標 | L91: 02_業績管理・オペレーション指標 | M91: 02_生販在 | N91: 在庫 | O91: 翌月繰越 | P91: 翌月繰越 | Q91: ー | R91: 生産計画書において、当月末時点で未使用のまま翌月へ繰り越される原材料・半製品の在庫量。翌月の前月繰越値として引き継がれる。マイナス値（▲）の場合は在庫不足・過消費を示す。 | S91: 前月繰越 − 使用 | T91: ㎏ | U91: — | V91: — | W91: — | X91: 生産計画 | Y91: — | Z91: — | AA91: — | AB91: — | AC91: 菓子アイス月間 | AD91: — | AL91: e
B92: =ROW()-3 -> 89 | K92: A_指標 | L92: 02_業績管理・オペレーション指標 | M92: 02_生販在 | N92: 在庫 | O92: 欠品率 | P92: 欠品率 | Q92: — | R92: 受注に対して在庫不足により出荷できなかった比率。全受注数に対して欠品（出荷不能）となった件数または金額の比率で、地区別・全国平均で管理される。SCM需給部が月次で管理・報告する在庫管理の主要KPI。社会課題取組フィの対象KPIの一つ。 | S92: 欠品件数（または金額） ÷ 総受注件数（または金額） × 100 | T92: % | U92: — | V92: — | W92: — | X92: 欠品実績管理（月次報）、地区別モニタリング、支払い報告MTG（在庫状況スライド）, SCM会議（KPI管理）, SCM本部会議（新商品出荷率・欠品率確認）, 需給部月次管理（在庫実績・欠品実績） | Y92: 経営会議（SCM本部KPI）、KK定例会長報告、本部KPI | Z92: — | AA92: — | AB92: — | AC92: 月次報, 支払報告需給, SCM会議, 第3回SCM議事録, 第2回SCM議事録, SCM本部会議全体, 4月SCM需給、SCM大会 | AD92: 本部KPI確認, KK定例会長報告 | AL92: e
B93: =ROW()-3 -> 90 | K93: A_指標 | L93: 02_業績管理・オペレーション指標 | M93: 02_生販在 | N93: 在庫 | O93: 現行 | P93: 現行 | Q93: ー | R93: 生販在計画表において、直近の確定済み在庫数量を示す列計画の起点となる実績ベースの在庫数。以降の生産・販売計画の算出基準として参照される。 | T93: CS | U93: — | V93: — | W93: — | X93: 業務用アイス生販在計画表 | Y93: — | Z93: — | AA93: — | AB93: — | AC93: 月末事前アイス業,月末事前アイス市 | AD93: — | AL93: e
B94: =ROW()-3 -> 91 | C94: ○ | K94: A_指標 | L94: 02_業績管理・オペレーション指標 | M94: 02_生販在 | N94: 在庫 | O94: 在庫 | P94: 在庫 | Q94: ー | R94: 生販在計画表における、在庫量 | T94: CS | U94: — | V94: — | W94: — | X94: 生販在計画表 | Y94: — | Z94: — | AA94: — | AB94: — | AC94: 月末キャン | AD94: — | AF94: SCM | AH94: 1 | AI94: 生販在計画表における、在庫量 →不良在庫も含む「在菅日報」の在庫金額・ケース数が基準 | AJ94: 「在菅日報」の在庫金額・ケース数が基準 https://docs.google.com/spreadsheets/d/14zti9ZT_FWpqFM_sWiXqSvBnFyqmYGgj/edit?gid=1287938920#gid=1287938920 | AK94: 円・CS | AL94: e
B95: =ROW()-3 -> 92 | C95: ○ | K95: A_指標 | L95: 02_業績管理・オペレーション指標 | M95: 02_生販在 | N95: 在庫 | O95: 末在庫 | P95: 末在庫 | Q95: ー | R95: 生販在計画表における、月末在庫量 | T95: ー | U95: — | V95: — | W95: — | X95: — | Y95: — | Z95: — | AA95: — | AB95: — | AC95: — | AD95: — | AF95: SCM | AH95: 1 | AI95: 生販在計画表における、月末在庫量 | AJ95: 前月末在庫＋当月生産数量ｰ当月販売数量 | AK95: 円・CS | AL95: e
B96: =ROW()-3 -> 93 | C96: ○ | K96: A_指標 | L96: 02_業績管理・オペレーション指標 | M96: 02_生販在 | N96: 在庫 | O96: 在庫金額 | P96: 在庫金額 | Q96: 在庫 | R96: 製品・商品・仕掛品・原材料の合計在庫金額 | S96: 製品在庫 + 商品在庫 + 仕掛品 + 原材料 | T96: 円 | U96: — | V96: — | W96: — | X96: — | Y96: KK定例会長報告 | Z96: — | AA96: — | AB96: — | AC96: — | AD96: KK定例会長報告 | AF96: SCM | AH96: 1 | AI96: 会長報告としては正しいが、SCM本部での生販在表の在庫金額は製品と商品のみ（仕掛品・原材料除く） | AJ96: 商品＋製品（完成品のみ） | AK96: 円 | AL96: e
B97: =ROW()-3 -> 94 | K97: A_指標 | L97: 02_業績管理・オペレーション指標 | M97: 02_生販在 | N97: 在庫 | O97: 引当可能在庫 | P97: 引当可能在庫 | Q97: — | R97: 受注に対して引き当て可能な在庫量。実在庫から引当済・移動中・品質保留分を除いた有効在庫。 | S97: 実在庫 − 引当済数量 − 積送中在庫 等 | T97: CS | U97: — | V97: — | W97: — | X97: SAP受注照会・在庫管理（需給部） | Y97: — | Z97: — | AA97: — | AB97: — | AC97: 0330-0423受注データ | AD97: — | AL97: e
B98: =ROW()-3 -> 95 | C98: ○ | K98: A_指標 | L98: 02_業績管理・オペレーション指標 | M98: 02_生販在 | N98: 在庫 | O98: 在庫回転日数 | P98: 在庫回転日数 | Q98: — | R98: 棚卸金額が何日分の売上に相当するかを示す指標。小さいほど在庫効率が高い。SCMの効率性KGIの一つ。 | S98: 棚卸金額 ÷ 売上高 × 365（日） | T98: 日 | U98: — | V98: — | W98: — | X98: SCM効率化指標管理、S&OP分析 | Y98: 経営KPI、KK定例会長報告 | Z98: — | AA98: — | AB98: — | AC98: S&OP事例 | AD98: KK定例会長報告 | AE98: ・KK定例会長報告では、在庫金額÷総売上高or純売上高×365でも記載されている数値と一致しない | AF98: 経理 | AH98: 1 | AL98: e
B99: =ROW()-3 -> 96 | C99: ○ | K99: A_指標 | L99: 02_業績管理・オペレーション指標 | M99: 02_生販在 | N99: 在庫 | O99: 在庫日数 | P99: 在庫日数 | Q99: 日数, 在庫率 | R99: 現在の在庫数量を、当月の日平均販売数量で割った日数。在庫の過不足を判断するための指標。生販在計画表の各月の在庫欄に隣接して表示される。 | S99: 在庫日数 = 月末在庫 ÷ (月間販売数 ÷ 月日数) | T99: 日 | U99: — | V99: — | W99: — | X99: 生販在計画表（月別在庫管理）、月末調整会議での在庫水準評価, SCM本部会議（品目別在庫日数確認） | Y99: — | Z99: — | AA99: — | AB99: — | AC99: 月末事前ガム, 月末事前キャン, 月末事前ビス, 月末事前チョコ, 月末事前アイス業, 月末事前アイス市, SCM本部会議全体 | AD99: — | AF99: SCM | AH99: 1 | AI99: 現在の在庫数量を、当月の日平均販売数量で割った日数。在庫の過不足を判断するための指標。生販在計画表の各月の在庫欄に隣接して表示される。 →生販在表では菓子は在庫日数で表示し、アイスは在庫率で表示されているのが実態 | AJ99: 在庫日数 = 月末在庫 ÷ (翌月販売数 ÷ 月日数) 在庫率＝月末在庫 ÷ 翌月販売数 | AK99: 在庫日数：日 在庫率：％ | AL99: e
B100: =ROW()-3 -> 97 | K100: A_指標 | L100: 02_業績管理・オペレーション指標 | M100: 02_生販在 | N100: 在庫 | O100: 在庫率 | P100: 在庫率 | Q100: — | R100: 翌月販売実績に対する当月末在庫の比率。 | S100: 当月末在庫/翌月販売実績 | T100: % | U100: — | V100: — | W100: — | X100: 需給部月次報告（月末在庫率：菓子・アイス別管理）、SCM本部KPI | Y100: — | Z100: — | AA100: — | AB100: — | AC100: 4月SCM需給、SCM大会、SCM会議, 第2回SCM会議 | AD100: — | AL100: e
B101: =ROW()-3 -> 98 | K101: A_指標 | L101: 02_業績管理・オペレーション指標 | M101: 02_生販在 | N101: 在庫 | O101: 仕掛品在庫 | P101: 仕掛品在庫 | Q101: 仕掛品 | R101: 製造途中で完成品になっていない中間製品の在庫。日分で管理される。 | T101: 円, 日分 | U101: — | V101: — | W101: 会長報告（月次在庫報告） | X101: — | Y101: — | Z101: — | AA101: — | AB101: 会長報告生産3月 | AC101: — | AD101: — | AL101: e
...

Sheet マスタ_用語辞書
B2: No | C2: 経営ダッシュボード | D2: 確認部門 | E2: 分科① | F2: 分科② | G2: 分科③ | H2: 分科④ | I2: 分科⑤ | J2: 分科⑥ | K2: 指標大分類 | L2: 指標タイプ Lv.1 | M2: 指標タイプ Lv.2 | N2: 指標タイプ Lv.3 | O2: 今後の正式名称 | P2: 現時点の資料での出現用語 | Q2: 略称/同義語 | R2: 定義 | S2: 算出式 / 構造 | T2: 単位 | U2: 使用シーン / 主な帳票 | Z2: 出典 | AH2: 要修正フラグ | AI2: 修正後 | AL2: e
U3: 営業 | V3: マーケ | W3: 生産 | X3: SCM | Y3: 経営戦略 ・収益企画 | Z3: 営業 | AA3: マーケ | AB3: 生産 | AC3: SCM | AD3: 経営戦略 ・収益企画 | AE3: 備考 | AF3: 確認対象部門 | AG3: 収益企画部担当者 | AH3: ドラフトに誤りがある場合1を記載 | AI3: 定義 | AJ3: 算出式 / 構造 | AK3: 単位 | AL3: e
B4: =ROW()-3 -> 1 | K4: B_マスタ | L4: 01_商品・ブランドマスタ | O4: 21963 2袋トッポ | P4: 21963 2袋トッポ | Q4: ー | R4: トッポブランドの2袋パック品を集計した小計。 | S4: トッポ（各品） | U4: — | V4: — | W4: — | X4: チョコレート生産計画表 | Y4: — | Z4: — | AA4: — | AB4: — | AC4: 月末事前チョコ, 協力チョコ, 滋賀チョコ, KYチョコ | AD4: — | AL4: e
B5: =ROW()-3 -> 2 | K5: B_マスタ | L5: 01_商品・ブランドマスタ | O5: 22351クランキービッツ | P5: 22351クランキービッツ | Q5: ー | R5: クランキービッツブランドの全品目を集計した小計。 | S5: クランキービッツ ＋ クランキービッツ'26 | U5: — | V5: — | W5: — | X5: チョコレート生産計画表 | Y5: — | Z5: — | AA5: — | AB5: — | AC5: 月末事前チョコ, 協力チョコ, 滋賀チョコ, KYチョコ | AD5: — | AL5: e
B6: =ROW()-3 -> 3 | K6: B_マスタ | L6: 01_商品・ブランドマスタ | O6: 35Gガーナミルク | P6: 35Gガーナミルク | Q6: ー | R6: 35g規格のガーナミルクチョコレート品を集計した小計。 | S6: 35Gガーナミルク | U6: — | V6: — | W6: — | X6: チョコレート生産計画表 | Y6: — | Z6: — | AA6: — | AB6: — | AC6: 月末事前チョコ, 協力チョコ, 滋賀チョコ, KYチョコ | AD6: — | AL6: e
B7: =ROW()-3 -> 4 | C7: ○ | K7: B_マスタ | L7: 01_商品・ブランドマスタ | O7: HAPPY HAPPY | P7: HAPPY HAPPY | Q7: ー | R7: HAPPY HAPPYブランドの全品目を集計した小計。 | S7: HAPPY HAPPY SP | U7: — | V7: — | W7: — | X7: チョコレート生産計画表 | Y7: — | Z7: — | AA7: — | AB7: — | AC7: 月末事前チョコ, 協力チョコ, 滋賀チョコ, KYチョコ | AD7: — | AL7: e
B8: =ROW()-3 -> 5 | C8: ○ | K8: B_マスタ | L8: 01_商品・ブランドマスタ | O8: LATTE MILKグループ | P8: LATTE MILK | Q8: ー | R8: LATTE MILKブランドの全品目を集計した小計。 | S8: LATTE MILK ＋ LATTE MILK（ポケモン） ＋ LATTE MILK'26（外装変更） ＋ LATTE MILK'26減量 ＋ LATTE MILK大容量 | U8: — | V8: — | W8: — | X8: チョコレート生産計画表 | Y8: — | Z8: — | AA8: — | AB8: — | AC8: 月末事前チョコ, 協力チョコ, 滋賀チョコ, KYチョコ | AD8: — | AL8: e
B9: =ROW()-3 -> 6 | C9: ○ | K9: B_マスタ | L9: 01_商品・ブランドマスタ | O9: LATTE MILK | P9: LATTE MILK | Q9: ラテミルク | R9: 2026年4月発売のロッテのチョコレート商品。発売初月で1,050百万円の売上貢献。チョコレートカテゴリーの新規ブランドとして年度実績に寄与。 | T9: 円 | U9: チョコ新商品提案, 月次実績振り返り | V9: — | W9: — | X9: — | Y9: — | Z9: 全営 | AA9: — | AB9: — | AC9: — | AD9: — | AL9: e
B10: =ROW()-3 -> 7 | C10: ○ | K10: B_マスタ | L10: 01_商品・ブランドマスタ | O10: アーモンド | P10: アーモンド | Q10: ー | R10: アーモンドチョコレートブランド全品（浦和・九州工場合算）の最上位集計行。 | S10: アーモンド ＋ アーモンド準チョコ化25/9 ＋ アーモンド'26（浦和分＋九州分） | U10: — | V10: — | W10: — | X10: チョコレート生産計画表 | Y10: — | Z10: — | AA10: — | AB10: — | AC10: 月末事前チョコ, 協力チョコ, 滋賀チョコ, KYチョコ | AD10: — | AL10: e
B11: =ROW()-3 -> 8 | C11: ○ | K11: B_マスタ | L11: 01_商品・ブランドマスタ | O11: アーモンドSP | P11: アーモンドSP | Q11: ー | R11: アーモンドチョコレートのSP品を集計した小計。 | S11: アーモンドSP VD ＋ アーモンドSP通常 ＋ アーモンドSP準チョコ化25/9 ＋ アーモンドSP'26 | U11: — | V11: — | W11: — | X11: チョコレート生産計画表 | Y11: — | Z11: — | AA11: — | AB11: — | AC11: 月末事前チョコ, 協力チョコ, 滋賀チョコ, KYチョコ | AD11: — | AL11: e
B12: =ROW()-3 -> 9 | C12: ○ | K12: B_マスタ | L12: 01_商品・ブランドマスタ | O12: アーモンドカリっと香ばしPJ | P12: アーモンドカリっと香ばしPJ | Q12: ー | R12: アーモンドカリっと香ばしシリーズのPJ品を集計した小計。 | S12: カリっとPJ増量 ＋ カリっとPJ通常 ＋ カリっと香ばしアーモンドPJ準チョコ化 ＋ カリっと香ばしアーモンドPJ'26 | U12: — | V12: — | W12: — | X12: チョコレート生産計画表 | Y12: — | Z12: — | AA12: — | AB12: — | AC12: 月末事前チョコ, 協力チョコ, 滋賀チョコ, KYチョコ | AD12: — | AL12: e
B13: =ROW()-3 -> 10 | C13: ○ | K13: B_マスタ | L13: 01_商品・ブランドマスタ | O13: アーモンドクリスプ | P13: アーモンドクリスプ | Q13: ー | R13: アーモンドクリスプブランド全品（浦和・九州工場合算）の最上位集計行。 | S13: アーモンドクリスプ ＋ アーモンドクリスプ準チョコ化25/9 ＋ アーモンドクリスプ'26（浦和分＋九州分） | U13: — | V13: — | W13: — | X13: チョコレート生産計画表 | Y13: — | Z13: — | AA13: — | AB13: — | AC13: 月末事前チョコ, 協力チョコ, 滋賀チョコ, KYチョコ | AD13: — | AL13: e
B14: =ROW()-3 -> 11 | C14: ○ | K14: B_マスタ | L14: 01_商品・ブランドマスタ | O14: アーモンドビターPJ | P14: アーモンドビターPJ | Q14: ー | R14: アーモンドビターシリーズのPJ品を集計した小計。 | S14: とろける旨チョコ仕立て ＋ ザクザクとまらんアーモンドPJ ＋ リッチアーモンドチョコレートポップジョイ9か月 ＋ リッチアーモンドチョコレートポップジョイ'26 ＋ リッチアーモンドチョコレートPJ'26秋 | U14: — | V14: — | W14: — | X14: チョコレート生産計画表 | Y14: — | Z14: — | AA14: — | AB14: — | AC14: 月末事前チョコ, 協力チョコ, 滋賀チョコ, KYチョコ | AD14: — | AL14: e
B15: =ROW()-3 -> 12 | C15: ○ | K15: B_マスタ | L15: 01_商品・ブランドマスタ | O15: アジアに恋して | P15: アジアに恋して | Q15: ー | R15: ロッテのプレミアムアイスブランド。アジアの食文化をテーマにした風味（烏龍ミルクティー・杏仁豆腐・ジャスミンミルクティー等）を展開。若年女性向けのデイリープレミアム訴求ブランド。 | T15: — | U15: プレミアム売場獲得・バンドル提案・アイス重点施策 | V15: プレミアムアイスブランド戦略・TVCM施策 | W15: — | X15: — | Y15: — | Z15: 営政 | AA15: アジア恋ナレッジ | AB15: — | AC15: — | AD15: — | AL15: e
B16: =ROW()-3 -> 13 | K16: B_マスタ | L16: 01_商品・ブランドマスタ | O16: 育成ブランド | P16: 育成ブランド | Q16: ー | R16: ロッテのアイスブランドの内、ガーナ・LBの合計 売上控除前のBO売上を使用 | S16: ガーナ + LB | T16: 円 | U16: — | V16: — | W16: — | X16: — | Y16: 経営報告 | Z16: — | AA16: — | AB16: — | AC16: — | AD16: 3月販売実績 | AL16: e
B17: =ROW()-3 -> 14 | C17: ○ | K17: B_マスタ | L17: 01_商品・ブランドマスタ | O17: いちごつみ | P17: いちごつみ | Q17: ー | R17: いちごつみブランドの全品目を集計した小計。 | S17: いちごつみ | U17: — | V17: — | W17: — | X17: チョコレート生産計画表 | Y17: — | Z17: — | AA17: — | AB17: — | AC17: 月末事前チョコ, 協力チョコ, 滋賀チョコ, KYチョコ | AD17: — | AL17: e
B18: =ROW()-3 -> 15 | K18: B_マスタ | L18: 01_商品・ブランドマスタ | O18: エクセレント(B-5,S-6) | P18: エクセレント(B-5,S-6) | Q18: ー | R18: B-5・S-6ラインで製造するエクセレントシリーズ全品を集計したシート内最上位集計行。 | S18: ガーナミルクEX ＋ ガーナローストミルクEX ＋ ガーナブラックEX ＋ クランキーEX | U18: — | V18: — | W18: — | X18: チョコレート生産計画表 | Y18: — | Z18: — | AA18: — | AB18: — | AC18: 月末事前チョコ, 協力チョコ, 滋賀チョコ, KYチョコ | AD18: — | AL18: e
B19: =ROW()-3 -> 16 | C19: ○ | K19: B_マスタ | L19: 01_商品・ブランドマスタ | O19: オオツブガーナ | P19: オオツブガーナ | Q19: ー | R19: オオツブガーナブランドの全品目を集計した小計。 | S19: 大粒ガーナ'25 ＋ 大粒ガーナ'26外品変更 ＋ 大粒ガーナ'26配合変更 | T19: 円 | U19: — | V19: — | W19: — | X19: チョコレート生産計画表 | Y19: — | Z19: — | AA19: — | AB19: — | AC19: 月末事前チョコ, 協力チョコ, 滋賀チョコ, KYチョコ | AD19: — | AL19: e
B20: =ROW()-3 -> 17 | C20: ○ | K20: B_マスタ | L20: 01_商品・ブランドマスタ | O20: ガーナPJ | P20: ガーナPJ | Q20: ー | R20: ガーナブランドのPJ品を集計した小計。 | S20: ガーナPJ周年 ＋ ガーナPJ ＋ ガーナPJ'26 | T20: 円 | U20: — | V20: — | W20: — | X20: チョコレート生産計画表 | Y20: — | Z20: — | AA20: — | AB20: — | AC20: 月末事前チョコ, 協力チョコ, 滋賀チョコ, KYチョコ | AD20: — | AL20: e
B21: =ROW()-3 -> 18 | C21: ○ | K21: B_マスタ | L21: 01_商品・ブランドマスタ | O21: ガーナザクほろPJ | P21: ガーナザクほろPJ | Q21: ー | R21: ガーナザクほろシリーズのPJ品を集計した小計。 | S21: ガーナザクほろココアシュー＆クッキーポップジョイ ＋ ガーナザクほろシュー＆クッキー＜塩ミルク＞ポップジョイ ＋ ガーナザクほろ発酵バターシューPJ | T21: 円 | U21: — | V21: — | W21: — | X21: チョコレート生産計画表 | Y21: — | Z21: — | AA21: — | AB21: — | AC21: 月末事前チョコ, 協力チョコ, 滋賀チョコ, KYチョコ | AD21: — | AL21: e
B22: =ROW()-3 -> 19 | C22: ○ | K22: B_マスタ | L22: 01_商品・ブランドマスタ | O22: ガーナスリムパック | P22: ガーナスリムパック | Q22: ー | R22: ガーナブランドのスリムパック品を集計した小計。 | S22: ガーナスリムパック'25 | T22: 円 | U22: — | V22: — | W22: — | X22: チョコレート生産計画表 | Y22: — | Z22: — | AA22: — | AB22: — | AC22: 月末事前チョコ, 協力チョコ, 滋賀チョコ, KYチョコ | AD22: — | AL22: e
B23: =ROW()-3 -> 20 | C23: ○ | K23: B_マスタ | L23: 01_商品・ブランドマスタ | O23: ガーナピンク | P23: ガーナピンク | Q23: ー | R23: ガーナピンクブランドの全品目を集計した小計。 | S23: ガーナピンク（各品） | T23: 円 | U23: — | V23: — | W23: — | X23: チョコレート生産計画表 | Y23: — | Z23: — | AA23: — | AB23: — | AC23: 月末事前チョコ, 協力チョコ, 滋賀チョコ, KYチョコ | AD23: — | AL23: e
B24: =ROW()-3 -> 21 | C24: ○ | K24: B_マスタ | L24: 01_商品・ブランドマスタ | O24: ガーナブラック | P24: ガーナブラック | Q24: ー | R24: ガーナブラックチョコレートブランドの全品目を集計した小計。 | S24: ガーナブラック母の日 ＋ ガーナブラック'25 ＋ ガーナブラック'26母の日 ＋ ガーナブラック'26賞味 | T24: 円 | U24: — | V24: — | W24: — | X24: チョコレート生産計画表 | Y24: — | Z24: — | AA24: — | AB24: — | AC24: 月末事前チョコ, 協力チョコ, 滋賀チョコ, KYチョコ | AD24: — | AL24: e
B25: =ROW()-3 -> 22 | C25: ○ | K25: B_マスタ | L25: 01_商品・ブランドマスタ | O25: ガーナブラックEX | P25: ガーナブラックEX | Q25: ー | R25: ガーナブラックのエクセレント品を集計した小計。 | S25: ガーナブラックEX'25 ＋ ガーナブラックEX'26 | T25: 円 | U25: — | V25: — | W25: — | X25: チョコレート生産計画表 | Y25: — | Z25: — | AA25: — | AB25: — | AC25: 月末事前チョコ, 協力チョコ, 滋賀チョコ, KYチョコ | AD25: — | AL25: e
B26: =ROW()-3 -> 23 | C26: ○ | K26: B_マスタ | L26: 01_商品・ブランドマスタ | O26: ガーナホワイト | P26: ガーナホワイト | Q26: ー | R26: ガーナホワイトチョコレートブランドの全品目を集計した小計。 | S26: ガーナホワイト母の日 ＋ ガーナホワイト'25 ＋ ガーナホワイト'26母の日 ＋ ガーナホワイト'26賞味 | T26: 円 | U26: — | V26: — | W26: — | X26: チョコレート生産計画表 | Y26: — | Z26: — | AA26: — | AB26: — | AC26: 月末事前チョコ, 協力チョコ, 滋賀チョコ, KYチョコ | AD26: — | AL26: e
B27: =ROW()-3 -> 24 | C27: ○ | K27: B_マスタ | L27: 01_商品・ブランドマスタ | O27: ガーナミルク | P27: ガーナミルク | Q27: ー | R27: ガーナミルクチョコレートブランドの全品目を集計した小計。 | S27: ガーナミルク母の日 ＋ ガーナミルク'25 ＋ ガーナミルク'26母の日 ＋ ガーナミルク'26賞味 ＋ ガーナミルク10箱入 | T27: 円 | U27: — | V27: — | W27: — | X27: チョコレート生産計画表 | Y27: — | Z27: — | AA27: — | AB27: — | AC27: 月末事前チョコ, 協力チョコ, 滋賀チョコ, KYチョコ | AD27: — | AL27: e
B28: =ROW()-3 -> 25 | C28: ○ | K28: B_マスタ | L28: 01_商品・ブランドマスタ | O28: ガーナミルクEX | P28: ガーナミルクEX | Q28: ー | R28: ガーナミルクのエクセレント品を集計した小計。 | S28: ガーナミルクEX'25 | T28: 円 | U28: — | V28: — | W28: — | X28: チョコレート生産計画表 | Y28: — | Z28: — | AA28: — | AB28: — | AC28: 月末事前チョコ, 協力チョコ, 滋賀チョコ, KYチョコ | AD28: — | AL28: e
B29: =ROW()-3 -> 26 | C29: ○ | K29: B_マスタ | L29: 01_商品・ブランドマスタ | O29: ガーナミルクトットプチ | P29: ガーナミルクトットプチ | Q29: ー | R29: ガーナミルクのトットプチ品を集計した小計。 | S29: ガーナミルクトットプチ ＋ ガーナミルクトットプチ'26 | T29: 円 | U29: — | V29: — | W29: — | X29: チョコレート生産計画表 | Y29: — | Z29: — | AA29: — | AB29: — | AC29: 月末事前チョコ, 協力チョコ, 滋賀チョコ, KYチョコ | AD29: — | AL29: e
B30: =ROW()-3 -> 27 | C30: ○ | K30: B_マスタ | L30: 01_商品・ブランドマスタ | O30: ガーナミルクボトル | P30: ガーナミルクボトル | Q30: ー | R30: ガーナミルクのボトル容器品を集計した小計。 | S30: ガーナミルクボトル | T30: 円 | U30: — | V30: — | W30: — | X30: チョコレート生産計画表 | Y30: — | Z30: — | AA30: — | AB30: — | AC30: 月末事前チョコ, 協力チョコ, 滋賀チョコ, KYチョコ | AD30: — | AL30: e
... B36: =ROW()-3 -> 33 | C36: ○ | K36: B_マスタ | L36: 01_商品・ブランドマスタ | O36: ガーナ抹茶 | P36: ガーナ抹茶 | Q36: ー | R36: ガーナ抹茶ブランドの全品目を集計した小計。 | S36: ガーナ抹茶（下期定番化） ＋ ガーナ抹茶'26母の日 ＋ ガーナ抹茶'26秋 | T36: 円 | U36: — | V36: — | W36: — | X36: チョコレート生産計画表 | Y36: — | Z36: — | AA36: — | AB36: — | AC36: 月末事前チョコ, 協力チョコ, 滋賀チョコ, KYチョコ | AD36: — | AL36: e
B37: =ROW()-3 -> 34 | C37: ○ | K37: B_マスタ | L37: 01_商品・ブランドマスタ | O37: カカオの恵み×ゼロ袋 | P37: カカオの恵み×ゼロ袋 | Q37: ー | R37: カカオの恵みとゼロのコラボ袋タイプ品を集計した小計。 | S37: カカオの恵み＜糖類ゼロ＞袋 | U37: — | V37: — | W37: — | X37: チョコレート生産計画表 | Y37: — | Z37: — | AA37: — | AB37: — | AC37: 月末事前チョコ, 協力チョコ, 滋賀チョコ, KYチョコ | AD37: — | AL37: e
B38: =ROW()-3 -> 35 | C38: ○ | K38: B_マスタ | L38: 01_商品・ブランドマスタ | O38: カカオの恵み×ゼロ大容量 | P38: カカオの恵み×ゼロ大容量 | Q38: ー | R38: カカオの恵みとゼロのコラボ大容量品を集計した小計。 | S38: カカオの恵み＜糖類ゼロ＞大容量 | U38: — | V38: — | W38: — | X38: チョコレート生産計画表 | Y38: — | Z38: — | AA38: — | AB38: — | AC38: 月末事前チョコ, 協力チョコ, 滋賀チョコ, KYチョコ | AD38: — | AL38: e
B39: =ROW()-3 -> 36 | C39: ○ | K39: B_マスタ | L39: 01_商品・ブランドマスタ | O39: カカオの恵みSP | P39: カカオの恵みSP | Q39: ー | R39: カカオの恵みブランドのSP品を集計した小計。 | S39: カカオの恵みSP値上げ減量 ＋ カカオの恵みSP品質変更（カカオ産地） ＋ カカオの恵みSP'26JAN変 | U39: — | V39: — | W39: — | X39: チョコレート生産計画表 | Y39: — | Z39: — | AA39: — | AB39: — | AC39: 月末事前チョコ, 協力チョコ, 滋賀チョコ, KYチョコ | AD39: — | AL39: e
B40: =ROW()-3 -> 37 | C40: ○ | K40: B_マスタ | L40: 01_商品・ブランドマスタ | O40: カカオの恵み箱 | P40: カカオの恵み箱 | Q40: ー | R40: カカオの恵みブランドの箱タイプ品を集計した小計。 | S40: カカオの恵み72%箱'26 | U40: — | V40: — | W40: — | X40: チョコレート生産計画表 | Y40: — | Z40: — | AA40: — | AB40: — | AC40: 月末事前チョコ, 協力チョコ, 滋賀チョコ, KYチョコ | AD40: — | AL40: e
B41: =ROW()-3 -> 38 | C41: ○ | K41: B_マスタ | L41: 01_商品・ブランドマスタ | O41: カジッテ | P41: カジッテ | Q41: KAZITTE | R41: ロッテのハードグミブランド。「カジる、果実感。」をコンセプトに、ハード食感でありながら果実感が存分に楽しめる「果実感引き立て製法」（香り・食感・原料のこだわり）を特徴とする。2025年発売。 | T41: — | U41: 新商品提案・定番採用交渉・施策提案 | V41: — | W41: — | X41: — | Y41: — | Z41: 営政 | AA41: — | AB41: — | AC41: — | AD41: — | AL41: e
B42: =ROW()-3 -> 39 | C42: ○ | K42: B_マスタ | L42: 01_商品・ブランドマスタ | O42: ガナクラSP | P42: ガナクラSP | Q42: ー | R42: ガーナ・クランキーブランドのSP品を集計した小計。 | S42: ガナクラSP ＋ ガナクラSP減量JAN変 ＋ ガナクラSP'26 | U42: — | V42: — | W42: — | X42: チョコレート生産計画表 | Y42: — | Z42: — | AA42: — | AB42: — | AC42: 月末事前チョコ, 協力チョコ, 滋賀チョコ, KYチョコ | AD42: — | AL42: e
B43: =ROW()-3 -> 40 | C43: ○ | K43: B_マスタ | L43: 01_商品・ブランドマスタ | O43: カプッチョ | P43: カプッチョ | Q43: ー | R43: カプッチョブランドの全品目を集計した小計。 | S43: カプッチョ ＋ カプッチョ'26 | U43: — | V43: — | W43: — | X43: チョコレート生産計画表 | Y43: — | Z43: — | AA43: — | AB43: — | AC43: 月末事前チョコ, 協力チョコ, 滋賀チョコ, KYチョコ | AD43: — | AL43: e
B44: =ROW()-3 -> 41 | C44: ○ | K44: B_マスタ | L44: 01_商品・ブランドマスタ | O44: キシリトールガム エンジョイシリーズ | P44: キシリトールガム エンジョイシリーズ | Q44: エンジョイシリーズ | R44: キシリトールブランドの若年層向けフレーバーラインナップ。炭酸飲料フレーバー（コーラ等）やフルーツ・飲料フレーバーを展開し、ガム離反ユーザー・フルーツ系錠菓ユーザー・グミユーザーの取り込みを目的とする。 | T44: — | U44: キシリトール定番獲得・ノンユーザー新規獲得提案 | V44: — | W44: — | X44: — | Y44: — | Z44: 営政 | AA44: — | AB44: — | AC44: — | AD44: — | AL44: e
B45: =ROW()-3 -> 42 | C45: ○ | K45: B_マスタ | L45: 01_商品・ブランドマスタ | O45: キャラメルミルク | P45: キャラメルミルク | Q45: ー | R45: ガーナキャラメルミルクブランドの全品目を集計した小計。 | S45: ガーナキャラメルミルク ＋ ガーナキャラメルミルク'26塩+母の日 | U45: — | V45: — | W45: — | X45: チョコレート生産計画表 | Y45: — | Z45: — | AA45: — | AB45: — | AC45: 月末事前チョコ, 協力チョコ, 滋賀チョコ, KYチョコ | AD45: — | AL45: e
B46: =ROW()-3 -> 43 | C46: ○ | K46: B_マスタ | L46: 01_商品・ブランドマスタ | O46: クラガナSP | P46: クラガナSP | Q46: ー | R46: クランキー・ガーナ合同スペシャルパック品を集計した小計。 | S46: クラガナSP各品 | U46: — | V46: — | W46: — | X46: チョコレート生産計画表 | Y46: — | Z46: — | AA46: — | AB46: — | AC46: 月末事前チョコ, 協力チョコ, 滋賀チョコ, KYチョコ | AD46: — | AL46: e
B47: =ROW()-3 -> 44 | C47: ○ | K47: B_マスタ | L47: 01_商品・ブランドマスタ | O47: クランキー | P47: クランキー | Q47: ー | R47: クランキーブランド定番品の全品目を集計した小計。 | S47: クランキー'25 ＋ クランキー'26 | U47: — | V47: — | W47: — | X47: チョコレート生産計画表 | Y47: — | Z47: — | AA47: — | AB47: — | AC47: 月末事前チョコ, 協力チョコ, 滋賀チョコ, KYチョコ | AD47: — | AL47: e
B48: =ROW()-3 -> 45 | C48: ○ | K48: B_マスタ | L48: 01_商品・ブランドマスタ | O48: クランキー2nd | P48: クランキー2nd | Q48: ー | R48: クランキーブランドの第2世代・派生品を集計した小計。 | S48: クランキーバースデーケーキ味 ＋ クランキーあまずっぱ苺 ＋ クランキー塩バニラ ＋ クランキー香ばしキャラメル ＋ ザクザクやみつきクランキー板 | U48: — | V48: — | W48: — | X48: チョコレート生産計画表 | Y48: — | Z48: — | AA48: — | AB48: — | AC48: 月末事前チョコ, 協力チョコ, 滋賀チョコ, KYチョコ | AD48: — | AL48: e
B49: =ROW()-3 -> 46 | C49: ○ | K49: B_マスタ | L49: 01_商品・ブランドマスタ | O49: クランキーBIGパウチ | P49: クランキーBIGパウチ | Q49: ー | R49: クランキーBIGパウチ品を集計した小計。 | S49: クランキーBIGパウチ ＋ クランキーBIGパウチ'26 | U49: — | V49: — | W49: — | X49: チョコレート生産計画表 | Y49: — | Z49: — | AA49: — | AB49: — | AC49: 月末事前チョコ, 協力チョコ, 滋賀チョコ, KYチョコ | AD49: — | AL49: e
B50: =ROW()-3 -> 47 | C50: ○ | K50: B_マスタ | L50: 01_商品・ブランドマスタ | O50: クランキーBIGパウチ2nd | P50: クランキーBIGパウチ2nd | Q50: ー | R50: クランキーBIGパウチの第2世代品を集計した小計。 | S50: ナッツトリュフパウチ ＋ クランキーBIGパウチセカンド ＋ ザクザクやみつきクランキーBIGパウチ | U50: — | V50: — | W50: — | X50: チョコレート生産計画表 | Y50: — | Z50: — | AA50: — | AB50: — | AC50: 月末事前チョコ, 協力チョコ, 滋賀チョコ, KYチョコ | AD50: — | AL50: e
B51: =ROW()-3 -> 48 | C51: ○ | K51: B_マスタ | L51: 01_商品・ブランドマスタ | O51: クランキーBIGパウチ3rd | P51: クランキーBIGパウチ3rd | Q51: ー | R51: クランキーBIGパウチの第3世代品を集計した小計。 | S51: クランキーBIGパウチ3rd各品 | U51: — | V51: — | W51: — | X51: チョコレート生産計画表 | Y51: — | Z51: — | AA51: — | AB51: — | AC51: 月末事前チョコ, 協力チョコ, 滋賀チョコ, KYチョコ | AD51: — | AL51: e
B52: =ROW()-3 -> 49 | C52: ○ | K52: B_マスタ | L52: 01_商品・ブランドマスタ | O52: クランキーEX | P52: クランキーEX | Q52: ー | R52: クランキーのエクセレント品を集計した小計。 | S52: クランキーEX原原対応 ＋ クランキーEX'26 | U52: — | V52: — | W52: — | X52: チョコレート生産計画表 | Y52: — | Z52: — | AA52: — | AB52: — | AC52: 月末事前チョコ, 協力チョコ, 滋賀チョコ, KYチョコ | AD52: — | AL52: e
B53: =ROW()-3 -> 50 | C53: ○ | K53: B_マスタ | L53: 01_商品・ブランドマスタ | O53: クランキーPJ | P53: クランキーPJ | Q53: ー | R53: クランキーブランドのPJ品を集計した小計。 | S53: クランキーPJ ＋ クランキーPJ'26 | U53: — | V53: — | W53: — | X53: チョコレート生産計画表 | Y53: — | Z53: — | AA53: — | AB53: — | AC53: 月末事前チョコ, 協力チョコ, 滋賀チョコ, KYチョコ | AD53: — | AL53: e
B54: =ROW()-3 -> 51 | C54: ○ | K54: B_マスタ | L54: 01_商品・ブランドマスタ | O54: クランキーPJクッキー | P54: クランキーPJクッキー | Q54: ー | R54: クランキーPJのクッキータイプ品を集計した小計。 | S54: クランキーPJクッキー&クリーム ＋ クランキーPJクッキー&クリーム'26 | U54: — | V54: — | W54: — | X54: チョコレート生産計画表 | Y54: — | Z54: — | AA54: — | AB54: — | AC54: 月末事前チョコ, 協力チョコ, 滋賀チョコ, KYチョコ | AD54: — | AL54: e
B55: =ROW()-3 -> 52 | C55: ○ | K55: B_マスタ | L55: 01_商品・ブランドマスタ | O55: クランキーPJストロ | P55: クランキーPJストロ | Q55: ー | R55: クランキーPJのストロベリー品を集計した小計。 | S55: クランキーPJストロ ＋ クランキーPJストロ'26 | U55: — | V55: — | W55: — | X55: チョコレート生産計画表 | Y55: — | Z55: — | AA55: — | AB55: — | AC55: 月末事前チョコ, 協力チョコ, 滋賀チョコ, KYチョコ | AD55: — | AL55: e
B56: =ROW()-3 -> 53 | C56: ○ | K56: B_マスタ | L56: 01_商品・ブランドマスタ | O56: クランキーアーモンドプチ | P56: クランキーアーモンドプチ | Q56: ー | R56: クランキーアーモンドプチ品を集計した小計。 | S56: クランキーアーモンドプチ ＋ クランキーアーモンドプチ'26 | U56: — | V56: — | W56: — | X56: チョコレート生産計画表 | Y56: — | Z56: — | AA56: — | AB56: — | AC56: 月末事前チョコ, 協力チョコ, 滋賀チョコ, KYチョコ | AD56: — | AL56: e
... B59: =ROW()-3 -> 56 | C59: ○ | K59: B_マスタ | L59: 01_商品・ブランドマスタ | O59: クランキースリムパック | P59: クランキースリムパック | Q59: ー | R59: クランキーブランドのスリムパック品を集計した小計。 | S59: クランキースリムパック'25 ＋ クランキースリムパック'26 | U59: — | V59: — | W59: — | X59: チョコレート生産計画表 | Y59: — | Z59: — | AA59: — | AB59: — | AC59: 月末事前チョコ, 協力チョコ, 滋賀チョコ, KYチョコ | AD59: — | AL59: e
B60: =ROW()-3 -> 57 | K60: B_マスタ | L60: 01_商品・ブランドマスタ | O60: クランキー中袋 | P60: クランキー中袋 | Q60: ー | R60: クランキーブランドの中袋品を集計した小計。 | S60: クランキーミニ中袋 ＋ クランキー＜無限サクサクパック＞ ＋ クランキー3種アソートパック | U60: — | V60: — | W60: — | X60: チョコレート生産計画表 | Y60: — | Z60: — | AA60: — | AB60: — | AC60: 月末事前チョコ, 協力チョコ, 滋賀チョコ, KYチョコ | AD60: — | AL60: e
B61: =ROW()-3 -> 58 | K61: B_マスタ | L61: 01_商品・ブランドマスタ | O61: クランキー留型 | P61: クランキー留型 | Q61: ー | R61: 特定取引先向け専用品（留型）のクランキー品目を集計した小計。 | S61: クランキー留型各品 | U61: — | V61: — | W61: — | X61: チョコレート生産計画表 | Y61: — | Z61: — | AA61: — | AB61: — | AC61: 月末事前チョコ, 協力チョコ, 滋賀チョコ, KYチョコ | AD61: — | AL61: e
B62: =ROW()-3 -> 59 | K62: B_マスタ | L62: 01_商品・ブランドマスタ | O62: コアラのマーチ3rd | P62: コアラのマーチ3rd | Q62: ー | R62: コアラのマーチブランドの第3世代品を集計した小計。 | S62: コアラのマーチ＜チョコ＞名前第二弾 ＋ コアラのマーチ＜チョコ＞ ＋ コアラのマーチ＜チョコ＞'26 ＋ コアラのマーチ＜チョコ＞'26夏 ＋ コアラのマーチ＜いちご＞ ＋ コアラのマーチ＜いちご＞名前第二弾 ＋ コアラのマーチ＜いちご＞新 | U62: — | V62: — | W62: — | X62: チョコレート生産計画表 | Y62: — | Z62: — | AA62: — | AB62: — | AC62: 月末事前チョコ, 協力チョコ, 滋賀チョコ, KYチョコ | AD62: — | AL62: e
B63: =ROW()-3 -> 60 | K63: B_マスタ | L63: 01_商品・ブランドマスタ | O63: コアラのマーチSP | P63: コアラのマーチSP | Q63: ー | R63: コアラのマーチブランドのSP品を集計した小計。 | S63: コアラのマーチSP'25 ＋ コアラのマーチSP'25冬名前入り ＋ コアラのマーチSP'26 ＋ コアラのマーチSP'26裏面 | U63: — | V63: — | W63: — | X63: チョコレート生産計画表 | Y63: — | Z63: — | AA63: — | AB63: — | AC63: 月末事前チョコ, 協力チョコ, 滋賀チョコ, KYチョコ | AD63: — | AL63: e
B64: =ROW()-3 -> 61 | C64: ○ | K64: B_マスタ | L64: 01_商品・ブランドマスタ | O64: コアラミニパック | P64: コアラミニパック | Q64: ー | R64: コアラのマーチのミニパック品を集計した小計。 | S64: コアラのマーチSP ハローキティデザイン ＋ コアラのマーチSP 大阪・関西万博デザイン ＋ コアラのマーチSP まるごとカカオ豆(5/27) | U64: — | V64: — | W64: — | X64: チョコレート生産計画表 | Y64: — | Z64: — | AA64: — | AB64: — | AC64: 月末事前チョコ, 協力チョコ, 滋賀チョコ, KYチョコ | AD64: — | AL64: e
B65: =ROW()-3 -> 62 | K65: B_マスタ | L65: 01_商品・ブランドマスタ | O65: コンテンツウエハース | P65: コンテンツウエハース | Q65: ー | R65: コンテンツIPを使用したウエハース品を集計した小計。 | S65: にじさんじマンチョコ２ ＋ 鬼滅無限城 ＋ スターウォーズビックリマン | U65: — | V65: — | W65: — | X65: チョコレート生産計画表 | Y65: — | Z65: — | AA65: — | AB65: — | AC65: 月末事前チョコ, 協力チョコ, 滋賀チョコ, KYチョコ | AD65: — | AL65: e
B66: =ROW()-3 -> 63 | C66: ○ | K66: B_マスタ | L66: 01_商品・ブランドマスタ | O66: ザクザククランキーPP | P66: ザクザククランキーPP | Q66: ー | R66: ザクザククランキーPPの全品目を集計した小計。 | S66: ザクザククランキーPP値上げ ＋ ザクザククランキーPP ＋ ザクザククランキーPPコストダウン配合 ＋ 留型ザクザクやみつきクランキープチパック | U66: — | V66: — | W66: — | X66: チョコレート生産計画表 | Y66: — | Z66: — | AA66: — | AB66: — | AC66: 月末事前チョコ, 協力チョコ, 滋賀チョコ, KYチョコ | AD66: — | AL66: e
B67: =ROW()-3 -> 64 | C67: ○ | K67: B_マスタ | L67: 01_商品・ブランドマスタ | O67: ザクザククランキーSP | P67: ザクザククランキーSP | Q67: ー | R67: ザクザククランキーSPの全品目を集計した小計。 | S67: ザクザククランキーSP食品ヒット大賞ロゴ削除 ＋ ザクザククランキーSPコストダウン配合 ＋ ザクザククランキーSP RF(JAN変) ＋ ザクザククランキーSP'26 | U67: — | V67: — | W67: — | X67: チョコレート生産計画表 | Y67: — | Z67: — | AA67: — | AB67: — | AC67: 月末事前チョコ, 協力チョコ, 滋賀チョコ, KYチョコ | AD67: — | AL67: e
B68: =ROW()-3 -> 65 | K68: B_マスタ | L68: 01_商品・ブランドマスタ | O68: ザクザククランキーSP2nd | P68: ザクザククランキーSP2nd | Q68: ー | R68: ザクザククランキーSP2ndの全品目を集計した小計。 | S68: ザクザククランキースナックインSP（各品） | U68: — | V68: — | W68: — | X68: チョコレート生産計画表 | Y68: — | Z68: — | AA68: — | AB68: — | AC68: 月末事前チョコ, 協力チョコ, 滋賀チョコ, KYチョコ | AD68: — | AL68: e
B69: =ROW()-3 -> 66 | C69: ○ | K69: B_マスタ | L69: 01_商品・ブランドマスタ | O69: 市販用 | P69: 市販用 | Q69: — | R69: 市販用アイスの生販在計画表における最大集計区分。スーパー・CVS・ドラッグストア等の小売チャネル向けアイス製品全体の合計。主要ブランド計とその他計の2区分で構成される。業務用計とは別帳票・別予算で管理される。 | S69: 主要ブランド計 + その他計 | T69: CS | U69: — | V69: — | W69: — | X69: 業務用アイス生販在計画表 | Y69: — | Z69: — | AA69: — | AB69: — | AC69: 月末事前アイス業,月末事前アイス市 | AD69: — | AL69: e
B70: =ROW()-3 -> 67 | C70: ○ | K70: B_マスタ | L70: 01_商品・ブランドマスタ | O70: 重点ブランド | P70: 重点ブランド | Q70: ー | R70: ロッテのアイスブランドの内、爽・クーリッシュ・雪見だいふく・モナ王の合計 売上控除前のBO売上を使用 | S70: 爽 + クーリッシュ + 雪見だいふく + モナ王 | T70: 円 | U70: — | V70: — | W70: — | X70: — | Y70: 経営報告 | Z70: — | AA70: — | AB70: — | AC70: — | AD70: 3月販売実績 | AL70: e
B71: =ROW()-3 -> 68 | C71: ○ | K71: B_マスタ | L71: 01_商品・ブランドマスタ | O71: 主力ブランド | P71: 主力ブランド | Q71: ー | R71: 重点ブランド（爽・クーリッシュ・雪見だいふく・モナ王）と、育成ブランド（ガーナ・LB）の合計 売上控除前の BO売上を使用 | S71: 重点ブランド + 育成ブランド | T71: 円 | U71: — | V71: — | W71: — | X71: — | Y71: 経営報告 | Z71: — | AA71: — | AB71: — | AC71: — | AD71: 3月販売実績 | AL71: e
B72: =ROW()-3 -> 69 | K72: B_マスタ | L72: 01_商品・ブランドマスタ | O72: スティック | P72: スティック | Q72: ー | R72: チョコレート市場の機能別分類の一つ。形状がスティック状（細長い棒状）のチョコレート商品。他分類でスティック形状のものは形状属性として本分類に含まれる場合がある。 | T72: ー | U72: チョコレートサブカテゴリ別市場分析 | V72: — | W72: — | X72: — | Y72: — | Z72: 菓初 | AA72: — | AB72: — | AC72: — | AD72: — | AL72: e
B73: =ROW()-3 -> 70 | C73: ○ | K73: B_マスタ | L73: 01_商品・ブランドマスタ | O73: スポット | P73: スポット | Q73: — | R73: 短期投入・期間限定の商品。 | T73: — | U73: 棚割, 営業計画 | V73: — | W73: — | X73: — | Y73: — | Z73: 菓初, 営政 | AA73: — | AB73: — | AC73: — | AD73: — | AL73: e
B74: =ROW()-3 -> 71 | K74: B_マスタ | L74: 01_商品・ブランドマスタ | O74: スリムボトルライン | P74: スリムボトルライン | Q74: ー | R74: ACUOグリーンミントSB、SCUOクリアブルーSB、オーラテクト＜クリア＞SB、オーラテクト＜シトラス＞SB、フッ素ペパーミントSB、マイニチケア血圧SBの総称 | T74: — | U74: — | V74: — | W74: — | X74: 生産計画 | Y74: — | Z74: — | AA74: — | AB74: — | AC74: SCM企画課MT | AD74: — | AL74: e
B75: =ROW()-3 -> 72 | C75: ○ | K75: B_マスタ | L75: 01_商品・ブランドマスタ | O75: ゼロ | P75: ゼロ | Q75: ー | R75: ゼロブランドの通年品を集計した小計。 | S75: ゼロ ＋ ゼロ「カカオマス」原材料標記25/3～ ＋ ゼロ'26 | T75: — | U75: — | V75: — | W75: — | X75: チョコレート生産計画表 | Y75: — | Z75: — | AA75: — | AB75: — | AC75: 月末事前チョコ, 協力チョコ, 滋賀チョコ, KYチョコ | AD75: — | AL75: e
B76: =ROW()-3 -> 73 | C76: ○ | K76: B_マスタ | L76: 01_商品・ブランドマスタ | O76: ゼロカカオ70% | P76: ゼロカカオ70% | Q76: ー | R76: ゼロブランドのカカオ70%品を集計した小計。 | S76: ゼロカカオ70 ＋ ゼロカカオ70「カカオマス」原材料標記25/3～ ＋ ゼロカカオ70'26 | T76: — | U76: — | V76: — | W76: — | X76: チョコレート生産計画表 | Y76: — | Z76: — | AA76: — | AB76: — | AC76: 月末事前チョコ, 協力チョコ, 滋賀チョコ, KYチョコ | AD76: — | AL76: e
B77: =ROW()-3 -> 74 | C77: ○ | K77: B_マスタ | L77: 01_商品・ブランドマスタ | O77: ゼロくちどけショコラ | P77: ゼロくちどけショコラ | Q77: ー | R77: ゼロブランドのくちどけショコラ品を集計した小計。 | S77: ゼロくちどけショコラ'25 | T77: — | U77: — | V77: — | W77: — | X77: チョコレート生産計画表 | Y77: — | Z77: — | AA77: — | AB77: — | AC77: 月末事前チョコ, 協力チョコ, 滋賀チョコ, KYチョコ | AD77: — | AL77: e
B78: =ROW()-3 -> 75 | C78: ○ | K78: B_マスタ | L78: 01_商品・ブランドマスタ | O78: ゼログラノラバー | P78: ゼログラノラバー | Q78: ー | R78: ゼロブランドのグラノラバー品を集計した小計。 | S78: ゼログラノーラチョコバー9ヶ月 ＋ ゼログラノーラチョコバー'26 | T78: — | U78: — | V78: — | W78: — | X78: チョコレート生産計画表 | Y78: — | Z78: — | AA78: — | AB78: — | AC78: 月末事前チョコ, 協力チョコ, 滋賀チョコ, KYチョコ | AD78: — | AL78: e
B79: =ROW()-3 -> 76 | C79: ○ | K79: B_マスタ | L79: 01_商品・ブランドマスタ | O79: ゼロシュガーチョコ | P79: ゼロシュガーチョコ | Q79: ー | R79: 砂糖不使用チョコレートブランドの全品目を集計した小計。 | S79: ゼロシュガーフリーパウチ ＋ ゼロシュガーフリーパウチ「カカオマス」原材料標記25/3～ ＋ ゼロシュガーフリーパウチ'26 ＋ ゼロシュガーフリーパウチ'26秋 | T79: — | U79: — | V79: — | W79: — | X79: チョコレート生産計画表 | Y79: — | Z79: — | AA79: — | AB79: — | AC79: 月末事前チョコ, 協力チョコ, 滋賀チョコ, KYチョコ | AD79: — | AL79: e
B80: =ROW()-3 -> 77 | C80: ○ | K80: B_マスタ | L80: 01_商品・ブランドマスタ | O80: ゼロプロテインバー | P80: ゼロプロテインバー | Q80: ー | R80: ゼロブランドのプロテインバー品を集計した小計。 | S80: ゼロプロテインチョコバー12か月賞味 ＋ ゼロプロテインチョコバー'26 | T80: — | U80: — | V80: — | W80: — | X80: チョコレート生産計画表 | Y80: — | Z80: — | AA80: — | AB80: — | AC80: 月末事前チョコ, 協力チョコ, 滋賀チョコ, KYチョコ | AD80: — | AL80: e
B81: =ROW()-3 -> 78 | C81: ○ | K81: B_マスタ | L81: 01_商品・ブランドマスタ | O81: ゼロ袋 | P81: ゼロ袋 | Q81: ー | R81: ゼロブランドの袋タイプ品を集計した小計。 | S81: ゼロ袋 ＋ ゼロ袋「カカオマス」原材料標記25/3～ ＋ ゼロ袋'26秋 | T81: — | U81: — | V81: — | W81: — | X81: チョコレート生産計画表 | Y81: — | Z81: — | AA81: — | AB81: — | AC81: 月末事前チョコ, 協力チョコ, 滋賀チョコ, KYチョコ | AD81: — | AL81: e
B82: =ROW()-3 -> 79 | C82: ○ | K82: B_マスタ | L82: 01_商品・ブランドマスタ | O82: ゼロ大容量 | P82: ゼロ大容量 | Q82: ー | R82: ゼロブランドの大容量品を集計した小計。 | S82: ゼロチョコレート大容量 | T82: — | U82: — | V82: — | W82: — | X82: チョコレート生産計画表 | Y82: — | Z82: — | AA82: — | AB82: — | AC82: 月末事前チョコ, 協力チョコ, 滋賀チョコ, KYチョコ | AD82: — | AL82: e
B83: =ROW()-3 -> 80 | K83: B_マスタ | L83: 01_商品・ブランドマスタ | O83: センター | P83: センター | Q83: ー | R83: チョコレート市場の機能別分類の一つ。クリーム・洋酒・細かく砕いたクランチ・キャラメル・スナック等がチョコレートの中に入っている商品。クリーム・洋酒・ジュレなどの中に乾燥フルーツが入ったものも含む。 | T83: ー | U83: チョコレートサブカテゴリ別市場分析 | V83: — | W83: — | X83: — | Y83: — | Z83: 菓初 | AA83: — | AB83: — | AC83: — | AD83: — | AL83: e
B84: =ROW()-3 -> 81 | K84: B_マスタ | L84: 01_商品・ブランドマスタ | O84: ダークミルク | P84: ダークミルク | Q84: ー | R84: ガーナダークミルクブランドの全品目を集計した小計。 | S84: ダークミルク塩なし ＋ ダークミルク春夏塩あり ＋ ダークミルク'25 ＋ ダークミルク'26塩+母の日 | T84: ー | U84: — | V84: — | W84: — | X84: チョコレート生産計画表 | Y84: — | Z84: — | AA84: — | AB84: — | AC84: 月末事前チョコ, 協力チョコ, 滋賀チョコ, KYチョコ | AD84: — | AL84: e
B85: =ROW()-3 -> 82 | K85: B_マスタ | L85: 01_商品・ブランドマスタ | O85: たっぷり果実とビタミングミ | P85: たっぷり果実とビタミングミ | Q85: 果実とビタミン | R85: ロッテの機能性フルーツグミ。1袋で1日分の9種マルチビタミン（ナイアシン・ビタミンA〜E等）を摂取できる「ホワイトスペース」商品。ミックスフルーツ果汁20%使用。20〜40代女性向け。 | T85: — | U85: 健康訴求グミ提案・CVS・レール先行提案 | V85: — | W85: — | X85: — | Y85: — | Z85: 営政 | AA85: — | AB85: — | AC85: — | AD85: — | AL85: e
B86: =ROW()-3 -> 83 | K86: B_マスタ | L86: 01_商品・ブランドマスタ | O86: チョコスナック | P86: チョコスナック | Q86: ー | R86: チョコレート市場の機能別分類の一つ。スナック（ビスケット・プレッツェル・クッキー等）が主体的なチョコレート商品。チョコレートの中にそのままの果実が入ったものも含む。 | T86: ー | U86: チョコレートサブカテゴリ別市場分析 | V86: — | W86: — | X86: — | Y86: — | Z86: 菓初 | AA86: — | AB86: — | AC86: — | AD86: — | AL86: e
B87: =ROW()-3 -> 84 | C87: ○ | K87: B_マスタ | L87: 01_商品・ブランドマスタ | O87: チョコパイプレミアム | P87: チョコパイプレミアム | Q87: チョコパイPR | R87: 個売りのチョコパイにプレミアム素材を使用した上位品。笠間栗（茨城県産）・安納芋（鹿児島県産）等の季節素材を使用したスポット商品として展開し、いもくり催事やプレミアム需要を取り込む。 | T87: 円 | U87: いもくり催事提案・個売り定番拡大・本社対策活用 | V87: — | W87: — | X87: — | Y87: — | Z87: 営政 | AA87: — | AB87: — | AC87: — | AD87: — | AL87: e
B88: =ROW()-3 -> 85 | K88: B_マスタ | L88: 01_商品・ブランドマスタ | O88: デイリープレミアム | P88: デイリープレミアム | Q88: — | R88: 日常的に購入できる価格帯で高品質・高付加価値を訴求するアイス商品ポジション。ハーゲンダッツ等のプレミアムアイスよりは低価格だが、通常品より付加価値の高い価格帯。 | T88: — | U88: — | V88: — | W88: — | X88: — | Y88: — | Z88: 営政 | AA88: — | AB88: — | AC88: — | AD88: — | AL88: e
B89: =ROW()-3 -> 86 | K89: B_マスタ | L89: 01_商品・ブランドマスタ | O89: デンタル | P89: デンタル | Q89: ー | R89: ガム市場のサブカテゴリの一つ。歯の健康・口腔ケアを主な訴求軸とするガム商品。虫歯予防・歯を白くする・歯周病ケア等の機能性を前面に打ち出した商品群。市場構成比最大（45.1%）のカテゴリ。 | T89: ー | U89: ガムサブカテゴリ別市場分析 | V89: — | W89: — | X89: — | Y89: — | Z89: 菓初 | AA89: — | AB89: — | AC89: — | AD89: — | AL89: e
B90: =ROW()-3 -> 87 | C90: ○ | K90: B_マスタ | L90: 01_商品・ブランドマスタ | O90: トッポ（滋賀含む） | P90: トッポ（滋賀含む） | Q90: ー | R90: トッポブランド全品（浦和・滋賀工場合算）のシート内最上位集計行。 | S90: CR（滋賀除く） ＋ 滋賀工場生産トッポ分 | T90: ー | U90: — | V90: — | W90: — | X90: チョコレート生産計画表 | Y90: — | Z90: — | AA90: — | AB90: — | AC90: 月末事前チョコ, 協力チョコ, 滋賀チョコ, KYチョコ | AD90: — | AL90: e
B91: =ROW()-3 -> 88 | K91: B_マスタ | L91: 01_商品・ブランドマスタ | O91: トッポ8→7袋 | P91: トッポ8→7袋 | Q91: ー | R91: 規格変更後のトッポ品を集計した小計。 | S91: VDトッポ7袋 ＋ トッポ袋 ＋ トッポ7袋 | T91: ー | U91: — | V91: — | W91: — | X91: チョコレート生産計画表 | Y91: — | Z91: — | AA91: — | AB91: — | AC91: 月末事前チョコ, 協力チョコ, 滋賀チョコ, KYチョコ | AD91: — | AL91: e
B92: =ROW()-3 -> 89 | C92: ○ | K92: B_マスタ | L92: 01_商品・ブランドマスタ | O92: トッポザショコラ | P92: トッポザショコラ | Q92: ー | R92: トッポザショコラブランドの全品目を集計した小計。 | S92: トッポザショコラ通常 ＋ トッポザショコラ品質変更（カカオ産地） ＋ トッポザショコラオーバーハング25/6生産～ | T92: ー | U92: — | V92: — | W92: — | X92: チョコレート生産計画表 | Y92: — | Z92: — | AA92: — | AB92: — | AC92: 月末事前チョコ, 協力チョコ, 滋賀チョコ, KYチョコ | AD92: — | AL92: e
B93: =ROW()-3 -> 90 | K93: B_マスタ | L93: 01_商品・ブランドマスタ | O93: トッポ味通年 | P93: トッポ味通年 | Q93: ー | R93: トッポブランドの通年フレーバー展開品を集計した小計。 | S93: トッポ冬の濃厚ホワイト ＋ トッポピスタチオ＆ベリー ＋ トッポ＜ザ・ストロベリー＞ | T93: ー | U93: — | V93: — | W93: — | X93: チョコレート生産計画表 | Y93: — | Z93: — | AA93: — | AB93: — | AC93: 月末事前チョコ, 協力チョコ, 滋賀チョコ, KYチョコ | AD93: — | AL93: e
B94: =ROW()-3 -> 91 | K94: B_マスタ | L94: 01_商品・ブランドマスタ | O94: トッポ味変 | P94: トッポ味変 | Q94: ー | R94: トッポブランドの期間限定フレーバー品をを集計した小計。 | S94: トッポナッツのキャラメリゼ ＋ トッポ厳選香る抹茶 ＋ トッポロイヤルミルクティー | T94: ー | U94: — | V94: — | W94: — | X94: チョコレート生産計画表 | Y94: — | Z94: — | AA94: — | AB94: — | AC94: 月末事前チョコ, 協力チョコ, 滋賀チョコ, KYチョコ | AD94: — | AL94: e
B95: =ROW()-3 -> 92 | K95: B_マスタ | L95: 01_商品・ブランドマスタ | O95: トリュフ | P95: トリュフ | Q95: ー | R95: トリュフチョコレートブランドの全品目を集計した小計。 | S95: アーモンド＆ヘーゼルプラリネ ＋ イスパハン ＋ サブレショコラ＜ソルティバター＞ ＋ Pガーナトリュフ(キャラメルマリアージュ) ＋ Pガーナトリュフ(アンフィニマンピスターシュ) ＋ Pガーナサブレショコラ＜深み抹茶＞（Wドラジェ） | T95: ー | U95: — | V95: — | W95: — | X95: チョコレート生産計画表 | Y95: — | Z95: — | AA95: — | AB95: — | AC95: 月末事前チョコ, 協力チョコ, 滋賀チョコ, KYチョコ | AD95: — | AL95: e
B96: =ROW()-3 -> 93 | K96: B_マスタ | L96: 01_商品・ブランドマスタ | O96: ナッツ | P96: ナッツ | Q96: ー | R96: チョコレート市場の機能別分類の一つ。チョコレートの中にアーモンド・ピーナッツ等のナッツ類が入っている商品。木の実・栗・クルミ・大豆を含む。 | T96: ー | U96: チョコレートサブカテゴリ別市場分析 | V96: — | W96: — | X96: — | Y96: — | Z96: 菓初 | AA96: — | AB96: — | AC96: — | AD96: — | AL96: e
B97: =ROW()-3 -> 94 | K97: B_マスタ | L97: 01_商品・ブランドマスタ | O97: パイ（浦和） | P97: パイ（浦和） | Q97: ー | R97: 浦和工場で生産するパイの実ブランド全品を集計した小計。 | S97: パイの実 ＋ 韓国パイの実 ＋ 留型パイの実（浦和工場分） | T97: ー | U97: — | V97: — | W97: — | X97: チョコレート生産計画表 | Y97: — | Z97: — | AA97: — | AB97: — | AC97: 月末事前チョコ, 協力チョコ, 滋賀チョコ, KYチョコ | AD97: — | AL97: e
B98: =ROW()-3 -> 95 | C98: ○ | K98: B_マスタ | L98: 01_商品・ブランドマスタ | O98: パイの実 | P98: パイの実 | Q98: ー | R98: パイの実ブランドの通年品を集計した小計。 | S98: パイの実品質R ＋ パイの実新デザ2面付 ＋ パイの実新包材10月店頭 ＋ パイの実※春夏デザイン ＋ パイの実'26秋冬 | T98: ー | U98: — | V98: — | W98: — | X98: チョコレート生産計画表 | Y98: — | Z98: — | AA98: — | AB98: — | AC98: 月末事前チョコ, 協力チョコ, 滋賀チョコ, KYチョコ | AD98: — | AL98: e
B99: =ROW()-3 -> 96 | C99: ○ | K99: B_マスタ | L99: 01_商品・ブランドマスタ | O99: パイの実SP | P99: パイの実SP | Q99: ー | R99: パイの実ブランドのSP品を集計した小計。 | S99: パイの実SP ＋ パイの実SP新デザイン10月店頭 ＋ パイの実シェアパック※春夏デザイン ＋ パイの実シェアパック'26秋冬 | T99: ー | U99: — | V99: — | W99: — | X99: チョコレート生産計画表 | Y99: — | Z99: — | AA99: — | AB99: — | AC99: 月末事前チョコ, 協力チョコ, 滋賀チョコ, KYチョコ | AD99: — | AL99: e
B100: =ROW()-3 -> 97 | C100: ○ | K100: B_マスタ | L100: 01_商品・ブランドマスタ | O100: パイの実SP ショコラ | P100: パイの実SP ショコラ | Q100: ー | R100: パイの実SPのショコラフレーバー品を集計した小計。 | S100: パイの実SPショコラVD ＋ パイの実SPショコラ新デザイン ＋ パイの実SPショコラ新デザイン10月店頭 ＋ パイの実SP＜深みショコラ＞※春夏デザイン ＋ パイの実SP＜深みショコラ＞'26秋冬 | T100: ー | U100: — | V100: — | W100: — | X100: チョコレート生産計画表 | Y100: — | Z100: — | AA100: — | AB100: — | AC100: 月末事前チョコ, 協力チョコ, 滋賀チョコ, KYチョコ | AD100: — | AL100: e
B101: =ROW()-3 -> 98 | K101: B_マスタ | L101: 01_商品・ブランドマスタ | O101: パイの実SP催事 | P101: パイの実SP催事 | Q101: ー | R101: パイの実SPの催事専用品を集計した小計。 | S101: パイの実SP大阪・関西万博デザイン ＋ パイの実SPハロウィン ＋ パイの実SPハロウィン26 | T101: ー | U101: — | V101: — | W101: — | X101: チョコレート生産計画表 | Y101: — | Z101: — | AA101: — | AB101: — | AC101: 月末事前チョコ, 協力チョコ, 滋賀チョコ, KYチョコ | AD101: — | AL101: e
B102: =ROW()-3 -> 99 | K102: B_マスタ | L102: 01_商品・ブランドマスタ | O102: パイの実SP味 | P102: パイの実SP味 | Q102: ー | R102: パイの実SPの各フレーバー品を集計した小計。 | S102: パイの実SPキャラメルショコラ ＋ パイの実SP抹茶 ＋ 冬のパイの実SP＜Wキャラメル＞ | T102: ー | U102: — | V102: — | W102: — | X102: チョコレート生産計画表 | Y102: — | Z102: — | AA102: — | AB102: — | AC102: 月末事前チョコ, 協力チョコ, 滋賀チョコ, KYチョコ | AD102: — | AL102: e
B103: =ROW()-3 -> 100 | K103: B_マスタ | L103: 01_商品・ブランドマスタ | O103: パイの実味 | P103: パイの実味 | Q103: ー | R103: パイの実の各フレーバー品を集計した小計。 | S103: パイの実ピスタチオ＆ストロベリー ＋ パイの実贅沢とちおとめタルト ＋ パイの実レアチーズケーキベリー仕立て ＋ パイの実メープルバターサンド | T103: ー | U103: — | V103: — | W103: — | X103: チョコレート生産計画表 | Y103: — | Z103: — | AA103: — | AB103: — | AC103: 月末事前チョコ, 協力チョコ, 滋賀チョコ, KYチョコ | AD103: — | AL103: e
B104: =ROW()-3 -> 101 | C104: ○ | K104: B_マスタ | L104: 01_商品・ブランドマスタ | O104: パイント | P104: パイント | Q104: ー | R104: アイスクリームの形態別分類の一つ。約473ml（1パイント）サイズの大容量カップアイス商品。欧米発祥の形態でプレミアムブランドが多く、自宅での贅沢消費を訴求。 | T104: ー | U104: アイスサブカテゴリ別市場分析 | V104: — | W104: — | X104: — | Y104: — | Z104: 氷初 | AA104: — | AB104: — | AC104: — | AD104: — | AL104: e
B105: =ROW()-3 -> 102 | K105: B_マスタ | L105: 01_商品・ブランドマスタ | O105: バッカス | P105: バッカス | Q105: ー | R105: バッカスブランドの全品目を集計した小計。 | S105: バッカス ＋ バッカス'26 | T105: ー | U105: — | V105: — | W105: — | X105: チョコレート生産計画表 | Y105: — | Z105: — | AA105: — | AB105: — | AC105: 月末事前チョコ, 協力チョコ, 滋賀チョコ, KYチョコ | AD105: — | AL105: e
B106: =ROW()-3 -> 103 | C106: ○ | K106: B_マスタ | L106: 01_商品・ブランドマスタ | O106: パルク | P106: パルク | Q106: — | R106: 業務用アイスの生販在計画表における分類区分の一つ。飲食店・給食施設等の業務用途向けに大容量で提供されるアイス製品群の合計。ベーシック・バラエティ・フルーツソルベ・匠のジェラート・留型バルクの5品目で構成される。 | S106: ベーシック + バラエティ + フルーツソルベ + 匠のジェラート + 留型バルク | T106: CS | U106: — | V106: — | W106: — | X106: 業務用アイス生販在計画表 | Y106: — | Z106: — | AA106: — | AB106: — | AC106: 月末事前アイス業,月末事前アイス市 | AD106: — | AL106: e
B107: =ROW()-3 -> 104 | C107: ○ | K107: B_マスタ | L107: 01_商品・ブランドマスタ | O107: ビックリマン | P107: ビックリマン | Q107: ー | R107: ビックリマンウエハースの全品目を集計した小計。 | S107: ポケピースウエハース ＋ ビックリマン ミャクミャクマン ＋ ビックリマン悪魔VS天使40thスペシャルエディション ＋ ビックリマンヘッドだらけ ＋ ビックリマンご当地東日本編 ＋ ビックリマンご当地西日本編 ＋ 浮世（各品） | T107: ー | U107: — | V107: — | W107: — | X107: チョコレート生産計画表 | Y107: — | Z107: — | AA107: — | AB107: — | AC107: 月末事前チョコ, 協力チョコ, 滋賀チョコ, KYチョコ | AD107: — | AL107: e
B108: =ROW()-3 -> 105 | C108: ○ | K108: B_マスタ | L108: 01_商品・ブランドマスタ | O108: ブランド | P108: ブランド | Q108: — | R108: キシリトール、ACUO、ガーナ等のブランド単位。 | T108: — | U108: 全営業帳票 | V108: — | W108: — | X108: — | Y108: — | Z108: 営政, 全営 | AA108: — | AB108: — | AC108: — | AD108: — | AL108: e
...

Sheet PL構成項目のマスタ
A1: ※BOのくくり | G1: ※PLのくくり
B2: 大分類 | C2: 中分類 | D2: 小分類 | H2: 大分類 | I2: 中分類 | J2: 小分類
B3: 総売上高 | H3: 総売上高
B4: 売上控除 | C4: フィ | H4: 売上控除 | I4: フィ
C5: 特売費(控除対象) | I5: 特売費（控除対象）
C6: 拡売費(控除対象) | I6: 拡売費（控除対象）
C7: 販売店手数料(控除対象) | I7: 注文獲得促進費（控除対象）
C8: 経費出荷 | I8: 運賃（直取引）
C9: 売上控除(輸出) | I9: 売上割引
C10: 手数料(直接取引) | I10: 手数料（直接取引）
B11: 純売上高 | H11: 純売上高
B12: 売上原価 | C12: 原料費 | H12: 売上原価 | I12: 原料費
C13: 包材費 | I13: 包材費
C14: 外注加工費 | D14: 外注原料費 | I14: 外注加工費
D15: 外注包材費 | I15: 直接労務費
D16: 外注成型費 | I16: 機械変動費
D17: 外注 | I17: 減価償却費
C18: 直接労務費 | I18: その他機械費
C19: 機械変動費 | I19: 間接費
C20: 機械固定費 | D20: 減価償却費 | I20: 評価・廃棄損
D21: その他機械費 | I21: 売上原価調整
C22: 間接費 | H22: 売上総利益
C23: 廃棄損 | H23: 販売費 | I23: 注文獲得費 | J23: フィ（控除対象外）
C24: 売上原価調整 | J24: 特売費（控除対象外）
B25: 売上総利益 | J25: 拡売費（控除対象外）
B26: 販売費 | C26: 注文獲得費 | D26: 特売費（控除対象外） | I26: 注文獲得促進費 | J26: 見本費（旧KK分）
D27: 拡売費（控除対象外） | J27: 見本費
D28: 注文獲得費調整 | J28: 市場対策費
C29: 注文獲得促進費 | D29: 販売店手数料（控除対象外） | J29: 自動販売機費
D30: 自動販売機費 | J30: フィールド関連費
D31: 注文獲得促進費（その他） | J31: 自動車費
D32: 注文獲得促進費（輸出） | J32: 販売店指導費
B33: 広告宣伝費 | C33: 媒体 | J33: 販売店手数料
C34: 広告宣伝費（その他） | J34: その他
C35: 広告宣伝費（輸出） | H35: 一般管理費 | I35: 運賃保管料 | J35: 運賃 | K35: 運賃(一次輸送費)
B36: 運賃保管料 | C36: 運賃 | K36: 運賃(二次輸送費)
C37: 保管料 | K37: 運賃(直取引)
C38: 運賃保管料（その他） | K38: 運賃(資材ｾﾝﾀｰ)
C39: 運賃保管料（輸出） | K39: 運賃(その他)
B40: 人件費 | J40: 保管料 | K40: 保管料(一次輸送費)
B41: 一般管理費 | K41: 運賃保管料(詰替資材)
K42: 運賃保管料(販促資材)
K43: 保管料(資材ｾﾝﾀｰ)
J44: その他 | K44: 運賃(原材料)
K45: 保管料(原材料)
K46: 保管料(工場製品倉庫)
B47: 総売上高 | I47: 広告宣伝費 | J47: 媒体
B48: 変動費 | C48: 売上控除 | J48: その他
C49: 原料費 | I49: 労務費 | J49: 給与
C50: 包材費 | J50: 賞与
C51: 外注加工費 | J51: 退職給付費用
C52: 直接労務費 | J52: 法定福利費
C53: 機械変動費 | J53: 雑給
C54: 運賃保管料 | I54: 一般経費 | J54: 商標権使用料
B55: 限界利益 | J55: 福利厚生費
B56: 固定費 | C56: 機械固定費 | J56: 消耗品費
C57: 間接費 | J57: 修繕費
C58: 廃棄損 | J58: 通信費
C59: 売上原価調整 | J59: 旅費交通費
C60: 販売費 | J60: 保険料
C61: 広告宣伝費 | J61: 公租公課
C62: 人件費 | J62: 自動車費
C63: 一般管理費 | J63: 酒税
B64: 営業利益 | J64: 賃借料
J65: 接待交際費
J66: 寄付金
J67: 減価償却費
J68: 電力費
J69: 水道燃料費
J70: 研究費
J71: 社員募集費
J72: 社員教育費
J73: 調査費
J74: 支払手数料
J75: 雑費
J76: 貸倒引当金繰入
H77: 営業利益
H78: 営業外収益 | I78: 受取利息
I79: 受取配当金
I80: 賃貸収入
I81: 為替差益
I82: 貸倒戻入益
I83: 雑収入
H84: 営業外費用 | I84: 支払利息
I85: 売上割引
I86: 賃貸原価
I87: 支払手数料
I88: 為替差損
I89: 休止資産償却
I90: 雑損失
H91: 経常利益
H92: 特別利益
H93: 特別損失
H94: 税引前利益
H95: 法人税
H96: 当期利益

Sheet ★ロッテ用語_用語辞書
B2: No | C2: 経営ダッシュボード | D2: 確認部門 | E2: 分科① | F2: 分科② | G2: 分科③ | H2: 分科④ | I2: 分科⑤ | J2: 分科⑥ | K2: 指標大分類 | L2: 指標タイプ Lv.1 | M2: 指標タイプ Lv.2 | N2: 指標タイプ Lv.3 | O2: 今後の正式名称 | P2: 現時点の資料での出現用語 | Q2: 略称/同義語 | R2: 定義 | S2: 算出式 / 構造 | T2: 単位 | U2: 使用シーン / 主な帳票 | Z2: 出典 | AH2: 要修正フラグ | AI2: 修正後 | AL2: e
U3: 営業 | V3: マーケ | W3: 生産 | X3: SCM | Y3: 経営戦略 ・収益企画 | Z3: 営業 | AA3: マーケ | AB3: 生産 | AC3: SCM | AD3: 経営戦略 ・収益企画 | AE3: 備考 | AF3: 確認対象部門 | AG3: 収益企画部担当者 | AH3: ドラフトに誤りがある場合1を記載 | AI3: 定義 | AJ3: 算出式 / 構造 | AK3: 単位 | AL3: e
B4: =ROW()-3 -> 1 | K4: C_ロッテ用語 | L4: 01_全社 | O4: 5品目 | P4: 5品目 | Q4: 5品目 | R4: ロッテの主要菓子5カテゴリー（ガム・チョコレート・キャンディ・ビスケット・その他?）の合計。全国営業会議・販売実績の集計単位。 | S4: ガム ＋ チョコレート ＋ キャンディ ＋ ビスケット（＋その他？） | T4: 円 | U4: 全国営業会議・販売実績 | V4: — | W4: — | X4: — | Y4: 経営報告 | Z4: 営政, 全営 | AA4: — | AB4: — | AC4: — | AD4: 3月販売実績 | AE4: ・菓子計にはスナック・開発・飲料含む（３月販売実績）とあり、５品目計の合計範囲要確認 | AL4: e
B5: =ROW()-3 -> 2 | K5: C_ロッテ用語 | L5: 02_営業 | O5: セルオフ | P5: セルオフ | Q5: セルオフ, CA期間, 出荷期限・店頭期限 | R5: 旧品番から新品番への切替時や終売時に設定する出荷・店頭販売の期限管理。開発計画表に「セルオフ期間」「出荷期限」「店頭期限」として記載される。旧在庫を計画的に消化するための管理指標。 | T5: — | U5: — | V5: 新製品・リフレッシュ開発計画表（品番切替管理） | W5: — | X5: 生販在計画での旧/新品番の切替管理 | Y5: — | Z5: — | AA5: 新製品開発計画, チョコ定例帳票 | AB5: — | AC5: 月末事前チョコ | AD5: — | AL5: e
B6: =ROW()-3 -> 3 | C6: ○ | K6: C_ロッテ用語 | L6: 02_営業 | O6: CVS | P6: CVS | Q6: コンビニ | R6: コンビニエンスストア。50-250㎡前後で14時間以上営業。 | T6: — | U6: 全営業帳票 | V6: — | W6: — | X6: 月次市況 | Y6: — | Z6: 菓初, 全営 | AA6: — | AB6: — | AC6: 月次市況3月 | AD6: — | AH6: 1 | AI6: 下の画像にある区分で管理 | AL6: e
B7: =ROW()-3 -> 4 | C7: ○ | K7: C_ロッテ用語 | L7: 02_営業 | O7: DRUG | P7: DRUG | Q7: ドラッグストア、DgS | R7: 薬品・ヘルスケア・ビューティ売上構成比50%以上の小売業。 | T7: — | U7: 全営業帳票 | V7: — | W7: — | X7: 月次市況 | Y7: — | Z7: 菓初, 営政 | AA7: — | AB7: — | AC7: 月次市況3月 | AD7: — | AH7: 1 | AL7: e
B8: =ROW()-3 -> 5 | C8: ○ | K8: C_ロッテ用語 | L8: 02_営業 | O8: DS | P8: DS | Q8: ディスカウントストア | R8: 薄利多売を戦略とする業態。 | T8: — | U8: 営業政策 | V8: — | W8: — | X8: — | Y8: — | Z8: 営政 | AA8: — | AB8: — | AC8: — | AD8: — | AH8: 1 | AL8: e
B9: =ROW()-3 -> 6 | C9: ○ | K9: C_ロッテ用語 | L9: 02_営業 | O9: EC | P9: EC | Q9: — | R9: ネット通販。コロナ禍で利用率伸長。 | T9: — | U9: 菓子はじめて | V9: — | W9: — | X9: — | Y9: — | Z9: 菓初 | AA9: — | AB9: — | AC9: — | AD9: — | AL9: e
B10: =ROW()-3 -> 7 | C10: ○ | K10: C_ロッテ用語 | L10: 02_営業 | O10: GMS | P10: GMS | Q10: 総合スーパー | R10: 総合スーパーマーケット。食料品・衣料品・生活用品を扱う。 | T10: — | U10: 菓子はじめて | V10: — | W10: — | X10: — | Y10: — | Z10: 菓初 | AA10: — | AB10: — | AC10: — | AD10: — | AL10: e
B11: =ROW()-3 -> 8 | C11: ○ | K11: C_ロッテ用語 | L11: 02_営業 | O11: HC | P11: HC | Q11: ホームセンター | R11: ホームセンターチャネル。タスクフォース対象（カインズ・DCM・島忠・コメリ・ジョイフル本田）。 | T11: — | U11: 営業政策 | V11: — | W11: — | X11: — | Y11: — | Z11: 営政 | AA11: — | AB11: — | AC11: — | AD11: — | AL11: e
B12: =ROW()-3 -> 9 | C12: ○ | K12: C_ロッテ用語 | L12: 02_営業 | O12: JAN | P12: JAN | Q12: JANコード | R12: 日本商品コード。 | S12: 13桁 | T12: コード | U12: 全商品マスタ | V12: — | W12: — | X12: — | Y12: — | Z12: 営政, TN | AA12: — | AB12: — | AC12: — | AD12: — | AL12: e
B13: =ROW()-3 -> 10 | C13: ○ | K13: C_ロッテ用語 | L13: 02_営業 | O13: SM | P13: SM | Q13: スーパー | R13: スーパーマーケット。生鮮の扱いが強く、商品売上構成比50%以上。 | T13: — | U13: 全営業帳票 | V13: — | W13: — | X13: 月次市況 | Y13: — | Z13: 菓初, 営政 | AA13: — | AB13: — | AC13: 月次市況3月 | AD13: — | AL13: e
B14: =ROW()-3 -> 11 | K14: C_ロッテ用語 | L14: 02_営業 | O14: SM大型店 | P14: SM大型店 | Q14: — | R14: SM のうち SRI区分で1000㎡以上の店舗。 | S14: 売場面積1000㎡以上 | T14: — | U14: 営業政策, 主要商品KPI | V14: — | W14: — | X14: — | Y14: — | Z14: 営政 | AA14: — | AB14: — | AC14: — | AD14: — | AL14: e
B15: =ROW()-3 -> 12 | K15: C_ロッテ用語 | L15: 02_営業 | O15: SM中・小型店 | P15: SM中・小型店 | Q15: — | R15: SM のうち SRI区分で1000㎡以下の店舗。 | S15: 売場面積1000㎡以下 | T15: — | U15: 営業政策 | V15: — | W15: — | X15: — | Y15: — | Z15: 営政 | AA15: — | AB15: — | AC15: — | AD15: — | AL15: e
B16: =ROW()-3 -> 13 | K16: C_ロッテ用語 | L16: 02_営業 | O16: 未開拓小売業 | P16: 未開拓小売業 | Q16: ー | T16: 企業 | U16: — | V16: — | W16: — | X16: — | Y16: 本部KPI | Z16: — | AA16: — | AB16: — | AC16: — | AD16: 本部KPI確認 | AL16: e
B17: =ROW()-3 -> 14 | K17: C_ロッテ用語 | L17: 02_営業 | O17: 企業店舗コード | P17: 企業店舗コード | Q17: — | R17: 実績管理する小売業店舗コード。 | S17: 8始まりの8桁 | T17: コード | U17: 店出システム | V17: — | W17: — | X17: — | Y17: — | Z17: 推進M, 菓初 | AA17: — | AB17: — | AC17: — | AD17: — | AL17: e
B18: =ROW()-3 -> 15 | K18: C_ロッテ用語 | L18: 02_営業 | O18: 企業法人コード | P18: 企業法人コード | Q18: — | R18: 実績管理する大元の企業（小売業）法人コード。 | S18: 7始まりの8桁 | T18: コード | U18: WebPerformer, 店出システム | V18: — | W18: — | X18: — | Y18: — | Z18: 推進M, 菓初 | AA18: — | AB18: — | AC18: — | AD18: — | AL18: e
B19: =ROW()-3 -> 16 | K19: C_ロッテ用語 | L19: 02_営業 | O19: 直送店 | P19: 直送店 | Q19: — | R19: 特約店付随の卸（小売業専用・特売・冷温センター等）。 | S19: 5始まりの8桁 | T19: コード | U19: WebPerformer | V19: — | W19: — | X19: — | Y19: — | Z19: 推進M, 菓初 | AA19: — | AB19: — | AC19: — | AD19: — | AL19: e
B20: =ROW()-3 -> 17 | K20: C_ロッテ用語 | L20: 02_営業 | O20: 特約店 | P20: 特約店 | Q20: — | R20: ロッテが直接お金のやり取りをする卸店。約280企業（菓子、社内口座除く）。 | S20: 売上30百万以上、信用評価D以上 等の基準 | T20: — | U20: 特約店マスタ | V20: — | W20: — | X20: — | Y20: — | Z20: 推進M, 菓初 | AA20: — | AB20: — | AC20: — | AD20: — | AL20: e
B21: =ROW()-3 -> 18 | K21: C_ロッテ用語 | L21: 02_営業 | O21: 二次店 | P21: 二次店 | Q21: — | R21: 特約店経由で取引する卸。請求・支払は特約店経由。 | T21: — | U21: 卸マスタ | V21: — | W21: — | X21: — | Y21: — | Z21: 推進M, 菓初 | AA21: — | AB21: — | AC21: — | AD21: — | AL21: e
B22: =ROW()-3 -> 19 | K22: C_ロッテ用語 | L22: 02_営業 | O22: 1/2許容（賞味期限） | P22: 1/2許容（賞味期限） | Q22: — | R22: 賞味期限の残存が1/2を切った製品でも受け入れを許容する得意先条件。通常は個別商談・重点企業との合意が必要。 | T22: — | U22: — | V22: — | W22: — | X22: 受注管理・物流管理 | Y22: — | Z22: — | AA22: — | AB22: — | AC22: 生販物流KO②, プロテイン質問 | AD22: — | AL22: e
B23: =ROW()-3 -> 20 | K23: C_ロッテ用語 | L23: 02_営業 | O23: 1/3ルール | P23: 1/3ルール | Q23: — | R23: 卸・小売業が製品を受け入れる際に要求する賞味期限残存条件の一つ。賞味期限の2/3以上残っていることを納品条件とするルール。例：賞味期限24か月商品では残存16か月以上必要。 | T23: — | U23: — | V23: — | W23: — | X23: 受注管理・物流管理 | Y23: — | Z23: — | AA23: — | AB23: — | AC23: 生販物流KO | AD23: — | AL23: e
B24: =ROW()-3 -> 21 | K24: C_ロッテ用語 | L24: 02_営業 | O24: FMS | P24: FMS | Q24: ラウンダー | R24: 業務委託の店頭ラウンダー（株式会社フィールドマーケティングシステムズ）。 | T24: — | U24: ドラッグ12企業フォロー | V24: — | W24: — | X24: — | Y24: — | Z24: 菓初 | AA24: — | AB24: — | AC24: — | AD24: — | AL24: e
B25: =ROW()-3 -> 22 | K25: C_ロッテ用語 | L25: 02_営業 | O25: HDからのシェア奪取 | P25: HDからのシェア奪取 | Q25: HD奪取 | R25: ハーゲンダッツ（HD）が2025年に大幅な価格改定を実施したことに伴い、プレミアムアイス市場でハーゲンダッツから消費者を取り込む戦略。「アジアに恋して」等のデイリープレミアム商品で対応。 | T25: — | U25: アイスプレミアム市場戦略, 得意先商談 | V25: — | W25: — | X25: — | Y25: — | Z25: 全営 | AA25: — | AB25: — | AC25: — | AD25: — | AL25: e
B26: =ROW()-3 -> 23 | K26: C_ロッテ用語 | L26: 02_営業 | O26: LP | P26: LP | Q26: ロッテプロパー | R26: ロッテの直接雇用販売員。担当店舗を定期巡回。 | T26: — | U26: 店舗フォロー | V26: — | W26: — | X26: — | Y26: — | Z26: 菓初, 推進M | AA26: — | AB26: — | AC26: — | AD26: — | AL26: e
B27: =ROW()-3 -> 24 | K27: C_ロッテ用語 | L27: 02_営業 | O27: LP活動カレンダー | P27: LP活動カレンダー | Q27: LPカレンダー | R27: ロッテプロパー（LP）の月次活動テーマと重点取り組み商品をスケジュール化したカレンダー。年度ごとに策定され、母の日・歯と口の健康週間・爽/クーリッシュ・キシリトール等の季節テーマを設定。「噛むチャレ」は通年テーマとして別途設定される。 | T27: — | U27: LP活動管理, 売場開発年間計画 | V27: — | W27: — | X27: — | Y27: — | Z27: 全営 | AA27: — | AB27: — | AC27: — | AD27: — | AL27: e
B28: =ROW()-3 -> 25 | K28: C_ロッテ用語 | L28: 02_営業 | O28: MD | P28: MD | Q28: マーチャンダイザー | R28: 得意先側の商品担当者。バイヤーと並ぶ商談相手。 | T28: — | U28: タイムリーナレッジ | V28: — | W28: — | X28: — | Y28: — | Z28: TN | AA28: — | AB28: — | AC28: — | AD28: — | AL28: e
B29: =ROW()-3 -> 26 | C29: ○ | K29: C_ロッテ用語 | L29: 02_営業 | O29: NB | P29: NB | Q29: — | R29: NB＝National Brand（メーカーブランド）。 | T29: — | U29: 営業政策（チョコチャネル戦略） | V29: — | W29: — | X29: VC改革 | Y29: — | Z29: 営政 | AA29: — | AB29: — | AC29: 第3回SCM会議 | AD29: — | AL29: e
B30: =ROW()-3 -> 27 | C30: ○ | K30: C_ロッテ用語 | L30: 02_営業 | O30: PB | P30: PB | Q30: — | R30: PB＝Private Brand（小売業固有商品）。 | T30: — | U30: 営業政策（チョコチャネル戦略） | V30: — | W30: — | X30: VC改革 | Y30: — | Z30: 営政 | AA30: — | AB30: — | AC30: 第3回SCM会議 | AD30: — | AL30: e
B31: =ROW()-3 -> 28 | K31: C_ロッテ用語 | L31: 02_営業 | O31: PF企業 | P31: PF企業 | Q31: PF, ポートフォリオ企業 | R31: 重点取引先。Anaplan入力必須、タイムリーナレッジ入力必須対象。セグメント予算率の基礎。 | S31: セルイン予算率ベースで選定 | T31: — | U31: Anaplan, アクションプラン, タイムリーナレッジ | V31: — | W31: — | X31: — | Y31: — | Z31: TN, 推進M, 営政 | AA31: — | AB31: — | AC31: — | AD31: — | AL31: e
B32: =ROW()-3 -> 29 | K32: C_ロッテ用語 | L32: 02_営業 | O32: アイス取引制度 | P32: アイス取引制度 | Q32: 新仕切制度 | R32: 2021年度に改正されたアイスクリームの取引制度。建値制度の見直し・割戻制度廃止・新仕切価格設定・卸店対策改正・値差補填改正・フィ新基準設定を含む包括的な制度。 | T32: — | U32: アイス商談・取引制度管理 | V32: — | W32: — | X32: — | Y32: — | Z32: 氷初 | AA32: — | AB32: — | AC32: — | AD32: — | AL32: e
B33: =ROW()-3 -> 30 | K33: C_ロッテ用語 | L33: 02_営業 | O33: いい歯の日・歯と口の健康週間 | P33: いい歯の日・歯と口の健康週間 | Q33: いい歯の日 | R33: 11月8日「いい歯の日」および6月の「歯と口の健康週間」（4〜10日）。キシリトールブランドの最大訴求機会として、キシリトール最大展開・いい歯の日キャンペーン等の施策を集中投下する時期。 | T33: — | U33: キシリトール施策最大化, 店頭展開, 売場増設取組み | V33: — | W33: — | X33: — | Y33: — | Z33: 全営, 営政 | AA33: — | AB33: — | AC33: — | AD33: — | AL33: e
B34: =ROW()-3 -> 31 | K34: C_ロッテ用語 | L34: 02_営業 | O34: いもくりフェア | P34: いもくりフェア | Q34: いもくり催事 | R34: お盆明けの8月下旬〜10月頃にかけて実施される、さつまいも・栗フレーバー商品を集めた季節催事。スーパーやコンビニ各社が一斉にいもくりフェアを開催し、ロッテもチョコパイプレミアム・プレミアムガーナ等で対応する。 | T34: — | U34: いもくり催事売場獲得・陳列提案 | V34: — | W34: — | X34: — | Y34: — | Z34: 営政 | AA34: — | AB34: — | AC34: — | AD34: — | AL34: e
B35: =ROW()-3 -> 32 | K35: C_ロッテ用語 | L35: 02_営業 | O35: インバウンド需要 | P35: インバウンド需要 | Q35: インバウンド | R35: 訪日外国人観光客による国内消費需要。ドンキホーテ等の免税対応店舗での売場獲得・販促費投下の対象として管理される。菓子・アイスともにインバウンド対応強化が2026年度施策の一つ。 | T35: 円 | U35: 営業政策（特売費運用・インバウンド売場）, タイムリーナレッジ（インバウンド向け商材提案） | V35: — | W35: — | X35: — | Y35: — | Z35: 営政, TN | AA35: — | AB35: — | AC35: — | AD35: — | AL35: e
B36: =ROW()-3 -> 33 | K36: C_ロッテ用語 | L36: 02_営業 | O36: エリア重点施策 | P36: エリア重点施策 | Q36: エリア重点施策枠 | R36: 菓子7-8月・アイス11-12月の年2期間、統括支店が独自テーマ・対象商品・目標値を設定できる販売施策枠。本社統一対策とは別に統括支店の裁量で取り組みを立案できる。営業評価（統括支店組織評価）に加点項目として反映される。 | T36: — | U36: 統括支店施策立案・倉入/店出目標設定・エリア重点施策申請書 | V36: — | W36: — | X36: — | Y36: — | Z36: 営政 | AA36: — | AB36: — | AC36: — | AD36: — | AL36: e
B37: =ROW()-3 -> 34 | K37: C_ロッテ用語 | L37: 02_営業 | O37: エンカレッジ | P37: エンカレッジ | Q37: encourage | R37: 受注管理部またはアイス部門での奨励・推進活動。主に得意先や社内向けの販促・目標達成促進活動。 | T37: — | U37: — | V37: — | W37: — | X37: 受注管理・販促活動 | Y37: — | Z37: — | AA37: — | AB37: — | AC37: アイスエンカレ | AD37: — | AL37: e
B38: =ROW()-3 -> 35 | K38: C_ロッテ用語 | L38: 02_営業 | O38: エンジョイハロウィン | P38: エンジョイハロウィン | Q38: エンジョイHW, ハロウィン限定商品 | R38: ロッテのハロウィン季節限定商品ライン。2026年テーマは「ENJOY 黒（ブラック）HALLOWEEN！」で、新キャラ「コアラのニャーチ」を起用したコアラのマーチ・パイの実・チョコパイのシェアパック・パーティーパックを展開。 | T38: 円 | U38: ハロウィン催事提案・売場陳列・シェアパック提案 | V38: — | W38: — | X38: — | Y38: — | Z38: 営政 | AA38: — | AB38: — | AC38: — | AD38: — | AL38: e
B39: =ROW()-3 -> 36 | K39: C_ロッテ用語 | L39: 02_営業 | O39: エンド | P39: エンド | Q39: エンド展開 | R39: 店頭の什器の端（エンド）への商品展開。 | T39: — | U39: 商談, 店頭展開 | V39: — | W39: — | X39: — | Y39: — | Z39: 菓初, TN | AA39: — | AB39: — | AC39: — | AD39: — | AL39: e
B40: =ROW()-3 -> 37 | K40: C_ロッテ用語 | L40: 02_営業 | O40: キット | P40: キット | Q40: ディスプレイ | R40: 店頭での販促資材。ショッパー接点増加に寄与。 | T40: — | U40: SPinno, 営業活動 | V40: — | W40: — | X40: — | Y40: — | Z40: 菓初 | AA40: — | AB40: — | AC40: — | AD40: — | AL40: e
B41: =ROW()-3 -> 38 | K41: C_ロッテ用語 | L41: 02_営業 | O41: キット展開 | P41: キット展開 | Q41: — | R41: キット販促を展開すること。市場前比に対するキット展開企業の前比効果を測定。 | T41: — | U41: 営業活動 | V41: — | W41: — | X41: — | Y41: — | Z41: 菓初 | AA41: — | AB41: — | AC41: — | AD41: — | AL41: e
B42: =ROW()-3 -> 39 | K42: C_ロッテ用語 | L42: 02_営業 | O42: ショッパー | P42: ショッパー | Q42: ショッパー接点 | R42: 店舗での買物客／商品との接触機会。 | T42: — | U42: 営業活動 | V42: — | W42: — | X42: — | Y42: — | Z42: 菓初 | AA42: — | AB42: — | AC42: — | AD42: — | AL42: e
B43: =ROW()-3 -> 40 | K43: C_ロッテ用語 | L43: 02_営業 | O43: タイムリーナレッジ | P43: タイムリーナレッジ | Q43: — | R43: 営業情報共有の仕組み。商談アンケート→ダッシュボード可視化→営業情報共有会の流れ。 | T43: — | U43: Salesforce, 営業情報共有会 | V43: — | W43: — | X43: — | Y43: — | Z43: TN | AA43: — | AB43: — | AC43: — | AD43: — | AL43: e
... B52: =ROW()-3 -> 49 | K52: C_ロッテ用語 | L52: 02_営業 | O52: マストバイCP | P52: マストバイCP | Q52: マストバイキャンペーン | R52: 消費者が対象商品を購入するとポイントやプレゼントがもらえるキャンペーン施策。ロッテグミ（カジッテ等）で展開し、新規購入を促す目的で実施。 | T52: — | U52: グミ新商品発売時施策・消費者プロモーション | V52: — | W52: — | X52: — | Y52: — | Z52: 営政 | AA52: — | AB52: — | AC52: — | AD52: — | AL52: e
B53: =ROW()-3 -> 50 | K53: C_ロッテ用語 | L53: 02_営業 | O53: リージョン | P53: リージョン | Q53: — | R53: CVS以外の地域SM・DRUG等を総称する内部用語。SRIデータ上の区分。 | S53: 全業態 − CVS | T53: — | U53: 営業政策, 主要商品KPI | V53: — | W53: — | X53: — | Y53: — | Z53: 営政 | AA53: — | AB53: — | AC53: — | AD53: — | AL53: e
B54: =ROW()-3 -> 51 | K54: C_ロッテ用語 | L54: 02_営業 | O54: レール卸 | P54: レール卸 | Q54: ー | R54: レール売店（鉄道駅構内・新幹線車内等の売店）への販売構成比が50%以上の卸店。 | T54: ー | U54: 卸分類 | V54: — | W54: — | X54: — | Y54: — | Z54: 菓初 | AA54: — | AB54: — | AC54: — | AD54: — | AL54: e
B55: =ROW()-3 -> 52 | K55: C_ロッテ用語 | L55: 02_営業 | O55: レンタルアイスストッカー | P55: レンタルアイスストッカー | Q55: レンタルストッカー | R55: ロッテが費用を負担して小売店に設置しているアイス専用冷凍ストッカー。アイス最需要期（6〜8月）での自社商品陳列機会を増やし、売上拡大を狙う。設置費・レンタル費・撤去費を本社が拠出。 | S55: レンタル費用：2万円/月、設置費・撤去費：各7,500円 | T55: 円/月 | U55: アイス売場拡大・夏季店有拡大施策・本社対策申請 | V55: — | W55: — | X55: — | Y55: — | Z55: 氷初, 営政 | AA55: — | AB55: — | AC55: — | AD55: — | AL55: e
B56: =ROW()-3 -> 53 | K56: C_ロッテ用語 | L56: 02_営業 | O56: 営業情報共有会 | P56: 営業情報共有会 | Q56: — | R56: 月次の営業情報共有定例会議。 | T56: — | U56: 毎月実施 | V56: — | W56: — | X56: — | Y56: — | Z56: TN | AA56: — | AB56: — | AC56: — | AD56: — | AL56: e
B57: =ROW()-3 -> 54 | K57: C_ロッテ用語 | L57: 02_営業 | O57: 応酬話法 | P57: 応酬話法 | Q57: — | R57: 商談時のバイヤー対応トーク。タイムリーナレッジで蓄積。 | T57: — | U57: タイムリーナレッジ | V57: — | W57: — | X57: — | Y57: — | Z57: TN | AA57: — | AB57: — | AC57: — | AD57: — | AL57: e
B58: =ROW()-3 -> 55 | K58: C_ロッテ用語 | L58: 02_営業 | O58: 外部品番 | P58: 外部品番 | Q58: ー | R58: 生販在計画表で使用する商品コード体系。外部品番はJAN/取引先向けコード（5〜6桁）生 | T58: コード | U58: — | V58: — | W58: — | X58: 生販在計画表（全カテゴリ）、SAPとの在庫連携 | Y58: — | Z58: — | AA58: — | AB58: — | AC58: 月末事前ガム, 月末事前キャン, 月末事前ビス, 月末事前チョコ, 月末事前アイス業, 月末事前アイス市 | AD58: — | AL58: e
B59: =ROW()-3 -> 56 | K59: C_ロッテ用語 | L59: 02_営業 | O59: 概況 | P59: 概況 | Q59: ー | R59: 月次の状況報告。Anaplanで作成。 | T59: 円 | U59: Anaplan, 月次帳票 | V59: — | W59: — | X59: 生販会議（月次概況報告） | Y59: — | Z59: 推進M, 全営 | AA59: — | AB59: — | AC59: 生販会議 | AD59: — | AL59: e
B60: =ROW()-3 -> 57 | K60: C_ロッテ用語 | L60: 02_営業 | O60: 覚書 | P60: 覚書 | Q60: — | R60: 取引条件を毎年新年度から見直すため、毎年取得。主に基本フィと直送に関する内容。 | T60: — | U60: 年契管理 | V60: — | W60: — | X60: — | Y60: — | Z60: 菓初 | AA60: — | AB60: — | AC60: — | AD60: — | AL60: e
B61: =ROW()-3 -> 58 | K61: C_ロッテ用語 | L61: 02_営業 | O61: 噛むこと取り組み | P61: 噛むこと取り組み | Q61: 噛むこと活動 | R61: 「噛むこと」の効能認知・意向向上を通じてガム・グミカテゴリーの活性化を図る、ロッテ営業本部の中長期的な社会貢献型マーケティング活動。自治体との連携協定締結から「継続的な課題解決」フェーズへ移行中。KPIは「全国 噛むこと効能認知」と「噛むこと意向」の数値向上。 | T61: % | U61: 自治体連携提案, 歯科連携活動, 店頭売場提案 | V61: — | W61: — | X61: — | Y61: — | Z61: 全営, 推進M | AA61: — | AB61: — | AC61: — | AD61: — | AL61: e
B62: =ROW()-3 -> 59 | K62: C_ロッテ用語 | L62: 02_営業 | O62: 噛むチャレ | P62: 噛むチャレ | Q62: 噛むこと売場作りチャレンジ | R62: ガム・グミカテゴリーの売場活性化を目的に、LP（ロッテプロパー）全員を対象として毎月実施する好事例選抜制度。Salesforceのマンスリーレポートに「噛むチャレ」タイトルで投稿し、毎月5名を表彰・景品贈呈する。2026年4月〜2027年3月で通年実施。 | T62: — | U62: LP活動管理, 売場開発推進, 月次報告（Salesforce） | V62: — | W62: — | X62: — | Y62: — | Z62: 全営 | AA62: — | AB62: — | AC62: — | AD62: — | AL62: e
B63: =ROW()-3 -> 60 | K63: C_ロッテ用語 | L63: 02_営業 | O63: 企業商品別収益構造改革 | P63: 企業商品別収益構造改革 | Q63: 収益構造改革 | R63: 営業本部が推進する取り組みで、企業別・商品別に「見なし利益」を算出し、利益率の低い企業の改善プランを商品単位で設定する。企業アクションプランとしてローリング管理する。 | S63: 売上 − 商品別実際原価 − 物流費 | T63: 円 | U63: 企業アクションプラン・営業政策 | V63: — | W63: — | X63: — | Y63: — | Z63: 営政 | AA63: — | AB63: — | AC63: — | AD63: — | AL63: e
B64: =ROW()-3 -> 61 | K64: C_ロッテ用語 | L64: 02_営業 | O64: 企業別大陳コンテスト | P64: 企業別大陳コンテスト | Q64: 大陳コンテスト | R64: 特定企業（PF企業・地区重点企業等）が自社でエンド等の大型陳列コンテストを開催し、売場獲得・回転促進を図る本社対策の施策形式。本社がインセンティブ費用（企業総店舗数×30%×1万円が目安）を拠出する。 | T64: ー | U64: アイスエンド売場獲得・本社施策申請 | V64: — | W64: — | X64: — | Y64: — | Z64: 営政 | AA64: — | AB64: — | AC64: — | AD64: — | AL64: e
B65: =ROW()-3 -> 62 | K65: C_ロッテ用語 | L65: 02_営業 | O65: 規定外値差 | P65: 規定外値差 | Q65: — | R65: 規定値差を超える条件提示。申請書の提出（規定外値差使用申請書）が必要。 | S65: 申請書ベース | T65: — | U65: Anaplan, シャチ畑任三郎君 | V65: — | W65: — | X65: — | Y65: — | Z65: 菓初 | AA65: — | AB65: — | AC65: — | AD65: — | AL65: e
B66: =ROW()-3 -> 63 | C66: ○ | K66: C_ロッテ用語 | L66: 02_営業 | O66: 業務用 | P66: 業務用 | Q66: — | R66: 業務用チャネル（外食産業向け）。アイスでは独立カット。 | T66: 円 | U66: 予算表 | V66: — | W66: — | X66: — | Y66: — | Z66: 営政, 全営 | AA66: — | AB66: — | AC66: — | AD66: — | AL66: e
B67: =ROW()-3 -> 64 | K67: C_ロッテ用語 | L67: 02_営業 | O67: 禁止値差 | P67: 禁止値差 | Q67: — | R67: 値差上限の全国統一化により、廉価販売によるブランド毀損を防ぐための上限。 | S67: 本社統一基準 | T67: 円 | U67: 禁止値差対象品リスト | V67: — | W67: — | X67: SCM会議（特売費適正化・値差上限設定検討） | Y67: — | Z67: 菓初, 営政 | AA67: — | AB67: — | AC67: SCM会議, 第3回SCM議事録 | AD67: — | AL67: e
B68: =ROW()-3 -> 65 | K68: C_ロッテ用語 | L68: 02_営業 | O68: 限界利益率に基づいた販売戦略 | P68: 限界利益率に基づいた販売戦略 | Q68: 限界利益率販売戦略 | R68: 各商品の限界利益率（売上 − 変動費）を基準に販売シフト先を決める戦略。低利益率商品から高利益率商品へ販売構成を移すことで、売上増加なしに利益改善を図る。全国営業会議でチョコ・ビスケット等に適用。 | S68: 限界利益率 = （売上 − 変動費） ÷ 売上 × 100 | T68: % | U68: 月次営業会議, 年度チャネル別戦略, 商品別収益管理 | V68: — | W68: — | X68: — | Y68: — | Z68: 全営, 営政 | AA68: — | AB68: — | AC68: — | AD68: — | AL68: e
B69: =ROW()-3 -> 66 | K69: C_ロッテ用語 | L69: 02_営業 | O69: 広域卸 | P69: 広域卸 | Q69: — | R69: 通常卸の中で全国に出先が存在する卸店。 | T69: — | U69: 卸分類 | V69: — | W69: — | X69: — | Y69: — | Z69: 菓初 | AA69: — | AB69: — | AC69: — | AD69: — | AL69: e
B70: =ROW()-3 -> 67 | K70: C_ロッテ用語 | L70: 02_営業 | O70: 広域販促ツール | P70: 広域販促ツール | Q70: — | R70: SCM部門が管理する広域向け販売促進関連のツール。SCMDX推進課・需給部が利用。不具合対応中（2026年5月時点）。 | T70: — | U70: — | V70: — | W70: — | X70: 広域販促ツール不具合修正, 需給部 | Y70: — | Z70: — | AA70: — | AB70: — | AC70: 臼井T | AD70: — | AL70: e
B71: =ROW()-3 -> 68 | K71: C_ロッテ用語 | L71: 02_営業 | O71: 催事 | P71: 催事 | Q71: 52週MD | R71: 季節催事（母の日、バレンタイン等）に合わせた商品展開。 | T71: — | U71: 営業活動 | V71: — | W71: — | X71: — | Y71: — | Z71: 菓初, 氷初 | AA71: — | AB71: — | AC71: — | AD71: — | AL71: e
B72: =ROW()-3 -> 69 | K72: C_ロッテ用語 | L72: 02_営業 | O72: 最終見込差 | P72: 最終見込差 | Q72: — | R72: 最終（1か月前）見込と実績の差。誤差率±5%以上が見込精度改善の対象。 | S72: 実績 − 最終見込 | T72: 円, % | U72: 月次見込差表 | V72: — | W72: — | X72: — | Y72: — | Z72: 全営 | AA72: — | AB72: — | AC72: — | AD72: — | AL72: e
B73: =ROW()-3 -> 70 | K73: C_ロッテ用語 | L73: 02_営業 | O73: 採用アイテム数 | P73: 採用アイテム数 | Q73: ー | R73: 特定の小売チェーン・店舗において定番棚に採用されたロッテ商品のSKU（品目）数。採用アイテム数が増えるほど定番売上が拡大する。チェーン本部との商談により決定され、棚割への反映をもって採用とみなす。 | T73: — | U73: 棚割管理 | V73: — | W73: — | X73: — | Y73: — | Z73: 氷初 | AA73: — | AB73: — | AC73: — | AD73: — | AL73: e
B74: =ROW()-3 -> 71 | K74: C_ロッテ用語 | L74: 02_営業 | O74: 終売 | P74: 終売 | Q74: — | R74: 商品販売終了。 | T74: — | U74: 営業計画 | V74: — | W74: — | X74: — | Y74: — | Z74: TN, 全営 | AA74: — | AB74: — | AC74: — | AD74: — | AL74: e
B75: =ROW()-3 -> 72 | K75: C_ロッテ用語 | L75: 02_営業 | O75: 初週動向 | P75: 初週動向 | Q75: 初週 | R75: 新商品の発売後1週間の販売実績・市場動向を分析した報告。SRI+データ（推計販売規模）・チャネル別実績・過去同時期品との比較を含む。マーケ本部の生販会議やナレッジMTGで報告される。 | T75: 個、円 | U75: — | V75: アイス生販会議、新製品レビューMTG | W75: — | X75: — | Y75: — | Z75: — | AA75: マーケ生販会議 | AB75: — | AC75: — | AD75: — | AL75: e
B76: =ROW()-3 -> 73 | K76: C_ロッテ用語 | L76: 02_営業 | O76: 商談アンケート | P76: 商談アンケート | Q76: タイムリーナレッジアンケート | R76: タイムリーナレッジの一環として、新商品・プロモーション商談後にPF企業担当（必須）・その他企業担当（任意）が商談2日後までに入力するSalesforce上のアンケート。バイヤーの評価（ポジティブ・ネガティブ）を収集する。 | S76: Salesforce営業支援 > アンケート より入力 | T76: — | U76: タイムリーナレッジ運用, 商談後報告, Salesforce | V76: — | W76: — | X76: — | Y76: — | Z76: TN | AA76: — | AB76: — | AC76: — | AD76: — | AL76: e
B77: =ROW()-3 -> 74 | K77: C_ロッテ用語 | L77: 02_営業 | O77: 商品スケジュール | P77: 商品スケジュール | Q77: 商品スケ, 発売スケ, 販売スケジュール | R77: マーケティング本部が管理する商品別の発売・切替・終売の時期をまとめた計画表。定番・2nd・3rd・季節・CVS先行等のカテゴリ別に、発売月・品質変更・デザイン変更の情報を含む。アイスでは生販会議資料に添付される。 | T77: — | U77: — | V77: アイス生販会議（マーケ）、新製品・リフレッシュ開発計画表 | W77: — | X77: — | Y77: — | Z77: — | AA77: マーケ生販会議, 新製品開発計画 | AB77: — | AC77: — | AD77: — | AL77: e
B78: =ROW()-3 -> 75 | K78: C_ロッテ用語 | L78: 02_営業 | O78: 新製品・リフレッシュ開発計画表 | P78: 新製品・リフレッシュ開発計画表 | Q78: 開発計画表 | R78: マーケ本部が管理する商品開発の進捗管理帳票。品番（外部・内部）・品名・発売月・開発担当・デザイン担当・工場・サンプル生産有無・本生産スケジュール・数量等を一元管理する。チョコ・アイス等カテゴリ別に作成。 | T78: — | U78: — | V78: 新製品開発進捗管理、定例会議（チョコ定例等） | W78: — | X78: — | Y78: — | Z78: — | AA78: 新製品開発計画, チョコ定例帳票 | AB78: — | AC78: — | AD78: — | AL78: e
B79: =ROW()-3 -> 76 | K79: C_ロッテ用語 | L79: 02_営業 | O79: 数決 | P79: 数決 | Q79: — | R79: 数量決定。商談で合意成立を意味する営業用語。 | T79: CS | U79: 商談記録 | V79: — | W79: — | X79: — | Y79: — | Z79: TN | AA79: — | AB79: — | AC79: — | AD79: — | AL79: e
B80: =ROW()-3 -> 77 | K80: C_ロッテ用語 | L80: 02_営業 | O80: 前月概況差 | P80: 前月概況差 | Q80: — | R80: 前月時点の概況予測と実績の差。 | S80: 実績 − 前月概況 | T80: 円, % | U80: 月次見込差表 | V80: — | W80: — | X80: — | Y80: — | Z80: 全営 | AA80: — | AB80: — | AC80: — | AD80: — | AL80: e
B81: =ROW()-3 -> 78 | K81: C_ロッテ用語 | L81: 02_営業 | O81: 棚替え | P81: 棚替え | Q81: — | R81: 定番売場の商品配置実施。半期に一度実施が多い。 | T81: — | U81: StoreManager（棚割提案ツール） | V81: — | W81: — | X81: — | Y81: — | Z81: 菓初, 氷初 | AA81: — | AB81: — | AC81: — | AD81: — | AL81: e
B82: =ROW()-3 -> 79 | K82: C_ロッテ用語 | L82: 02_営業 | O82: 棚割 | P82: 棚割 | Q82: — | R82: 定番売場の商品配置計画。 | T82: — | U82: StoreManager（棚割提案ツール） | V82: — | W82: — | X82: — | Y82: — | Z82: 菓初, 氷初 | AA82: — | AB82: — | AC82: — | AD82: — | AL82: e
B83: =ROW()-3 -> 80 | K83: C_ロッテ用語 | L83: 02_営業 | O83: 棚貸し在庫補充 | P83: 棚貸し在庫補充 | Q83: ー | R83: 卸・小売の倉庫スペースをロッテが借り受け（棚貸し）、在庫を補充・管理する方式。棚貸しへの移管数量決定・配車依頼・STS登録等の業務が発生する。 | T83: — | U83: — | V83: — | W83: — | X83: 課内MTG0428（棚貸し配車業務フロー・受注管理部への移管検討） | Y83: — | Z83: — | AA83: — | AB83: — | AC83: 課内MTG0428 | AD83: — | AL83: e
B84: =ROW()-3 -> 81 | K84: C_ロッテ用語 | L84: 02_営業 | O84: 値差基準変更 | P84: 値差基準変更 | Q84: 値差変更対策 | R84: 通常の規定値差に対して期間限定で値差を引き上げる本社統一対策の形式。「通常値差＋対策期間限定加算額」で最大値差を設定し、特売回転の促進を目的とする。対策期間終了後は通常値差に戻す。 | S84: 最大値差 ＝ 規定値差 ＋ 対策期間加算額 | T84: 円 | U84: 特売提案・本社統一対策申請 | V84: — | W84: — | X84: — | Y84: — | Z84: 営政 | AA84: — | AB84: — | AC84: — | AD84: — | AL84: e
B85: =ROW()-3 -> 82 | K85: C_ロッテ用語 | L85: 02_営業 | O85: 通常卸 | P85: 通常卸 | Q85: ー | R85: 小売業に対する物流・情報・リテールサポート等を行い、物流・商流を円滑にする機能を持つ卸店。ロッテ特約店の中心的な分類。 | U85: 卸分類 | V85: — | W85: — | X85: — | Y85: — | Z85: 菓初 | AA85: — | AB85: — | AC85: — | AD85: — | AL85: e
B86: =ROW()-3 -> 83 | K86: C_ロッテ用語 | L86: 02_営業 | O86: 定番採用契約 | P86: 定番採用契約 | Q86: 定番採用対策 | R86: 新商品・育成商品の定番導入促進を目的に、対象期間内の納品金額に対して一定率（例：3%）を本社経費として支払う年間または期間契約。スポット採用への適用は原則不可。 | S86: 支払額 ＝ 対象期間納品金額 × 契約率（例：3%） | T86: 円 | U86: 新商品定番獲得交渉・本部商談・Biz対策申請 | V86: — | W86: — | X86: — | Y86: — | Z86: 営政 | AA86: — | AB86: — | AC86: — | AD86: — | AL86: e
B87: =ROW()-3 -> 84 | K87: C_ロッテ用語 | L87: 02_営業 | O87: 統括支店監査 | P87: 統括支店監査 | Q87: — | R87: 7月・10月実施。統括支店の運営状況確認（残高・Biz運用・労務・契約書 等）。 | T87: — | U87: 営業企画部主催 | V87: — | W87: — | X87: — | Y87: — | Z87: 推進M | AA87: — | AB87: — | AC87: — | AD87: — | AL87: e
B88: =ROW()-3 -> 85 | K88: C_ロッテ用語 | L88: 02_営業 | O88: 特殊卸 | P88: 特殊卸 | Q88: ー | R88: 特殊売店（駅・空港・観光地・病院等の特定施設内店舗）への販売構成比が50%以上の卸店。 | U88: 卸分類 | V88: — | W88: — | X88: — | Y88: — | Z88: 菓初 | AA88: — | AB88: — | AC88: — | AD88: — | AL88: e
B89: =ROW()-3 -> 86 | K89: C_ロッテ用語 | L89: 02_営業 | O89: 特約小売店 | P89: 特約小売店 | Q89: ー | R89: 特約小売業および特殊売店における特約店。ロッテと直接取引をする小売・特殊売店。 | U89: 卸分類 | V89: — | W89: — | X89: — | Y89: — | Z89: 菓初 | AA89: — | AB89: — | AC89: — | AD89: — | AL89: e
B90: =ROW()-3 -> 87 | K90: C_ロッテ用語 | L90: 02_営業 | O90: 販売振り返りミーティング | P90: 販売振り返りミーティング | Q90: 振り返りMTG | R90: カテゴリ（アイス・ガム・チョコ・ビス・キャンディ）ごとに月次で実施する販売実績の振り返り会議。前月実績とSCM見込み・営業見込みの乖離をSKU単位で確認し、次月以降の見込み精度向上に活用。 | T90: — | U90: — | V90: — | W90: — | X90: 月次（カテゴリ別・需給部主催） | Y90: — | Z90: — | AA90: — | AB90: — | AC90: 振返アイス, 振返ガム, 振返キャン, 振返チョコ, 振返ビス | AD90: — | AL90: e
B91: =ROW()-3 -> 88 | K91: C_ロッテ用語 | L91: 02_営業 | O91: 販売費運用計画 | P91: 販売費運用計画 | Q91: — | R91: 年度の特売費・拡売費等の販売費を戦略的に配分・管理する計画。特売費の「削る企業」と「積極投下する企業」をポートフォリオで区分し、限界利益率の改善も組み合わせて推進する。 | T91: 円, % | U91: 営業政策・予算管理 | V91: — | W91: — | X91: — | Y91: — | Z91: 営政 | AA91: — | AB91: — | AC91: — | AD91: — | AL91: e
B92: =ROW()-3 -> 89 | K92: C_ロッテ用語 | L92: 02_営業 | O92: 非計画購買 | P92: 非計画購買 | Q92: — | R92: 事前計画なしの店頭での購入決定。キット・ディスプレイで促進。 | T92: — | U92: 営業活動 | V92: — | W92: — | X92: — | Y92: — | Z92: 菓初 | AA92: — | AB92: — | AC92: — | AD92: — | AL92: e
B93: =ROW()-3 -> 90 | K93: C_ロッテ用語 | L93: 02_営業 | O93: 本社統一対策 | P93: 本社統一対策 | Q93: 本社対策 | R93: ロッテ本社が全国統一条件で期間・対象商品・対象企業を設定し、本社経費を投下する販売施策。値差変更（規定値差の一時引き上げ）・協賛金（納品金額比率や個数ベースの戻し）等の形式で提供される。 | T93: 円 / ％ | U93: 本社統一対策申請（Biz対策）・得意先商談・特売提案 | V93: — | W93: — | X93: — | Y93: — | Z93: 営政 | AA93: — | AB93: — | AC93: — | AD93: — | AL93: e
B94: =ROW()-3 -> 91 | K94: C_ロッテ用語 | L94: 02_営業 | O94: 本部担当 | P94: 本部担当 | Q94: — | R94: 本部担当＝バイヤー対応アイスは本部担当中心。 | T94: — | U94: 営業活動 | V94: — | W94: — | X94: — | Y94: — | Z94: 菓初, 氷初 | AA94: — | AB94: — | AC94: — | AD94: — | AL94: e
B95: =ROW()-3 -> 92 | K95: C_ロッテ用語 | L95: 02_営業 | O95: 店舗担当 | P95: 店舗担当 | Q95: — | R95: 店舗担当＝店舗オペレーション対応。菓子は両者あり。 | T95: — | U95: 営業活動 | V95: — | W95: — | X95: — | Y95: — | Z95: 菓初, 氷初 | AA95: — | AB95: — | AC95: — | AD95: — | AL95: e
B96: =ROW()-3 -> 93 | K96: C_ロッテ用語 | L96: 02_営業 | O96: 戻し交渉 | P96: 戻し交渉 | Q96: — | R96: 値引書で見積より多い値引があった場合の返金交渉。 | T96: — | U96: Biz, 値引書 | V96: — | W96: — | X96: — | Y96: — | Z96: 菓初 | AA96: — | AB96: — | AC96: — | AD96: — | AL96: e
B97: =ROW()-3 -> 94 | K97: C_ロッテ用語 | L97: 02_営業 | O97: 遊技場卸 | P97: 遊技場卸 | Q97: ー | R97: 遊技場（パチンコ店・ゲームセンター等）への販売構成比が50%以上の卸店。 | U97: 卸分類 | V97: — | W97: — | X97: — | Y97: — | Z97: 菓初 | AA97: — | AB97: — | AC97: — | AD97: — | AL97: e
B98: =ROW()-3 -> 95 | K98: C_ロッテ用語 | L98: 02_営業 | O98: 帳合 | P98: 帳合 | Q98: チョウアイ | R98: 商品が卸店を経由して最終的に納品される得意先チェーンの紐付け関係。例：DIG帳合→ドン・キホーテ、ファイブセンス帳合→Amazon・楽天・アスクル・杏林堂。 | T98: — | U98: 菓子営業・アイス営業の取引制度（卸店管理） | V98: — | W98: — | X98: 受注管理・物流管理 | Y98: — | Z98: 菓初, 氷初 | AA98: — | AB98: — | AC98: 生販物流KO, プロテイン質問, 生販物流KO② | AD98: — | AL98: e
B99: =ROW()-3 -> 96 | K99: C_ロッテ用語 | L99: 02_営業 | O99: 差し替え | P99: 差し替え | Q99: 改廃 | R99: 既存品との入れ替え／商品ライフサイクル末端の入れ替え。 | T99: — | U99: 商品リフレッシュ | V99: — | W99: — | X99: — | Y99: — | Z99: TN, 営政 | AA99: — | AB99: — | AC99: — | AD99: — | AL99: e
B100: =ROW()-3 -> 97 | K100: C_ロッテ用語 | L100: 02_営業 | O100: Anaplan | P100: Anaplan | Q100: アナプラン | R100: 販売計画・商品要求・概況作成システム。PF企業の主要管理ツール。 | T100: — | U100: Anaplan | V100: — | W100: — | X100: — | Y100: — | Z100: 推進M, 菓初 | AA100: — | AB100: — | AC100: — | AD100: — | AL100: e
B101: =ROW()-3 -> 98 | K101: C_ロッテ用語 | L101: 02_営業 | O101: Biz | P101: Biz | Q101: — | R101: 販促費（値差/協賛金）の申請・精算システム。20万円超は稟議書要。 | T101: — | U101: 販促費管理 | V101: — | W101: — | X101: — | Y101: — | Z101: 推進M, 菓初 | AA101: — | AB101: — | AC101: — | AD101: — | AL101: e
B102: =ROW()-3 -> 99 | K102: C_ロッテ用語 | L102: 02_営業 | O102: Quicksight | P102: Quicksight | Q102: — | R102: POSデータ・市場データ確認用のBIツール。 | T102: — | U102: 営業分析 | V102: — | W102: — | X102: — | Y102: — | Z102: 菓初 | AA102: — | AB102: — | AC102: — | AD102: — | AL102: e
B103: =ROW()-3 -> 100 | K103: C_ロッテ用語 | L103: 02_営業 | O103: Salesforce | P103: Salesforce | Q103: セールスフォース | R103: 提案書・発売計画書・終売切替情報・商談情報・タイムリーナレッジを管理するCRM。 | T103: — | U103: Salesforce | V103: — | W103: — | X103: — | Y103: — | Z103: 推進M, 菓初, TN | AA103: — | AB103: — | AC103: — | AD103: — | AL103: e
B104: =ROW()-3 -> 101 | K104: C_ロッテ用語 | L104: 02_営業 | O104: SPinno | P104: SPinno | Q104: — | R104: 店頭資材要求・出荷システム。 | T104: — | U104: 資材管理 | V104: — | W104: — | X104: — | Y104: — | Z104: 菓初 | AA104: — | AB104: — | AC104: — | AD104: — | AL104: e
B105: =ROW()-3 -> 102 | K105: C_ロッテ用語 | L105: 02_営業 | O105: SRI+ | P105: SRI+ | Q105: — | R105: インテージ社の小売パネル調査データ（推計販売規模）。 | T105: — | U105: 市場分析 | V105: — | W105: — | X105: — | Y105: — | Z105: 営政, 菓初, TN | AA105: — | AB105: — | AC105: — | AD105: — | AL105: e
B106: =ROW()-3 -> 103 | K106: C_ロッテ用語 | L106: 02_営業 | O106: StoreManager | P106: StoreManager | Q106: — | R106: 棚割提案ツール。 | T106: — | U106: 棚割提案 | V106: — | W106: — | X106: — | Y106: — | Z106: 菓初 | AA106: — | AB106: — | AC106: — | AD106: — | AL106: e
B107: =ROW()-3 -> 104 | K107: C_ロッテ用語 | L107: 02_営業 | O107: WebPerformer | P107: WebPerformer | Q107: — | R107: 得意先・業者マスタ承認システム。 | T107: — | U107: マスタ管理 | V107: — | W107: — | X107: — | Y107: — | Z107: 推進M | AA107: — | AB107: — | AC107: — | AD107: — | AL107: e
B108: =ROW()-3 -> 105 | K108: C_ロッテ用語 | L108: 02_営業 | O108: アンケート集計ダッシュボード | P108: アンケート集計ダッシュボード | Q108: タイムリーナレッジDB, 集計DB | R108: タイムリーナレッジで収集した商談アンケートをリアルタイム集計・可視化するSalesforce上のダッシュボード。先行商談企業のバイヤーの声を即時確認できる。 | S108: Salesforceアンケート機能 → 集計 → ダッシュボード表示 | T108: — | U108: Salesforce, タイムリーナレッジ運用, 営業情報共有会 | V108: — | W108: — | X108: — | Y108: — | Z108: TN | AA108: — | AB108: — | AC108: — | AD108: — | AL108: e
B109: =ROW()-3 -> 106 | K109: C_ロッテ用語 | L109: 02_営業 | O109: 見える化DB | P109: 見える化DB | Q109: — | R109: 経営/営業の各種データを統合した参照DB。 | T109: — | U109: 経営/営業 | V109: — | W109: — | X109: — | Y109: — | Z109: 推進M | AA109: — | AB109: — | AC109: — | AD109: — | AL109: e
...

Sheet 99_区分マスタ
I1: e
I2: e
B3: 指標大分類 | C3: ※注 | D3: 指標タイプLv.1 | E3: ※注 | F3: 指標タイプLv.2 | G3: ※注 | H3: 指標タイプLv.3 | I3: e
B4: A_指標 | D4: 01_財務指標 | E4: 各種項目一覧 | F4: 01_PL | H4: 売上高 | I4: e
B5: A_指標 | D5: 01_財務指標 | F5: 01_PL | H5: 売上控除 | I5: e
B6: A_指標 | D6: 01_財務指標 | F6: 01_PL | H6: 売上原価 | I6: e
B7: A_指標 | D7: 01_財務指標 | F7: 01_PL | H7: 販管費 | I7: e
B8: A_指標 | D8: 01_財務指標 | F8: 01_PL | H8: 利益・損失 | I8: e
B9: A_指標 | D9: 01_財務指標 | F9: 02_BS | H9: 資産 | I9: e
B10: A_指標 | D10: 01_財務指標 | F10: 02_BS | H10: 負債 | I10: e
B11: A_指標 | D11: 01_財務指標 | F11: 03_CF | G11: 該当なし | I11: e
B12: A_指標 | D12: 02_業績管理・オペレーション指標 | E12: 部門KPIや日々業務で発生する数字 | F12: 01_商品開発 | H12: 利益項目 | I12: e
B13: A_指標 | D13: 02_業績管理・オペレーション指標 | F13: 01_商品開発 | H13: その他 | I13: e
B14: A_指標 | D14: 02_業績管理・オペレーション指標 | F14: 02_生販在 | H14: 生産 | I14: e
B15: A_指標 | D15: 02_業績管理・オペレーション指標 | F15: 02_生販在 | H15: 販売 | I15: e
B16: A_指標 | D16: 02_業績管理・オペレーション指標 | F16: 02_生販在 | H16: 在庫 | I16: e
B17: A_指標 | D17: 02_業績管理・オペレーション指標 | F17: 03_商品製造 | H17: 収益性 | I17: e
B18: A_指標 | D18: 02_業績管理・オペレーション指標 | F18: 03_商品製造 | H18: 生産性 | I18: e
B19: A_指標 | D19: 02_業績管理・オペレーション指標 | F19: 03_商品製造 | H19: 品質 | I19: e
B20: A_指標 | D20: 02_業績管理・オペレーション指標 | F20: 03_商品製造 | H20: 労務 | I20: e
B21: A_指標 | D21: 02_業績管理・オペレーション指標 | F21: 04_販売 | H21: 特売費項目 | I21: e
B22: A_指標 | D22: 02_業績管理・オペレーション指標 | F22: 04_販売 | H22: フィ項目 | I22: e
B23: A_指標 | D23: 02_業績管理・オペレーション指標 | F23: 04_販売 | H23: LP管理 | I23: e
B24: A_指標 | D24: 02_業績管理・オペレーション指標 | F24: 04_販売 | H24: 販売価格 | I24: e
... B36: A_指標 | D36: 02_業績管理・オペレーション指標 | F36: 06_コーポレート | H36: 非財務 | I36: e
B37: A_指標 | D37: 03_その他 | F37: - | I37: e
B38: B_マスタ | D38: 01_商品・ブランドマスタ | E38: 各種システムでマスタ扱いされているもの | I38: e
B39: B_マスタ | D39: 02_製造ラインマスタ | E39: （SAP 等） | I39: e
B40: B_マスタ | D40: 03_得意先マスタ | I40: e
B41: B_マスタ | D41: 04_プラントマスタ | I41: e
B42: B_マスタ | D42: 05_組織マスタ | I42: e
B43: B_マスタ | D43: 06_その他マスタ | I43: e
B44: C_ロッテ用語 | C44: 単純な用語の説明 | D44: 01_全社 | I44: e
B45: C_ロッテ用語 | D45: 02_営業 | I45: e
B46: C_ロッテ用語 | D46: 03_SCM | I46: e
B47: C_ロッテ用語 | D47: 04_生産 | I47: e
B48: C_ロッテ用語 | D48: 05_マーケ・研究 | I48: e
B49: C_ロッテ用語 | D49: 06_コーポレート | I49: e
B50: C_ロッテ用語 | D50: 07_その他 | I50: e
B51: e | C51: e | D51: e | E51: e | F51: e | G51: e | H51: e | I51: e

Sheet 出典
A1: 出典マスタ — ロッテグループ標準言語定義辞書 | E1: e
A2: 列の順序：①部門区分 ②略称（辞書の出典欄で使用する短縮形） ③正式名称 | E2: e
A3: ①部門区分 | B3: ②略称 | C3: ③正式名称／ファイル名 | D3: 備考 | E3: e
A4: SCM | B4: 臼井T | C4: 臼井さん_タスク一覧.xlsx | D4: SCMDX推進課のツール開発タスク管理表 | E4: e
A5: SCM | B5: SCM大会 | C5: 【投影】SCM大会260420.pptx | D5: 2026年4月SCM大会の投影資料 | E5: e
A6: SCM | B6: SCM会議 | C6: 20260316SCM会議資料.pptx | D6: 同名のpdfも同一資料 | E6: e
A7: SCM | B7: SCM本部会議 | C7: SCM本部会議_エグゼクティブサマリ_260424.pptx | D7: 2026年4月SCM本部会議エグゼクティブサマリ | E7: e
A8: SCM | B8: SCM戦略MTG | C8: 20260430SCM戦略部MTG.pptx | D8: 2026年4月SCM戦略部MTG資料 | E8: e
A9: SCM | B9: 月次報 | C9: ３月月次報告.pptx | D9: SCM需給部の欠品率・D+2締め率月次報告 | E9: e
A10: SCM | B10: 生販会議 | C10: 4月SCM生販会議資料_.pptx | D10: SCM需給部の販売振り返り・見込資料 | E10: e
A11: SCM | B11: 振返アイス | C11: アイス_3月度_販売振り返りミーティング.xlsx | D11: アイス3月度品目別販売振り返り | E11: e
A12: SCM | B12: 振返ガム | C12: ガム_2603_販売振り返りミーティング.xlsx | D12: ガム3月度品目別販売振り返り | E12: e
A13: SCM | B13: 振返キャン | C13: キャンディ_3月度_振り返りミーティング.xlsx | D13: キャンディ3月度品目別販売振り返り | E13: e
A14: SCM | B14: 振返チョコ | C14: チョコ_3月度_販売振り返りミーティング.xlsx | D14: チョコ3月度品目別販売振り返り | E14: e
... A21: SCM | B21: 月末事前チョコ | C21: ☆【0420】チョコレート長期数表生販在表（26年4月月末生販会議前）.xlsx さ☆【0420】チョコレート長期数表生販在表（26年4月月末生販会議前）.xlsx | D21: チョコレート長期数表生販在表。月末調整事前会議（2026/4/20）用。 | E21: e
A22: SCM | B22: 協力チョコ | C22: 協力☆【0423チョコ協力】チョコレート長期数表生販在表（26年4月月末生販会議前）.xlsx | E22: e
A23: SCM | B23: 滋賀チョコ | C23: 滋賀☆【0420】チョコレート長期数表生販在表（26年4月月末生販会議前）.xlsx | E23: e
A24: SCM | B24: 滋賀菓子工程 | C24: 滋賀菓子工程4-6月（４月月末会議）.xlsx | E24: e
A25: SCM | B25: KYチョコ | C25: ｋｙ☆【0420】チョコレート長期数表生販在表（26年4月月末生販会議前・九州工場案）.xlsx | E25: e
A26: SCM | B26: ローテ | C26: ﾛｰﾃｰｼｮﾝ(4月生販会議前) .xlsx | E26: e
A27: SCM | B27: 月末会議キャン | C27: 202604キャンディ月末会議資料.xlsx | D27: キャンディ2026年度生販在計画（月末調整会議版）。 | E27: e
A28: SCM | B28: 月末会議ビス | C28: 202604ビスケット月末生販会議前.xlsx | D28: ビスケット生販在計画（月末調整会議版）。 | E28: e
A29: SCM | B29: 月末会議ガム | C29: ガム25年度長期計画(4月月末会議資料).xlsx | D29: ガム生販在計画（月末調整会議版）。 | E29: e
A30: SCM | B30: 工程狭山 | C30: ●2604狭山月末生販前★確定版★2026年度ビスケットチョコ工程.xlsx | D30: 狭山工場2026年度ビスケット・チョコ月間工程表。 | E30: e
A31: SCM | B31: 工程九州菓子 | C31: ●2604九州月末生販前0420２５菓子・アイス月間工程.xlsx | D31: 九州工場菓子・アイス月間工程表（2026/4/20版）。 | E31: e
A32: SCM | B32: 工程浦和アイス業 | C32: 浦和アイス月間工程（業務用）4-6.xlsx | D32: 浦和工場アイス月次工程表（業務用）4〜6月。 | E32: e
A33: SCM | B33: 工程浦和アイス市 | C33: 浦和アイス月間工程（市販用）4-6.xlsx | D33: 浦和工場アイス月次工程表（市販用）4〜6月。 | E33: e
A34: SCM | B34: 工程九州アイス | C34: 九州アイス月間工程4-6.xlsx | D34: 九州工場アイス月間工程表4〜6月。 | E34: e
A35: SCM | B35: 工程滋賀アイス | C35: 滋賀アイス工程4-6月.xlsx | D35: 滋賀工場アイス月間工程表4〜6月。 | E35: e
A36: SCM | B36: 工程滋賀菓子 | C36: 滋賀菓子工程4-6月（４月月末会議）.xlsx | D36: 滋賀工場菓子月間工程表4〜6月（月末会議版）。 | E36: e
A37: SCM | B37: 菓子アイス月間 | C37: 0427予定２５菓子・アイス月間工程 - コピー.xlsx | E37: e
A38: SCM | B38: 支払報告需給 | C38: 2026.04支払い報告資料（需給部） .pptx | D38: 4月度支払い報告（需給部）：販売状況・在庫状況・滞貨状況。 | E38: e
A39: SCM | B39: 物流費報告 | C39: 物流費報告（26.04).pptx | D39: 4月度物流費報告：一次輸送・二次配送・保管料・廃棄焼却申請。 | E39: e
A40: SCM | B40: 生販会議生産 | C40: 26年4月生販会議（生産管理課） .pptx | D40: SCM需給部生産管理課の生販情報共有会議資料。在庫・滞貨・欠品率推移。 | E40: e
A41: SCM | B41: STS定例 | C41: STS_改修週次定例_20260428.pptx | D41: SCMシステム（STS）の改修・保守課題進捗の週次定例資料。 | E41: e
A42: SCM | B42: 物流企画一課 | C42: 26年4月度SCM会議資料（物流企画一課）.pptx | D42: 物流部物流企画一課の4月SCM本部会議資料。物流費・生販在計画。 | E42: e
A43: SCM | B43: 第3回SCM議事録 | C43: 20260316_第3回SCM会議 議事録.docx | D43: 2026年3月16日開催SCM会議（第3回）の議事録。物流効率化法・生販在PSI計画・VC改革を議論。 | E43: e
A44: SCM | B44: 第1回SCM議事録 | C44: 【参考】20250512_SCM会議 議事録.docx | D44: 2025年5月12日開催SCM会議（第1回）の議事録。SCM会議立ち上げ・限界利益領域・欠品時意思決定ケーススタディ。 | E44: e
A45: SCM | B45: 第2回SCM議事録 | C45: 【参考】20250828_第2回SCM会議 議事録.docx | D45: 2025年8月28日開催SCM会議（第2回）の議事録。夏季アイス販売・特売費コントロール・在庫適正化を議論。 | E45: e
A46: SCM | B46: SCM本部（SCM戦略部・受注管理部・需給部・物流部・SCMDX推進課） | E46: e
A47: SCM | B47: SCM本部会議全体 | C47: 4月SCM本部会議【全体版】.pptx | D47: 2026年4月SCM本部会議全体版。新商品スケジュール・要求精度・コスト・生販会議資料を収録。 | E47: e
A48: SCM | B48: Anaplan精度検証 | C48: Anaplan精度検証2603.pptx | D48: Anaplan精度検証（2026年3月）資料。新商品要求精度・出荷率分析。 | E48: e
A49: SCM | B49: 新商品カレンダー07 | C49: 新商品カレンダー（2026.07）.pptx | D49: 2026年7月度の新商品スケジュール・販促テーマ・商品カレンダー。 | E49: e
A50: SCM | B50: 持ち戻りPPT | C50: 26.4月度本部会議用【持ち戻り】.pptx | D50: 2026年3月持ち戻り削減取組報告。発生件数・発生率・要因別分析。 | E50: e
A51: SCM | B51: 受注本編 | C51: 【本編】4月度本部会議受注管理部パート.pptx | D51: 4月度SCM本部会議受注管理部パート。KPI・D+2・EDI・ウエルネス等報告。 | E51: e
A52: SCM | B52: アイスエンカレ | C52: アイス・エンカレッジ資料.pptx | D52: アイス部門のエンカレッジ（奨励）資料。 | E52: e
A53: SCM | B53: プロテイン製品 | C53: プロテイン製品情報.xlsx | E53: e
A54: SCM | B54: プロテイン質問 | C54: マーケ回答_プロテイン質問(SCM纏め一旦4.15提出） (1).xlsx | D54: プロテイン発売に関するSCMからの質問とマーケ回答（受注・物流・保管等）。 | E54: e
A55: SCM | B55: 生販物流KO | C55: 生販_物流_キックオフミーティング.pptx | D55: GPN社プロテイン輸入の生販・物流キックオフMTG資料。輸入リードタイム・在庫スキーム。 | E55: e
A56: SCM | B56: 生販物流KO② | C56: 生販_物流_キックオフミーティング②.pptx | D56: 生販・物流キックオフMTG②。フォローアップ事項・課題回答・物流スキーム詳細。 | E56: e
A57: SCM | B57: アイス持ち戻り時系列 | C57: ｱｲｽ持ち戻り【営業】時系列ﾘｽﾄ.XLSX | D57: アイスの持ち戻り時系列リスト（卸先別・月別）。 | E57: e
A58: SCM | B58: B実績 | C58: 2504B実績.XLSX〜2603B実績.XLSX（ボール実績・月次12ファイル） | D58: 受注管理部が管理する月次ボール実績。倉庫別・得意先別・日次の出荷指図数量（CS）をピボット形式で記録。 | E58: e
A59: SCM | B59: 物流企画二課 | C59: 2026年4月SCM会議資料（物流企画二課）.pptx | D59: 物流部物流企画二課の4月SCM本部会議資料。物流費状況・工直備蓄直送名変状況。 | E59: e
A60: SCM | B60: 4月SCM需給 | C60: 2026年4月度SCM会議需給.pptx | D60: 需給部の4月SCM本部会議資料。在庫実績・滞貨実績・欠品実績・需給トピックス（組織強靭化・アジアに恋して動向）。 | E60: e
A61: SCM | B61: 0330-0423受注データ | C61: 0330-0423.XLSX | D61: SAPからエクスポートした受注データ（3/30-4/23）。EDI受注・受注数量・確認済数量・引当可能在庫・積送中在庫を収録。 | E61: e
A62: SCM | B62: SM_DRAG_SRI | C62: SM+DRAG_250303_260419.xlsx | D62: SRI+のSM・DgSチャネルのアイス商品別週次データ。平均販売単価・週販個数・販売店率を収録（2025/3/3-2026/4/19）。 | E62: e
A63: SCM | B63: アジア恋POSデータ | C63: アジアに恋して初週POSデータ(火-月データ).xlsx | D63: アジアに恋して初週POS実績（4/7-4/13）。SEJ・LAW・FM・MS別の販売数量・販売金額・販売カバー率・週販個数。 | E63: e
A64: SCM | B64: S&OP事例 | C64: ロッテ様_S&OP事例紹介資料_v1.0.pdf | D64: アビームによるS&OP事例紹介資料（鉄鋼・食品メーカー事例） | E64: e
A65: SCM | B65: o9紹介 | C65: ロッテ様 オーナインこ゛紹介資料20260423.pdf | D65: o9ソリューションズによる次世代SCMシステム紹介資料 | E65: e
... A76: SCM | B76: 課内MTG0428 | C76: 202600428_課内MTG.pptx | D76: 2026年4月28日 SCMDX推進課 課内MTG（棚貸し配車業務移管・アイス棚貸しSTSフロー等） | E76: e
A77: SCM | B77: 中長期計画ver1 | C77: 中長期計画ver1について.pptx | E77: e
A78: SCM | B78: 中長期計画書試作版 | C78: 中長期計画書試作版ver1.pdf | E78: e
A79: SCM | B79: 荷待ち荷役時時間状況 | C79: 荷待ち荷役時間把握状況について.pptx | E79: e
A80: SCM | B80: 【中京倉庫株式会社 御中】荷待ち荷役時間まとめ | C80: 【中京倉庫株式会社 御中】荷待ち荷役時間まとめ（2026.01）.pdf | E80: e
A81: SCM | B81: 【予約システム】浦和工場 | C81: 【予約システム】菓子浦和工場分析 (1).xlsx | E81: e
A82: SCM | B82: 入庫チェック表 | C82: 入庫チェック表(1月6日-15日).pdf | E82: e
A83: SCM | B83: 受付日報(1月分) | C83: 受付日報(1月分).pdf | E83: e
A84: SCM | B84: 支払い報告サマリ | C84: 支払い報告 _エグゼクティブサマリ2026.04.27.pptx | E84: e
A85: マーケ | B85: マーケ生販会議 | C85: 【マーケアイス】生販会議資料260410.pdf | D85: マーケ本部プランニング課のアイス生販会議資料。初週動向・商品スケジュール。 | E85: e
A86: マーケ | B86: 新製品開発計画 | C86: 【更新用】新アイス新製品リフレッシュ開発計画表・業務用 2019年度版.xlsx | D86: アイス新製品・リフレッシュ開発計画表（市販用）。品番・品名・発売日・生産情報。 | E86: e
A87: マーケ | B87: プランニング実績 | C87: ①【実績レビュー】_プランニング実績.pptx | D87: マーケ本部プランニング実績レビュー。カテゴリ別シェア実績。 | E87: e
A88: マーケ | B88: 損益共有MTG | C88: ?【実績レビュー】_2604損益共有ミーティング_損益部分.pptx | D88: マーケ本部損益共有ミーティング。年度・単月の営業利益増減要因。 | E88: e
A89: マーケ | B89: Theシリーズ共有 | C89: ③【新製品レビュー】_260415 Ｔｈｅシリーズ マーケティングナレッジ共有会.pptx | D89: Theシリーズ（The BUTTER等）のマーケティングナレッジ共有会資料。 | E89: e
A90: マーケ | B90: アジア恋ナレッジ | C90: ④【新製品レビュー】_アジアに恋して_ナレッジMTG資料 0415(2).pptx | D90: 「アジアに恋して」新ブランドのナレッジMTG資料。 | E90: e
A91: マーケ | B91: コアラの街 | C91: ⑤【施策レビュー】_ナレッジMT用_コアラの街_202604.pdf | D91: コアラの街イベント（2026/3/3-8）の施策レビュー資料。 | E91: e
A92: マーケ | B92: チョコ定例帳票 | C92: チョコ定例会議帳票.xlsx | D92: チョコレート定例会議帳票。品番・発売日・開発担当・工場・仕切等の新製品管理表。 | E92: e
A93: マーケ | B93: BillOne | C93: ⑥【諸連絡】_BillOne申請・承認改革説明会資料_ﾏｰｹﾃｨﾝｸﾞ本部.pptx | E93: e
A94: 営業 | B94: 営政 | C94: 2026年度 営業政策 | D94: 営業政策書。売上・利益・価格・販促等の基本方針を収載 | E94: e
A95: 営業 | B95: 全営 | C95: 26年4月 全国営業会議資料 | D95: 月次の全国営業会議で使用する資料 | E95: e
A96: 営業 | B96: 推進M | C96: 営業推進マニュアル（2025年3月更新版） | D96: 営業推進業務の手順・ルールを定めたマニュアル | E96: e
A97: 営業 | B97: 菓初 | C97: 菓子営業はじめてセット（営業政策抜き） | D97: 菓子営業向けオンボーディング資料 | E97: e
A98: 営業 | B98: 氷初 | C98: アイス営業はじめてセット（営業政策抜き） | D98: アイス営業向けオンボーディング資料 | E98: e
A99: 営業 | B99: TN | C99: 26年6-7月度タイムリーナレッジ（リテールサポート課） | D99: 営業情報共有のナレッジ資料 | E99: e
A100: 営業 | B100: 8月商品 | C100: （事前共有用）8月度商品資料.pdf | D100: 2026年8月度新商品提案書（チューイング・チョコ・ビスケット・アイス）。新商品概要・市場背景・本社対策・施策スケジュールを収載。 | E100: e
A101: 経営戦略・収益企画 | B101: 経営戦略部・収益企画部 | E101: e
A102: 経営戦略・収益企画 | B102: 2月個別決算 | C102: （配布のみ）2026年2月度 個別決算報告（確定）.pdf | D102: ロッテグループ2026年2月度の個別決算報告（累計・単月・損益計算書・海外現法） | E102: e
A103: 経営戦略・収益企画 | B103: 3月販売実績 | C103: （配布のみ）2026年3月度 販売実績.pdf | D103: 2026年3月度ロッテグループ販売実績速報（ブランド別・海外別・各社シェア） | E103: e
A104: 経営戦略・収益企画 | B104: インドネシア権限 | C104: 20260413_①_ロッテインドネシア決裁権限区分表の改定の件.pdf | D104: ロッテインドネシア決裁権限区分表の改定（副社長追加）に関する経営会議資料 | E104: e
A105: 経営戦略・収益企画 | B105: 本部KPI確認 | C105: 20260413_②_本部ミッション・KPIの確認.pdf | D105: 2026年度全本部ミッション・KPIの確認資料（事業部門・管理部門） | E105: e
A106: 経営戦略・収益企画 | B106: Gビジネス研修 | C106: 20260413_③_グローバルビジネス研修（公募）実施の件.pdf | D106: グローバルビジネス研修（公募）の概要・スケジュール・グローバル人材育成プラン | E106: e
A107: 経営戦略・収益企画 | B107: 経営会議レジュメ | C107: 20260413_KKロッテ経営会議 レジュメ.pdf | D107: 2026年4月13日経営会議のレジュメ（議題・出席者一覧） | E107: e
A108: 経営戦略・収益企画 | B108: 経営会議ES | C108: 20260413_経営会議アジェンダ・エグゼクティブサマリ.pdf | D108: 2026年4月13日経営会議のアジェンダ・エグゼクティブサマリ | E108: e
A109: 経営戦略・収益企画 | B109: 経営戦略会議ES | C109: 【更新】20260406_経営戦略会議アジェンダ.pptx | D109: 2026年4月6日経営戦略会議アジェンダ（事業予算月別修正・イラン情勢・為替予約の3議題） | E109: e
A110: 経営戦略・収益企画 | B110: 為替予約報告 | C110: 【報告資料】為替予約の実行スキーム及び実績・見込報告20260406.pdf | D110: 為替予約の運用ルール・期間別カバー率・25-26年度米ドル建取引実績/見込 | E110: e
A111: 経営戦略・収益企画 | B111: KK定例会長報告 | C111: 26年3月度KK定例会長報告資料（本番用②手持ちあり）.pdf | D111: 2026年3月度KK定例（会長向け）業績報告。㈱ロッテ単体・連結決算速報、販売状況・市場動向を収載 | E111: e
A112: 経営戦略・収益企画 | B112: 収益企画社長報告 | C112: 【260427】収益企画部月次社長報告資料.pdf | D112: 2026年4月27日収益企画部月次社長報告。2025年度損益振返り・原料費見込み・為替予約・L-Compass・学び場 | E112: e
A113: 生産 | B113: 包装工程1課 | C113: ★1課 包装工程(2026年度)20260421.xlsx | D113: キャンディ1課の生産計画表（2026年度）。生産回答・実績・シフト管理。 | E113: e
A114: 生産 | B114: 生産本部（生産戦略部・資材部） | E114: e
A115: 生産 | B115: イラン情勢 | C115: 20260406 イラン情勢の影響（投影用）.pptx | D115: イラン情勢による資材調達への影響（包材・樹脂・エネルギー費・設備納入遅延） | E115: e
A116: 生産 | B116: 資材部支払3月 | C116: 2026年3月度資材部支払報告資料.pptx | D116: 2026年3月度資材部の支払報告。原材料・包材の調達状況・コストを管理 | E116: e
...

Sheet >0604

Sheet 依頼内容
A1: ロッテグループ標準言語定義辞書化プロジェクト 作業依頼
A3: 1 | B3: 対象資料は出典シートに記載されている資料とする。ロッテの業績管理指標に関する用語・算出式・定義を中心に用語を抽出する。
A4: 2 | B4: 用語辞書シートのG列（定義）、H列（算出式/構造）、I列（単位）を確認し、誤りがある場合は以下の通り対応する。
B6: W列（フラグ）に「1」を記載する。
B7: X列（修正後の定義）、Y列（修正後の算出式/構造）、Z列（修正後の単位）に修正後の内容を記載する。
B8: 修正後欄に記載がある場合はその内容を正として上書きするため、修正後の全文を記載すること。修正が必要なX・Y・Z列のみ記載すれば良い。
A10: 3 | B10: T列（備考）および赤文字・黄色ハイライト箇所は特に確認が必要な箇所であるため、列（備考）とあわせて確認する。
B11: T列（備考）および赤文字・黄色ハイライト箇所は特に確認が必要な箇所であるため、T列（備考）とあわせて確認する。
A12: 4 | B12: 追記したい用語がある場合は、B列（指標大分類）、C列（指標タイプ）、D列（概念）、E列（用語）に内容を記載したうえで、
B13: W列（フラグ）に「1」を記載し、X列（修正後の定義）、Y列（修正後の算出式/構造）、Z列（修正後の単位）に定義を記載する。
D47: スマートファクトリー化計画進捗度

Sheet 0604FB_用語辞書
A1: No | B1: 経営ダッシュボード | C1: 確認部門 | D1: 分科① | E1: 分科② | F1: 分科③ | G1: 分科④ | H1: 分科⑤ | I1: 分科⑥ | J1: 指標大分類 | K1: 指標タイプ | L1: 概念 | M1: 用語 | N1: 略称/同義語 | O1: 定義 | P1: 算出式 / 構造 | Q1: 単位 | R1: 使用シーン / 主な帳票 | W1: 出典 | AE1: 要修正フラグ | AF1: 修正後 | AI1: e
R2: 営業 | S2: マーケ | T2: 生産 | U2: SCM | V2: 経営戦略 ・収益企画 | W2: 営業 | X2: マーケ | Y2: 生産 | Z2: SCM | AA2: 経営戦略 ・収益企画 | AB2: 備考 | AC2: 確認対象部門 | AD2: 収益企画部担当者 | AE2: ドラフトに誤りがある場合1を記載 | AF2: 定義 | AG2: 算出式 / 構造 | AH2: 単位 | AI2: e
A3: =ROW()-2 -> 1 | J3: 01_指標 | K3: =_xlfn.XLOOKUP(L3,'99_マスタ'!$D$5:$D$18,'99_マスタ'!$C$5:$C$18,"") -> 01_財務・業績指標 | L3: 01_売上 | M3: 売上 | N3: メーカー別売上、販売額 | O3: メーカー別の推定売上高。海外売上および内部取引を控除した国内市販用の販売金額。各月の着地（実績確定）ベースで集計され、月次および年度累計（4月〜3月）で管理される。 | P3: 推定売上高 − 海外売上 − 内部取引額 | Q3: 円 | R3: — | S3: マーケットシェア分析 | T3: — | U3: — | V3: — | W3: — | X3: プランニング実績,損益共有MTG,マーケ生販会議 | Y3: — | Z3: — | AA3: — | AI3: e
A4: =ROW()-2 -> 2 | J4: 01_指標 | K4: =_xlfn.XLOOKUP(L4,'99_マスタ'!$D$5:$D$18,'99_マスタ'!$C$5:$C$18,"") -> 01_財務・業績指標 | L4: 01_売上 | M4: 売上 | N4: 売上高 | O4: 純売上高を売上高として記載 | Q4: 円 | R4: — | S4: — | T4: — | U4: — | V4: KK定例会長報告 | W4: — | X4: — | Y4: — | Z4: — | AA4: KK定例会長報告 | AI4: e
A5: =ROW()-2 -> 3 | J5: 01_指標 | K5: =_xlfn.XLOOKUP(L5,'99_マスタ'!$D$5:$D$18,'99_マスタ'!$C$5:$C$18,"") -> 01_財務・業績指標 | L5: 01_売上 | M5: 売上（控除前） | N5: ー | O5: 売上控除項目（年契リベート・販促協賛金等の取引先への割戻し）を差し引く前の売上高。事業損益表において各種比率（特売費率・販売費計率等）の分母として使用される基準売上。控除後の純売上高とは異なり、割戻し前の総額ベースの売上を示す | P5: 純売上高 ＋ 売上控除額（年契・協賛金等） | Q5: 円 | R5: 事業損益 | S5: — | T5: — | U5: — | V5: — | W5: 全営 | X5: — | Y5: — | Z5: — | AA5: — | AI5: e
A6: =ROW()-2 -> 4 | J6: 01_指標 | K6: =_xlfn.XLOOKUP(L6,'99_マスタ'!$D$5:$D$18,'99_マスタ'!$C$5:$C$18,"") -> 01_財務・業績指標 | L6: 01_売上 | M6: 売上控除 | N6: 控除 | O6: 総売上高から差し引かれる控除項目の合計。主に特売費（控除対象）が含まれる。純売上高＝総売上高−売上控除。 | P6: 総売上高 − 純売上高 | Q6: 円 | R6: — | S6: — | T6: — | U6: — | V6: 損益計算書（P/L） | W6: — | X6: — | Y6: — | Z6: — | AA6: 2月個別決算, 3月販売実績 | AI6: e
A7: =ROW()-2 -> 5 | J7: 01_指標 | K7: =_xlfn.XLOOKUP(L7,'99_マスタ'!$D$5:$D$18,'99_マスタ'!$C$5:$C$18,"") -> 01_財務・業績指標 | L7: 01_売上 | M7: 一人当たり売上額 | N7: — | O7: 生産性指標。正社員、臨時社員合計の一人当たり売上額 | Q7: 円 | R7: — | S7: — | T7: — | U7: — | V7: KK定例会長報告 | W7: — | X7: — | Y7: — | Z7: — | AA7: KK定例会長報告 | AB7: ・算出式要確認 | AI7: e
A8: =ROW()-2 -> 6 | J8: 01_指標 | K8: =_xlfn.XLOOKUP(L8,'99_マスタ'!$D$5:$D$18,'99_マスタ'!$C$5:$C$18,"") -> 01_財務・業績指標 | L8: 01_売上 | M8: 海外事業計（現地会計基準） | N8: 海外事業計 | O8: ㈱ロッテの資料では、海外現法（アジア計＋ウェデル計）の純売上高・営業利益を現地の会計基準で集計した合計。社内レートで円換算して表示。 | P8: アジア計（タイ・インドネシア・ベトナム・台湾）+ ウェデル計（ウェデル・ウェデルカフェ） | Q8: 円 | R8: — | S8: — | T8: — | U8: — | V8: 個別決算報告（海外現法） | W8: — | X8: — | Y8: — | Z8: — | AA8: 2月個別決算 | AI8: e
A9: =ROW()-2 -> 7 | J9: 01_指標 | K9: =_xlfn.XLOOKUP(L9,'99_マスタ'!$D$5:$D$18,'99_マスタ'!$C$5:$C$18,"") -> 01_財務・業績指標 | L9: 01_売上 | M9: 営業概況 | N9: ー | O9: 販売振り返りMTGで使用される営業の売上 | Q9: 円 | R9: — | S9: — | T9: — | U9: 販売実績・見込みすり合わせ | V9: — | W9: — | X9: — | Y9: — | Z9: 振返アイス,振返ガム,振返チョコ,振返キャン,振返ビス | AA9: — | AB9: ・営業概況は売上高金額のようだが、それが総売上高なのか純売上高なのか要確認 | AI9: e
A10: =ROW()-2 -> 8 | J10: 01_指標 | K10: =_xlfn.XLOOKUP(L10,'99_マスタ'!$D$5:$D$18,'99_マスタ'!$C$5:$C$18,"") -> 01_財務・業績指標 | L10: 01_売上 | M10: 概況精度 | N10: ー | O10: 統括支店が提出した概況（需要予測）の精度を示す指標。倉入実績をAnaplan倉入計画と比較し、概況提出締切日時点での「1ヵ月前」の計画値がどれだけ実績に近かったかを測る。組織評価における評価指標の一つで、菓子・アイスそれぞれウェイト10%（合計20%）で配点される。広域流通のみ「店出実績/Anaplan店出計画」を基準として算出。 | P10: 倉入実績 ÷ Anaplan倉入計画（概況提出締切日時点の1ヵ月前計画値）※広域流通は店出実績 ÷ Anaplan店出計画 | Q10: 倍 | R10: 支店別評価 | S10: — | T10: — | U10: — | V10: — | W10: 全営 | X10: — | Y10: — | Z10: — | AA10: — | AI10: e
A11: =ROW()-2 -> 9 | J11: 01_指標 | K11: =_xlfn.XLOOKUP(L11,'99_マスタ'!$D$5:$D$18,'99_マスタ'!$C$5:$C$18,"") -> 01_財務・業績指標 | L11: 01_売上 | M11: 小売店年契-基本 | N11: ー | O11: 特売費の種類の一つ。XXX（どのような特売費か要確認） | Q11: 円 | R11: — | S11: — | T11: — | U11: SCM会議（特売費適正化） | V11: — | W11: — | X11: — | Y11: — | Z11: SCM会議 | AA11: — | AI11: e
A12: =ROW()-2 -> 10 | J12: 01_指標 | K12: =_xlfn.XLOOKUP(L12,'99_マスタ'!$D$5:$D$18,'99_マスタ'!$C$5:$C$18,"") -> 01_財務・業績指標 | L12: 01_売上 | M12: 小売店年契-達成 | N12: ー | O12: 特売費の種類の一つ。XXX（どのような特売費か要確認） | R12: — | S12: — | T12: — | U12: SCM会議（特売費適正化） | V12: — | W12: — | X12: — | Y12: — | Z12: SCM会議 | AA12: — | AI12: e
A13: =ROW()-2 -> 11 | J13: 01_指標 | K13: =_xlfn.XLOOKUP(L13,'99_マスタ'!$D$5:$D$18,'99_マスタ'!$C$5:$C$18,"") -> 01_財務・業績指標 | L13: 01_売上 | M13: 資材 | N13: ー | O13: 特売費の種類の一つ。XXX（どのような特売費か要確認） | R13: — | S13: — | T13: — | U13: SCM会議（特売費適正化） | V13: — | W13: — | X13: — | Y13: — | Z13: SCM会議 | AA13: — | AI13: e
A14: =ROW()-2 -> 12 | J14: 01_指標 | K14: =_xlfn.XLOOKUP(L14,'99_マスタ'!$D$5:$D$18,'99_マスタ'!$C$5:$C$18,"") -> 01_財務・業績指標 | L14: 01_売上 | M14: 滞貨品消化 | N14: ー | O14: 特売費の種類の一つ。XXX（どのような特売費か要確認） | Q14: ー | R14: — | S14: — | T14: — | U14: SCM会議（特売費適正化） | V14: — | W14: — | X14: — | Y14: — | Z14: SCM会議 | AA14: — | AI14: e
A15: =ROW()-2 -> 13 | J15: 01_指標 | K15: =_xlfn.XLOOKUP(L15,'99_マスタ'!$D$5:$D$18,'99_マスタ'!$C$5:$C$18,"") -> 01_財務・業績指標 | L15: 01_売上 | M15: 本部協賛-その他 | N15: ー | O15: 特売費の種類の一つ。XXX（どのような特売費か要確認） | Q15: ー | R15: — | S15: — | T15: — | U15: SCM会議（特売費適正化） | V15: — | W15: — | X15: — | Y15: — | Z15: SCM会議 | AA15: — | AI15: e
A16: =ROW()-2 -> 14 | J16: 01_指標 | K16: =_xlfn.XLOOKUP(L16,'99_マスタ'!$D$5:$D$18,'99_マスタ'!$C$5:$C$18,"") -> 01_財務・業績指標 | L16: 01_売上 | M16: 本部協賛-チラシ・POP代 | N16: ー | O16: 特売費の種類の一つ。XXX（どのような特売費か要確認） | Q16: ー | R16: — | S16: — | T16: — | U16: SCM会議（特売費適正化） | V16: — | W16: — | X16: — | Y16: — | Z16: SCM会議 | AA16: — | AI16: e
A17: =ROW()-2 -> 15 | J17: 01_指標 | K17: =_xlfn.XLOOKUP(L17,'99_マスタ'!$D$5:$D$18,'99_マスタ'!$C$5:$C$18,"") -> 01_財務・業績指標 | L17: 01_売上 | M17: 本部協賛-ポイント戻 | N17: ー | O17: 特売費の種類の一つ。XXX（どのような特売費か要確認） | Q17: ー | R17: — | S17: — | T17: — | U17: SCM会議（特売費適正化） | V17: — | W17: — | X17: — | Y17: — | Z17: SCM会議 | AA17: — | AI17: e
A18: =ROW()-2 -> 16 | J18: 01_指標 | K18: =_xlfn.XLOOKUP(L18,'99_マスタ'!$D$5:$D$18,'99_マスタ'!$C$5:$C$18,"") -> 01_財務・業績指標 | L18: 01_売上 | M18: 本部協賛-本部戻 | N18: ー | O18: 特売費の種類の一つ。XXX（どのような特売費か要確認） | Q18: ー | R18: — | S18: — | T18: — | U18: SCM会議（特売費適正化） | V18: — | W18: — | X18: — | Y18: — | Z18: SCM会議 | AA18: — | AI18: e
A19: =ROW()-2 -> 17 | J19: 01_指標 | K19: =_xlfn.XLOOKUP(L19,'99_マスタ'!$D$5:$D$18,'99_マスタ'!$C$5:$C$18,"") -> 01_財務・業績指標 | L19: 01_売上 | M19: 実販対策 | N19: ー | O19: 特売費の種類の一つ。XXX（どのような特売費か要確認） | Q19: ー | R19: — | S19: — | T19: — | U19: SCM会議（特売費適正化） | V19: — | W19: — | X19: — | Y19: — | Z19: SCM会議 | AA19: — | AI19: e
A20: =ROW()-2 -> 18 | J20: 01_指標 | K20: =_xlfn.XLOOKUP(L20,'99_マスタ'!$D$5:$D$18,'99_マスタ'!$C$5:$C$18,"") -> 01_財務・業績指標 | L20: 01_売上 | M20: センターフィ | N20: ー | O20: 特売費の種類の一つ。XXX（どのような特売費か要確認） | Q20: ー | R20: — | S20: — | T20: — | U20: SCM会議（特売費適正化） | V20: — | W20: — | X20: — | Y20: — | Z20: SCM会議 | AA20: — | AI20: e
A21: =ROW()-2 -> 19 | J21: 01_指標 | K21: =_xlfn.XLOOKUP(L21,'99_マスタ'!$D$5:$D$18,'99_マスタ'!$C$5:$C$18,"") -> 01_財務・業績指標 | L21: 01_売上 | M21: 特売経費率 | N21: 特売費率（総売比） | O21: 売上に占める特売費の割合。品目別・統括支店別・ブランド別に管理し、予算比・前年比で分析する。費用の使用効率を示す指標で、売上増加と特売費削減の両立が目標。 | P21: 特売経費率 = 特売費 ÷ 売上 × 100 | Q21: % | R21: 特売費分析, 月次全国営業会議, 営業政策 | S21: — | T21: — | U21: — | V21: — | W21: 全営, 営政 | X21: — | Y21: — | Z21: — | AA21: — | AI21: e
A22: =ROW()-2 -> 20 | J22: 01_指標 | K22: =_xlfn.XLOOKUP(L22,'99_マスタ'!$D$5:$D$18,'99_マスタ'!$C$5:$C$18,"") -> 01_財務・業績指標 | L22: 01_売上 | M22: 出荷実績 | N22: ー | O22: 当該年度累計における製品の出荷金額の確定値。予算・前年実績と対比する形で管理され、カテゴリ（ガム・チョコレート・キャンディ・ビスケット・市販用アイス・業務用アイス）別および菓子計・アイス計・菓子アイス計の集計単位で把握される。 | Q22: 円 | R22: — | S22: マーケットシェア分析 | T22: — | U22: — | V22: — | W22: — | X22: プランニング実績 | Y22: — | Z22: — | AA22: — | AB22: ・売上との違い要確認 | AI22: e
A23: =ROW()-2 -> 21 | J23: 01_指標 | K23: =_xlfn.XLOOKUP(L23,'99_マスタ'!$D$5:$D$18,'99_マスタ'!$C$5:$C$18,"") -> 01_財務・業績指標 | L23: 01_売上 | M23: チャンスロス | N23: 販売機会損失 | O23: 欠品や在庫不足により本来得られたはずの売上が失われること。SCM部門の主要KPIである欠品率と連動して管理される。 | Q23: 円 | R23: — | S23: — | T23: — | U23: SCM本部KPI（チャンスロス削減） | V23: 経営会議（SCM本部KPI） | W23: — | X23: — | Y23: — | Z23: SCM本部会議全体 | AA23: 本部KPI確認 | AI23: e
A24: =ROW()-2 -> 22 | J24: 01_指標 | K24: =_xlfn.XLOOKUP(L24,'99_マスタ'!$D$5:$D$18,'99_マスタ'!$C$5:$C$18,"") -> 01_財務・業績指標 | L24: 01_売上 | M24: 販売 | N24: ー | O24: 生販在計画表における、販売量 | Q24: CS | R24: — | S24: — | T24: — | U24: 生販在計画表 | V24: — | W24: — | X24: — | Y24: — | Z24: 月末キャン | AA24: — | AB24: ・何を基準として”販売”と、みなしているのか（出荷？どこ向け？）要確認 | AI24: e
A25: =ROW()-2 -> 23 | J25: 01_指標 | K25: =_xlfn.XLOOKUP(L25,'99_マスタ'!$D$5:$D$18,'99_マスタ'!$C$5:$C$18,"") -> 01_財務・業績指標 | L25: 01_売上 | M25: 純売上高 | N25: 純売ベース、純売 | O25: 総売上から返品・値引等を控除した売上。営業利益の率計算の分母として使用される。 | P25: 総売上 − 値引・返品・販売費（一部） | Q25: 円 | R25: 品目別営業利益（純売ベース）, 営業会議資料 | S25: 新商品マーケット分析 | T25: — | U25: — | V25: 個別決算 | W25: 全営 | X25: アジア恋ナレッジ | Y25: — | Z25: — | AA25: 2月個別決算、本部KPI確認 | AI25: e
A26: =ROW()-2 -> 24 | J26: 01_指標 | K26: =_xlfn.XLOOKUP(L26,'99_マスタ'!$D$5:$D$18,'99_マスタ'!$C$5:$C$18,"") -> 01_財務・業績指標 | L26: 01_売上 | M26: 生産性 | N26: ー | O26: 工場人員一人当たりの売上金額 | Q26: 円 | R26: — | S26: — | T26: — | U26: — | V26: 本部KPI | W26: — | X26: — | Y26: — | Z26: — | AA26: 本部KPI確認 | AB26: ・生産本部が掲げる生産性には2種類存在 | AI26: e
A27: =ROW()-2 -> 25 | J27: 01_指標 | K27: =_xlfn.XLOOKUP(L27,'99_マスタ'!$D$5:$D$18,'99_マスタ'!$C$5:$C$18,"") -> 01_財務・業績指標 | L27: 01_売上 | M27: 総売上高 | N27: 総売 | O27: 控除を行っていない売上の合計額。ロッテの場合は仕切り価格販売の積み上げ | P27: 販売数量×単価（仕切価格） | Q27: 円 | R27: 全国営業会議, 営業政策, 予算表 | S27: — | T27: — | U27: 商品規格適正化検討、ロッテ業績 | V27: 個別決算 | W27: 営政, 全営 | X27: — | Y27: — | Z27: SCM会議、ロッテ業績簡易版 | AA27: 2月個別決算 | AI27: e
A28: =ROW()-2 -> 26 | J28: 01_指標 | K28: =_xlfn.XLOOKUP(L28,'99_マスタ'!$D$5:$D$18,'99_マスタ'!$C$5:$C$18,"") -> 01_財務・業績指標 | L28: 01_売上 | M28: 店出実績 | N28: 店出, 店出し | O28: 得意先（卸）から小売業（企業）への納品実績。 | P28: 卸→小売業 への納品金額。直取得意先は倉入＝店出。 | Q28: 円, CS | R28: 店出システム, BO, 月次企業計画差異 | S28: — | T28: — | U28: — | V28: — | W28: 推進M, 全営 | X28: — | Y28: — | Z28: — | AA28: — | AI28: e
A29: =ROW()-2 -> 27 | J29: 01_指標 | K29: =_xlfn.XLOOKUP(L29,'99_マスタ'!$D$5:$D$18,'99_マスタ'!$C$5:$C$18,"") -> 01_財務・業績指標 | L29: 01_売上 | M29: 特売費 | N29: — | O29: 特売実施で発生する経費全般。控除対象/控除対象外で区別。 | P29: 値差補填 + 特売条件 + 特売拡売費 等 | Q29: 円 | R29: Biz, 特売費分析 | S29: — | T29: — | U29: SCM会議（特売費コントロール・値差上限導入検討） | V29: — | W29: 営政, 全営 | X29: — | Y29: — | Z29: SCM会議, 第3回SCM議事録, 第2回SCM議事録 | AA29: — | AI29: e
A30: =ROW()-2 -> 28 | J30: 01_指標 | K30: =_xlfn.XLOOKUP(L30,'99_マスタ'!$D$5:$D$18,'99_マスタ'!$C$5:$C$18,"") -> 01_財務・業績指標 | L30: 01_売上 | M30: 特売費率 | N30: — | O30: 売上に対する特売費の比率。営業利益管理の主要KPI。 | P30: 特売費 ÷ 売上 × 100 | Q30: % | R30: 営業政策, 全営の特売費分析 | S30: 損益概況 | T30: — | U30: SCM会議 | V30: 収益企画社長報告（PLツリー：品目別特売費率管理） | W30: 営政, 全営 | X30: 損益共有MTG | Y30: — | Z30: 第2回SCM議事録 | AA30: KK定例会長報告 | AI30: e
A31: =ROW()-2 -> 29 | J31: 01_指標 | K31: =_xlfn.XLOOKUP(L31,'99_マスタ'!$D$5:$D$18,'99_マスタ'!$C$5:$C$18,"") -> 01_財務・業績指標 | L31: 01_売上 | M31: 連結売上高 | N31: 連結 | O31: ㈱ロッテおよびグループ会社を連結した売上高。経理の連結決算で使用される概念で、単体（個別）売上とは異なる。 | P31: ・単体売上高 + グループ会社売上 − 内部取引消去 ・単体売上高＋グループ会社売上ー連結修正 | Q31: 円 | R31: — | S31: — | T31: — | U31: — | V31: 個別決算報告（参照概念）、KK定例会長報告（連結決算速報：国内計・海外計・WEDEL等） | W31: — | X31: — | Y31: — | Z31: — | AA31: KK定例会長報告 | AI31: e
A32: =ROW()-2 -> 30 | J32: 01_指標 | K32: =_xlfn.XLOOKUP(L32,'99_マスタ'!$D$5:$D$18,'99_マスタ'!$C$5:$C$18,"") -> 02_生販在 | L32: 07_販売 | M32: 1か月前見込比 | N32: — | O32: 販売振り返りミーティングで使用する精度指標。1か月前に立案されたSCM見込みまたは営業概況に対する当月実績の比率。 | P32: 当月実績 ÷ 1か月前見込み × 100 | Q32: % | R32: — | S32: — | T32: — | U32: 各カテゴリ振り返りMTG（アイス・ガム・チョコ・ビス・キャン） | V32: — | W32: — | X32: — | Y32: — | Z32: 振返アイス, 振返ガム, 振返キャン, 振返チョコ, 振返ビス | AA32: — | AI32: e
A33: =ROW()-2 -> 31 | J33: 01_指標 | K33: =_xlfn.XLOOKUP(L33,'99_マスタ'!$D$5:$D$18,'99_マスタ'!$C$5:$C$18,"") -> 02_生販在 | L33: 07_販売 | M33: SCM見込み | N33: SCM見込 | O33: SCM需給部が独自に立案する販売見込み。生販会議資料・振り返りミーティングで営業見込みと並べて比較される。生産計画の基礎となる。 | Q33: 円, CS | R33: — | S33: — | T33: — | U33: 生販会議（販売振り返り・次月見込）、各カテゴリ振り返りMTG, SCM本部会議（販売見込み・前回生販会議振り返り） | V33: — | W33: — | X33: — | Y33: — | Z33: 生販会議, 振返アイス, 振返ガム, 振返キャン, 振返チョコ, 振返ビス, SCM本部会議全体, SCM会議 | AA33: — | AI33: e
A34: =ROW()-2 -> 32 | J34: 01_指標 | K34: =_xlfn.XLOOKUP(L34,'99_マスタ'!$D$5:$D$18,'99_マスタ'!$C$5:$C$18,"") -> 02_生販在 | L34: 07_販売 | M34: 規定値差 | N34: — | O34: 商品ごとに設定された値差補填の上限。これを超える条件提示には申請が必要。 | P34: Salesforce発売計画書で確認 | Q34: 円 | R34: Salesforce, 発売計画書 | S34: — | T34: — | U34: — | V34: — | W34: 菓初 | X34: — | Y34: — | Z34: — | AA34: — | AI34: e
A35: =ROW()-2 -> 33 | J35: 01_指標 | K35: =_xlfn.XLOOKUP(L35,'99_マスタ'!$D$5:$D$18,'99_マスタ'!$C$5:$C$18,"") -> 02_生販在 | L35: 07_販売 | M35: アイス定番値差 | N35: 定番補填 | O35: アイス特有の定番納価補填。新仕切制度（2021年）以前は仕切60掛けへの5%補填、現在は仕切に対し9.46%が標準。 | P35: 仕切 × 9.46%（現行180円商品で約8.892円） | Q35: 円 | R35: アイス見積書 | S35: — | T35: — | U35: — | V35: — | W35: 氷初 | X35: — | Y35: — | Z35: — | AA35: — | AI35: e
A36: =ROW()-2 -> 34 | J36: 01_指標 | K36: =_xlfn.XLOOKUP(L36,'99_マスタ'!$D$5:$D$18,'99_マスタ'!$C$5:$C$18,"") -> 01_財務・業績指標 | L36: 02_原価 | M36: コストダウン金額 | N36: CD金額 | O36: 原材料・包材・製造コスト等の削減額。生産本部（工場・資材部）のKPIとして管理される。 | Q36: 円 | R36: — | S36: — | T36: 目標管理実績（生産本部KPI） | U36: — | V36: 本部KPI | W36: — | X36: — | Y36: 目標管理実績 | Z36: — | AA36: 本部KPI確認 | AI36: e
A37: =ROW()-2 -> 35 | J37: 01_指標 | K37: =_xlfn.XLOOKUP(L37,'99_マスタ'!$D$5:$D$18,'99_マスタ'!$C$5:$C$18,"") -> 01_財務・業績指標 | L37: 02_原価 | M37: 洗浄ロス率 | N37: — | O37: 設備や貴部に付着した洗い流されてしまう原料や半製品の発生率 | P37: （洗浄ロス量×洗浄回数）/実績使用量×100 | Q37: ％ | R37: — | S37: — | T37: 原材料ロス管理 | U37: — | V37: — | W37: — | X37: — | Y37: 管理指標定義 | Z37: — | AA37: — | AI37: e
A38: =ROW()-2 -> 36 | J38: 01_指標 | K38: =_xlfn.XLOOKUP(L38,'99_マスタ'!$D$5:$D$18,'99_マスタ'!$C$5:$C$18,"") -> 01_財務・業績指標 | L38: 02_原価 | M38: 一次輸送費 | N38: 一次配送費 | O38: 工場（または物流センター）から物流センター（または直接大型卸の拠点）への輸送を指し、物流費の内訳の一つ。長距離・大量輸送が主体で、消費地に先に運ぶ政策（前送り政策）の影響を受けやすい。 | Q38: 円 | R38: — | S38: — | T38: — | U38: 月次物流費報告（一次輸送費の実績・予算・前年比管理）, SCM本部会議（SCM費項目別確認）, 物流費報告（物流企画一課） | V38: — | W38: — | X38: — | Y38: — | Z38: 物流費報告, SCM本部会議全体, 物流企画一課, 物流企画二課, SCM会議 | AA38: — | AI38: e
A39: =ROW()-2 -> 37 | J39: 01_指標 | K39: =_xlfn.XLOOKUP(L39,'99_マスタ'!$D$5:$D$18,'99_マスタ'!$C$5:$C$18,"") -> 01_財務・業績指標 | L39: 02_原価 | M39: 運賃・保管料 | N39: SCM費、物流費 | O39: SCMが管轄する一次輸送費、二次配送費、保管・荷役料にその他物流費を加算したKPI | P39: 一次輸送費＋二次配送費＋保管・荷役料＋その他物流費 | Q39: 円 | R39: — | S39: — | T39: — | U39: SCM会議（年度KPI） | V39: — | W39: — | X39: — | Y39: — | Z39: SCM会議 | AA39: — | AI39: e
A40: =ROW()-2 -> 38 | J40: 01_指標 | K40: =_xlfn.XLOOKUP(L40,'99_マスタ'!$D$5:$D$18,'99_マスタ'!$C$5:$C$18,"") -> 01_財務・業績指標 | L40: 02_原価 | M40: 運賃保管料率 | N40: 物流費率 | O40: 売上（総売高）に対する運賃・保管料の比率。物流コスト効率の管理KPI。 | P40: （運賃 + 保管料） ÷ 総売上高 × 100 | Q40: % | R40: 全国営業会議（物流費効率化KPI） | S40: — | T40: — | U40: SCM本部会議（物流費率管理） | V40: 収益性分析、KK定例会長報告、収益企画社長報告 | W40: 営政, 全営 | X40: — | Y40: — | Z40: SCM本部会議全体 | AA40: 2月個別決算、KK定例会長報告, 収益企画社長報告 | AI40: e
A41: =ROW()-2 -> 39 | J41: 01_指標 | K41: =_xlfn.XLOOKUP(L41,'99_マスタ'!$D$5:$D$18,'99_マスタ'!$C$5:$C$18,"") -> 01_財務・業績指標 | L41: 02_原価 | M41: 物流費 | N41: SCM費 | O41: 商品の工場出荷から消費地までの輸送・保管・荷役にかかる費用の総称。一次輸送・二次配送・保管荷役料・その他に分類される。SCM本部物流はその他を除く3費目を管理し、純売上に対する経費率（物流費率）で評価される。 | P41: 物流費=一次配送+二次配送+保管料+荷役料+その他 | Q41: 円 | R41: — | S41: — | T41: — | U41: 月次物流費報告（需給部・物流部）、支払い報告MTG, SCM会議（運賃・保管料KPI管理）, SCM本部会議（SCM費・運賃保管料率確認）, 物流費報告（物流企画一課・二課）, 物流費見込（4-6月） | V41: — | W41: — | X41: — | Y41: — | Z41: 物流費報告, SCM会議, 第3回SCM議事録, SCM本部会議全体, 物流企画一課, 物流企画二課, SCM大会 | AA41: — | AI41: e
A42: =ROW()-2 -> 40 | J42: 01_指標 | K42: =_xlfn.XLOOKUP(L42,'99_マスタ'!$D$5:$D$18,'99_マスタ'!$C$5:$C$18,"") -> 01_財務・業績指標 | L42: 02_原価 | M42: 保管・荷役料 | N42: 保管料 | O42: 倉庫での保管費および入出庫の荷役作業費。SCM費の構成項目の一つ。総売比で管理し、アイスは保管量が季節変動するため比率が大きくなる。 →運賃保管料とは何が違う？ | Q42: 円、%（総売比） | R42: — | S42: — | T42: — | U42: SCM本部会議（SCM費項目別確認）、月次物流費報告 | V42: — | W42: — | X42: — | Y42: — | Z42: SCM本部会議全体 | AA42: — | AI42: e
A43: =ROW()-2 -> 41 | J43: 01_指標 | K43: =_xlfn.XLOOKUP(L43,'99_マスタ'!$D$5:$D$18,'99_マスタ'!$C$5:$C$18,"") -> 01_財務・業績指標 | L43: 02_原価 | M43: 保管料 | N43: — | O43: 工場・倉庫での商品保管に対して倉庫業者に支払う費用。在庫数量と単価の積で算出される。月次の物流費報告において一次輸送・二次配送等と並んで管理される。 | P43: 在庫数量 × 保管単価（円/ケース） | Q43: 円 | R43: — | S43: — | T43: — | U43: 月次物流費報告（物流企画一課・二課）、在庫状況との連動管理 | V43: — | W43: — | X43: — | Y43: — | Z43: 物流企画一課, 物流企画二課、SCM会議 | AA43: — | AI43: e
A44: =ROW()-2 -> 42 | J44: 01_指標 | K44: =_xlfn.XLOOKUP(L44,'99_マスタ'!$D$5:$D$18,'99_マスタ'!$C$5:$C$18,"") -> 01_財務・業績指標 | L44: 02_原価 | M44: 荷役料 | N44: — | O44: 倉庫内での入出庫・仕分け・積み替えなどの作業費用。物流費の内訳科目の一つ。 | Q44: 円 | R44: — | S44: — | T44: — | U44: 月次物流費報告（物流企画一課） | V44: — | W44: — | X44: — | Y44: — | Z44: 物流企画一課 | AA44: — | AI44: e
A45: =ROW()-2 -> 43 | J45: 01_指標 | K45: =_xlfn.XLOOKUP(L45,'99_マスタ'!$D$5:$D$18,'99_マスタ'!$C$5:$C$18,"") -> 01_財務・業績指標 | L45: 02_原価 | M45: 転送費 | N45: — | O45: 一度納品した商品を別の倉庫や配送先へ再輸送する際に発生する費用。首都圏出荷転送と首都圏以外転送に分けて管理される。 | P45: 転送数量（ケース）× 転送単価（円/ケース） | Q45: 円 | R45: — | S45: — | T45: — | U45: 月次物流費報告（物流企画一課） | V45: — | W45: — | X45: — | Y45: — | Z45: 物流企画一課、SCM会議 | AA45: — | AI45: e
A46: =ROW()-2 -> 44 | J46: 01_指標 | K46: =_xlfn.XLOOKUP(L46,'99_マスタ'!$D$5:$D$18,'99_マスタ'!$C$5:$C$18,"") -> 01_財務・業績指標 | L46: 02_原価 | M46: 経費率 | N46: 物流経費率, 物流費率 | O46: 総売上に対する物流費の比率。物流コスト効率の主要KPI。菓子・アイス・合計の3区分で管理される。 | P46: 物流費 ÷ 総売上高 × 100 | Q46: % | R46: — | S46: — | T46: — | U46: 月次物流費報告（物流企画一課・二課）, 月次物流費報告、支払いMTG、SCM本部会議, SCM本部会議（運賃保管料率推移確認）, ロッテ業績超簡易版 | V46: — | W46: — | X46: — | Y46: — | Z46: 物流企画一課, 物流企画二課, 物流費報告, SCM本部会議全体, ロッテ業績超簡易版, SCM大会 | AA46: — | AI46: e
A47: =ROW()-2 -> 45 | J47: 01_指標 | K47: =_xlfn.XLOOKUP(L47,'99_マスタ'!$D$5:$D$18,'99_マスタ'!$C$5:$C$18,"") -> 01_財務・業績指標 | L47: 02_原価 | M47: 廃棄ロス | N47: 廃棄金額（原価） | O47: 賞味期限切れや品質問題等で廃棄された商品の損失金額。 | P47: 廃棄数量 × 原価金額 | Q47: 円 | R47: — | S47: — | T47: — | U47: SCM大会（KPI） | V47: 本部KPI | W47: — | X47: — | Y47: — | Z47: SCM大会 | AA47: 本部KPI確認 | AB47: ・仕切り金額・原価金額双方で使用される場合有 | AI47: e
A48: =ROW()-2 -> 46 | J48: 01_指標 | K48: =_xlfn.XLOOKUP(L48,'99_マスタ'!$D$5:$D$18,'99_マスタ'!$C$5:$C$18,"") -> 01_財務・業績指標 | L48: 02_原価 | M48: 廃棄ロス | N48: 廃棄金額（仕切） | O48: 賞味期限切れや品質問題等で廃棄された商品の損失金額。仕切り価格ベースで計上し、予算・前年との差異をSCM本部会議で報告する。菓子・アイス別に月次と年度累計で管理する。 | P48: 廃棄数量 × 仕切り価格 | Q48: 円 | R48: — | S48: — | T48: — | U48: SCM本部会議（不動在庫・廃棄ロス確認）、支払い報告MTG | V48: 経営会議 | W48: — | X48: — | Y48: — | Z48: SCM本部会議全体 | AA48: 本部KPI確認 | AB48: ・仕切り金額・原価金額双方で使用される場合有 | AI48: e
A49: =ROW()-2 -> 47 | J49: 01_指標 | K49: =_xlfn.XLOOKUP(L49,'99_マスタ'!$D$5:$D$18,'99_マスタ'!$C$5:$C$18,"") -> 01_財務・業績指標 | L49: 02_原価 | M49: 売上原価率 | N49: 原価率 | O49: 純売上高に対する売上原価の比率。製造コスト効率を示す主要管理指標。 | P49: 売上原価 ÷ 純売上高 × 100 | Q49: % | R49: — | S49: — | T49: 生産本部月次管理（原価率実績・予算差管理） | U49: — | V49: KK定例会長報告 | W49: — | X49: — | Y49: 会長報告生産3月 | Z49: — | AA49: KK定例会長報告,2月個別決算 | AB49: ・KK定例会長報告では純売上高に対する売上原価率を算出、個別決算の収益性分析では総売上高に対する売上原価率を算出 | AI49: e
A50: =ROW()-2 -> 48 | J50: 01_指標 | K50: =_xlfn.XLOOKUP(L50,'99_マスタ'!$D$5:$D$18,'99_マスタ'!$C$5:$C$18,"") -> 01_財務・業績指標 | L50: 02_原価 | M50: 原料費率 | N50: — | O50: 売上に対する原料費（原材料費）の比率。カカオ豆等の原料相場の影響を直接受ける主要原価KPI。 | P50: 原料費 ÷ 総売上高（または純売上高）× 100 | Q50: % | R50: — | S50: 損益概況 | T50: 生産本部月次管理 | U50: — | V50: 収益企画社長報告 | W50: — | X50: 損益共有MTG | Y50: SCM会議 | Z50: — | AA50: 収益企画社長報告 | AI50: e
A51: =ROW()-2 -> 49 | J51: 01_指標 | K51: =_xlfn.XLOOKUP(L51,'99_マスタ'!$D$5:$D$18,'99_マスタ'!$C$5:$C$18,"") -> 01_財務・業績指標 | L51: 02_原価 | M51: 戦略原価 | N51: — | O51: 単品別の製造原価から製造固定費（減価償却・人件費等）を除いた変動費ベースの原価。営業本部の利益管理（限界利益・企業利益計算）に使用する。 | P51: 戦略原価 ＝ 製造原価 − 製造固定費 | Q51: 円/CS | R51: 限界利益率分析・企業利益計算 | S51: — | T51: — | U51: — | V51: — | W51: 菓初, 氷初, 営政 | X51: — | Y51: — | Z51: — | AA51: — | AI51: e
A52: =ROW()-2 -> 50 | J52: 01_指標 | K52: =_xlfn.XLOOKUP(L52,'99_マスタ'!$D$5:$D$18,'99_マスタ'!$C$5:$C$18,"") -> 01_財務・業績指標 | L52: 03_販管費 | M52: 24年問題対策費 | N52: ー | O52: 物流2024年問題対策に関する費用は切り出して管理 | P52: 要確認 | Q52: 円 | R52: — | S52: — | T52: — | U52: 物流費報告 | V52: — | W52: — | X52: — | Y52: — | Z52: 物流企画一課 | AA52: — | AI52: e
A53: =ROW()-2 -> 51 | J53: 01_指標 | K53: =_xlfn.XLOOKUP(L53,'99_マスタ'!$D$5:$D$18,'99_マスタ'!$C$5:$C$18,"") -> 01_財務・業績指標 | L53: 03_販管費 | M53: 一般管理費 | N53: ー | O53: 売上原価に含まれない、会社運営にかかわる費用 | P53: 商標権使用料＋福利厚生費＋消耗品費＋修繕費＋通信費＋旅費交通費＋保険料＋租税公課＋賃借料＋接待交際費＋寄付金＋減価償却費＋電力費＋水道燃料費＋研究費＋社員募集費＋社員教育費＋調査費＋支払手数料＋雑費 | Q53: 円 | R53: — | S53: — | T53: — | U53: — | V53: 一般管理費明細、損益計算書（P/L） | W53: — | X53: — | Y53: — | Z53: — | AA53: 2月個別決算 | AI53: e
A54: =ROW()-2 -> 52 | J54: 01_指標 | K54: =_xlfn.XLOOKUP(L54,'99_マスタ'!$D$5:$D$18,'99_マスタ'!$C$5:$C$18,"") -> 01_財務・業績指標 | L54: 03_販管費 | M54: 一般管理費率 | N54: — | O54: 総売上高に対する一般管理費の割合 | P54: 一般管理費計 ÷ 総売上高 | Q54: ％ | R54: — | S54: — | T54: — | U54: — | V54: 収益性分析 | W54: — | X54: — | Y54: — | Z54: — | AA54: 2月個別決算 | AB54: ・％と金額どちらが指標になるかは要確認 | AI54: e
A55: =ROW()-2 -> 53 | J55: 01_指標 | K55: =_xlfn.XLOOKUP(L55,'99_マスタ'!$D$5:$D$18,'99_マスタ'!$C$5:$C$18,"") -> 01_財務・業績指標 | L55: 03_販管費 | M55: 減価償却費 | N55: ー | O55: 有形固定資産（製造設備・機械・建物等）および無形固定資産の取得原価を耐用年数にわたって費用配分した金額。キャッシュの支出を伴わない非現金費用であり、PLツリー上では固定費の構成要素として原価関連・販管費に計上される。 | Q55: 円 | R55: — | S55: 損益概況 | T55: — | U55: — | V55: — | W55: — | X55: 損益共有MTG | Y55: — | Z55: — | AA55: — | AI55: e
A56: =ROW()-2 -> 54 | J56: 01_指標 | K56: =_xlfn.XLOOKUP(L56,'99_マスタ'!$D$5:$D$18,'99_マスタ'!$C$5:$C$18,"") -> 01_財務・業績指標 | L56: 03_販管費 | M56: 広告宣伝費 | N56: — | O56: 広告・宣伝に関する費用 | P56: 宣伝費媒体＋宣伝費その他（ディスプレイ・専門誌・オウンドメディアアド） | Q56: 円 | R56: — | S56: — | T56: — | U56: — | V56: 損益計算書（P/L) | W56: — | X56: — | Y56: — | Z56: — | AA56: 2月個別決算 | AI56: e
A57: =ROW()-2 -> 55 | J57: 01_指標 | K57: =_xlfn.XLOOKUP(L57,'99_マスタ'!$D$5:$D$18,'99_マスタ'!$C$5:$C$18,"") -> 01_財務・業績指標 | L57: 03_販管費 | M57: 広告宣伝費率 | N57: — | O57: 総売上高に対する広告宣伝費の割合 | P57: 広告宣伝費計 ÷ 総売上高 | Q57: ％ | R57: — | S57: — | T57: — | U57: — | V57: 収益性分析 | W57: — | X57: — | Y57: — | Z57: — | AA57: 2月個別決算 | AB57: ・％と金額どちらが指標になるかは要確認 | AI57: e
A58: =ROW()-2 -> 56 | J58: 01_指標 | K58: =_xlfn.XLOOKUP(L58,'99_マスタ'!$D$5:$D$18,'99_マスタ'!$C$5:$C$18,"") -> 01_財務・業績指標 | L58: 03_販管費 | M58: 人件費 | N58: — | O58: 自社社員の給与・賞与・退職給付費用・法定福利費、および派遣社員等臨時社員に対する人件費（雑給） | P58: 自社社員人件費（給与＋賞与＋退職給付費用＋法定福利費）＋雑給 | Q58: 円 | R58: — | S58: — | T58: — | U58: — | V58: 人件費明細 | W58: — | X58: — | Y58: — | Z58: — | AA58: 2月個別決算 | AB58: ・労務費が対象かは要確認 | AI58: e
A59: =ROW()-2 -> 57 | J59: 01_指標 | K59: =_xlfn.XLOOKUP(L59,'99_マスタ'!$D$5:$D$18,'99_マスタ'!$C$5:$C$18,"") -> 01_財務・業績指標 | L59: 03_販管費 | M59: 人件費率(総売比) | N59: — | O59: 総売上高に対する総人件費の割合 | P59: 総人件費 ÷ 総売上高 | Q59: ％ | R59: — | S59: — | T59: — | U59: — | V59: 収益性分析 | W59: — | X59: — | Y59: — | Z59: — | AA59: 2月個別決算 | AB59: ・目的によって分母が純売か総売か変わる ・％と金額どちらが指標になるかは要確認 | AI59: e
A60: =ROW()-2 -> 58 | J60: 01_指標 | K60: =_xlfn.XLOOKUP(L60,'99_マスタ'!$D$5:$D$18,'99_マスタ'!$C$5:$C$18,"") -> 01_財務・業績指標 | L60: 03_販管費 | M60: 人件費率(純売比) | N60: — | O60: 純売上高に対する総人件費の割合 | P60: 総人件費 ÷ 純売上高 | Q60: ％ | R60: — | S60: — | T60: — | U60: — | V60: KK定例会長報告 | W60: — | X60: — | Y60: — | Z60: — | AA60: KK定例会長報告 | AB60: ・目的によって分母が純売か総売か変わる | AI60: e
A61: =ROW()-2 -> 59 | J61: 01_指標 | K61: =_xlfn.XLOOKUP(L61,'99_マスタ'!$D$5:$D$18,'99_マスタ'!$C$5:$C$18,"") -> 01_財務・業績指標 | L61: 03_販管費 | M61: 一人当たり人件費 | N61: — | O61: 生産性指標。正社員、臨時社員それぞれのひと月当たりの人件費 | Q61: 円 | R61: — | S61: — | T61: — | U61: — | V61: KK定例会長報告 | W61: — | X61: — | Y61: — | Z61: — | AA61: KK定例会長報告 | AB61: ・算出式要確認 | AI61: e
A62: =ROW()-2 -> 60 | J62: 01_指標 | K62: =_xlfn.XLOOKUP(L62,'99_マスタ'!$D$5:$D$18,'99_マスタ'!$C$5:$C$18,"") -> 01_財務・業績指標 | L62: 03_販管費 | M62: 宣伝費媒体 | N62: ー | O62: テレビ・デジタル・新聞・雑誌等の広告媒体に出稿するための費用。宣伝費全体のうち、制作費（クリエイティブ制作コスト）を除いた媒体掲載・放映に要するコスト。PLツリー上では販売関連費の構成要素として計上される。 | Q62: 円 | R62: — | S62: 損益概況 | T62: — | U62: — | V62: — | W62: — | X62: 損益共有MTG | Y62: — | Z62: — | AA62: — | AI62: e
A63: =ROW()-2 -> 61 | J63: 01_指標 | K63: =_xlfn.XLOOKUP(L63,'99_マスタ'!$D$5:$D$18,'99_マスタ'!$C$5:$C$18,"") -> 01_財務・業績指標 | L63: 03_販管費 | M63: 販売費 | N63: ー | O63: 特売費・拡売費等販売に関わる費用 | P63: 注文獲得費（特売費＋拡売費）＋注文獲得促進費控除外（見本費（旧販社分）＋市場対策費＋自動販売機費＋自転車費（販促）＋販売店指導費＋販売店手数料＋その他（販促）） | Q63: 円 | R63: — | S63: — | T63: — | U63: — | V63: 損益計算書（P/L） | W63: — | X63: — | Y63: — | Z63: — | AA63: 2月個別決算 | AI63: e
A64: =ROW()-2 -> 62 | J64: 01_指標 | K64: =_xlfn.XLOOKUP(L64,'99_マスタ'!$D$5:$D$18,'99_マスタ'!$C$5:$C$18,"") -> 01_財務・業績指標 | L64: 03_販管費 | M64: 販売費率（売上控除＋控除対象外） | N64: ー | O64: 総売上に対する販売費の比率。 | P64: 販売費 ÷ 総売上高 × 100 | Q64: ％ | R64: — | S64: — | T64: — | U64: — | V64: 収益性分析 | W64: — | X64: — | Y64: — | Z64: — | AA64: 2月個別決算 | AI64: e
A65: =ROW()-2 -> 63 | J65: 01_指標 | K65: =_xlfn.XLOOKUP(L65,'99_マスタ'!$D$5:$D$18,'99_マスタ'!$C$5:$C$18,"") -> 01_財務・業績指標 | L65: 03_販管費 | M65: 拡売費 | N65: 注文獲得費 | O65: ディスプレイ・資材・本部対策など、小売店に支払われないキャンペーン経費。卸店への割戻に充当される本部インセンティブも含む。 | P65: 資材費 + ディスプレイ費 + 本部対策 等 | Q65: 円 | R65: 予算編成会議, アクションプラン | S65: — | T65: — | U65: — | V65: — | W65: 推進M, 営政 | X65: — | Y65: — | Z65: — | AA65: — | AI65: e
A66: =ROW()-2 -> 64 | J66: 01_指標 | K66: =_xlfn.XLOOKUP(L66,'99_マスタ'!$D$5:$D$18,'99_マスタ'!$C$5:$C$18,"") -> 01_財務・業績指標 | L66: 03_販管費 | M66: 付与額 | N66: ー | O66: 本社営業推進課が指定ドラッグストア企業および地区選定企業に対して付与する販促費用の金額。特定商品（キシリトールオーラテクト・フッ素対策等）の販売促進を目的として、統括支店ごとに割り当てられた予算から各企業に配分される。指定企業（DRG）と地区選定企業で付与額が異なる | Q66: 円 | R66: 商品別販促予算管理 | S66: — | T66: — | U66: — | V66: — | W66: 全営 | X66: — | Y66: — | Z66: — | AA66: — | AI66: e
A67: =ROW()-2 -> 65 | J67: 01_指標 | K67: =_xlfn.XLOOKUP(L67,'99_マスタ'!$D$5:$D$18,'99_マスタ'!$C$5:$C$18,"") -> 01_財務・業績指標 | L67: 03_販管費 | M67: ポイント販促費 | N67: — | O67: 小売店のポイント付与販促への協賛費。 | P67: 期間内の数量 × ポイント代 | Q67: 円 | R67: Biz | S67: — | T67: — | U67: — | V67: — | W67: 菓初 | X67: — | Y67: — | Z67: — | AA67: — | AI67: e
A68: =ROW()-2 -> 66 | J68: 01_指標 | K68: =_xlfn.XLOOKUP(L68,'99_マスタ'!$D$5:$D$18,'99_マスタ'!$C$5:$C$18,"") -> 01_財務・業績指標 | L68: 03_販管費 | M68: 控除固定費 | N68: — | O68: 貢献利益算出時に控除する固定費（広告宣伝費・人件費・一般管理費等）。売上に連動しない。 | P68: 予算時：売上予算 × 控除固定率 で算出（実績時もこの金額を流用） | Q68: 円 | R68: 貢献利益管理 | S68: — | T68: — | U68: — | V68: — | W68: 推進M | X68: — | Y68: — | Z68: — | AA68: — | AI68: e
A69: =ROW()-2 -> 67 | J69: 01_指標 | K69: =_xlfn.XLOOKUP(L69,'99_マスタ'!$D$5:$D$18,'99_マスタ'!$C$5:$C$18,"") -> 01_財務・業績指標 | L69: 03_販管費 | M69: 控除変動費 | N69: — | O69: 貢献利益算出時に控除する変動費（本社販売費・物流費等）。売上に連動する。 | P69: 予算時：売上予算 × 控除変動率 ／ 実績時：売上実績 × 控除変動率 | Q69: 円 | R69: 貢献利益管理 | S69: — | T69: — | U69: — | V69: — | W69: 推進M | X69: — | Y69: — | Z69: — | AA69: — | AI69: e
A70: =ROW()-2 -> 68 | J70: 01_指標 | K70: =_xlfn.XLOOKUP(L70,'99_マスタ'!$D$5:$D$18,'99_マスタ'!$C$5:$C$18,"") -> 01_財務・業績指標 | L70: 03_販管費 | M70: 販管費 | N70: — | O70: 販売費及び一般管理費の合計。広告宣伝費・運賃・保管料・人件費・一般管理費等を含む。 | P70: 販売費 + 広告宣伝費 + 運賃・保管料 + 人件費 + 一般管理費 | Q70: 円 | R70: — | S70: — | T70: — | U70: — | V70: 損益計算書（P/L） | W70: — | X70: — | Y70: — | Z70: — | AA70: 2月個別決算 | AI70: e
A71: =ROW()-2 -> 69 | J71: 01_指標 | K71: =_xlfn.XLOOKUP(L71,'99_マスタ'!$D$5:$D$18,'99_マスタ'!$C$5:$C$18,"") -> 01_財務・業績指標 | L71: 03_販管費 | M71: フィ | N71: 基本フィ | O71: 卸店の機能に対する割戻金。DBフィ／社会課題取組フィ／パートナーフィの3区分。 | P71: 売上規模ベース＋機能評価による加算 | Q71: %, 円 | R71: 卸取引制度, 基本フィ覚書 | S71: — | T71: — | U71: — | V71: — | W71: 菓初, 推進M | X71: — | Y71: — | Z71: — | AA71: — | AI71: e
A72: =ROW()-2 -> 70 | J72: 01_指標 | K72: =_xlfn.XLOOKUP(L72,'99_マスタ'!$D$5:$D$18,'99_マスタ'!$C$5:$C$18,"") -> 01_財務・業績指標 | L72: 03_販管費 | M72: パートナーフィ | N72: — | O72: 卸店の信用・店出データ提供・機能評価への対価。 | P72: 信用パート 0.8% + 店出データ 0.3% + 機能評価加算 | Q72: % | R72: 基本フィ覚書 | S72: — | T72: — | U72: — | V72: — | W72: 菓初 | X72: — | Y72: — | Z72: — | AA72: — | AI72: e
A73: =ROW()-2 -> 71 | J73: 01_指標 | K73: =_xlfn.XLOOKUP(L73,'99_マスタ'!$D$5:$D$18,'99_マスタ'!$C$5:$C$18,"") -> 01_財務・業績指標 | L73: 03_販管費 | M73: 社会課題取組フィ | N73: — | O73: ロッテと卸店の社会課題取組への対価。D+2対応・返品率削減等。 | P73: D+2対応：0.3% / 返品率削減：0.2-0.3% （4年ごと見直し） | Q73: % | R73: 基本フィ覚書 | S73: — | T73: — | U73: — | V73: — | W73: 菓初 | X73: — | Y73: — | Z73: — | AA73: — | AI73: e
A74: =ROW()-2 -> 72 | J74: 01_指標 | K74: =_xlfn.XLOOKUP(L74,'99_マスタ'!$D$5:$D$18,'99_マスタ'!$C$5:$C$18,"") -> 01_財務・業績指標 | L74: 03_販管費 | M74: 販売フィ | N74: — | O74: アイス取引制度における卸店への機能フィのうち、販売機能を評価した支払い。販路を持つ地域有力卸（販売型卸店）に対して販売伸長による達成フィとして設定される。 | P74: 売上達成率に応じた達成フィ率（%） | Q74: % | R74: アイス取引制度・卸店管理 | S74: — | T74: — | U74: — | V74: — | W74: 氷初 | X74: — | Y74: — | Z74: — | AA74: — | AI74: e
A75: =ROW()-2 -> 73 | J75: 01_指標 | K75: =_xlfn.XLOOKUP(L75,'99_マスタ'!$D$5:$D$18,'99_マスタ'!$C$5:$C$18,"") -> 01_財務・業績指標 | L75: 03_販管費 | M75: DBフィ | N75: ディストリビューターフィ | O75: 卸店の物流機能を評価した支払い。売上規模累進。 | P75: 卸別売上30百万からの累進適用 | Q75: % | R75: 基本フィ覚書 | S75: — | T75: — | U75: — | V75: — | W75: 菓初 | X75: — | Y75: — | Z75: — | AA75: — | AI75: e
A76: =ROW()-2 -> 74 | J76: 01_指標 | K76: =_xlfn.XLOOKUP(L76,'99_マスタ'!$D$5:$D$18,'99_マスタ'!$C$5:$C$18,"") -> 01_財務・業績指標 | L76: 03_販管費 | M76: 物流フィ | N76: — | O76: アイス取引制度における卸店への機能フィのうち、物流機能を評価した支払い。配送型卸店（小売業構成比が高い商社卸）に対して売上高規模による固定フィとして設定される。 | P76: 売上高規模基準による固定率（%） | Q76: % | R76: アイス取引制度・卸店管理 | S76: — | T76: — | U76: — | V76: — | W76: 氷初 | X76: — | Y76: — | Z76: — | AA76: — | AI76: e
A77: =ROW()-2 -> 75 | J77: 01_指標 | K77: =_xlfn.XLOOKUP(L77,'99_マスタ'!$D$5:$D$18,'99_マスタ'!$C$5:$C$18,"") -> 01_財務・業績指標 | L77: 04_利益・損失 | M77: 1人当たり生産性 | N77: ー | O77: 統括支店の職責別指数人員1人あたりが生み出した菓子・アイス貢献利益合計。組織評価における生産性評価指標で、ウェイト10%で配点される。前年比で評価され、人員効率の改善・悪化を測る。新入社員・試用見習・LPは対象外。産休・育休取得社員は月間暦日数で半分以上休みの場合対象外。 | P77: 菓子アイス貢献利益合計 ÷ 職責別指数人員 | R77: 支店別評価 | S77: — | T77: — | U77: — | V77: — | W77: 全営 | X77: — | Y77: — | Z77: — | AA77: — | AI77: e
A78: =ROW()-2 -> 76 | J78: 01_指標 | K78: =_xlfn.XLOOKUP(L78,'99_マスタ'!$D$5:$D$18,'99_マスタ'!$C$5:$C$18,"") -> 01_財務・業績指標 | L78: 04_利益・損失 | M78: EBITDA | N78: — | O78: 営業利益に売上原価と一般管理費内の減価償却費を加えた数値 | P78: 営業利益＋減価償却費（売上原価内＋一般管理費内） | Q78: 円 | R78: — | S78: — | T78: — | U78: — | V78: KK定例会長報告 | W78: — | X78: — | Y78: — | Z78: — | AA78: KK定例会長報告 | AB78: ・一般的なEBITDAは「経常利益＋支払利息＋減価償却費」とは異なりより保守的な算出式を利用 | AI78: e
A79: =ROW()-2 -> 77 | J79: 01_指標 | K79: =_xlfn.XLOOKUP(L79,'99_マスタ'!$D$5:$D$18,'99_マスタ'!$C$5:$C$18,"") -> 01_財務・業績指標 | L79: 04_利益・損失 | M79: 一人当たり利益 | N79: ー | O79: 生産性指標。営業本部で管理する生産性人員一人当たりの利益額 | Q79: 円/人 | R79: — | S79: — | T79: — | U79: — | V79: 営業本部KPI | W79: — | X79: — | Y79: — | Z79: — | AA79: 本部KPI確認 | AI79: e
A80: =ROW()-2 -> 78 | J80: 01_指標 | K80: =_xlfn.XLOOKUP(L80,'99_マスタ'!$D$5:$D$18,'99_マスタ'!$C$5:$C$18,"") -> 01_財務・業績指標 | L80: 04_利益・損失 | M80: 営業外収益 | N80: — | O80: 本業以外から得られる収益。受取利息・受取配当金・賃貸収入・為替差益・その他雑収入等を含む。 | P80: 受取利息 + 受取配当金 + 賃貸収入 + 為替差益 + 雑収入 | Q80: 円 | R80: — | S80: — | T80: — | U80: — | V80: 損益計算書（P/L） | W80: — | X80: — | Y80: — | Z80: — | AA80: 2月個別決算 | AI80: e
A81: =ROW()-2 -> 79 | J81: 01_指標 | K81: =_xlfn.XLOOKUP(L81,'99_マスタ'!$D$5:$D$18,'99_マスタ'!$C$5:$C$18,"") -> 01_財務・業績指標 | L81: 04_利益・損失 | M81: 営業外費用 | N81: — | O81: 本業以外で発生する費用。支払利息・売上割引・賃貸原価・為替差損等を含む。 | P81: 支払利息 +売上割引＋賃貸原価＋支払手数料＋ 為替差損 + その他雑損失 | Q81: 円 | R81: — | S81: — | T81: — | U81: — | V81: 損益計算書（P/L） | W81: — | X81: — | Y81: — | Z81: — | AA81: 2月個別決算 | AI81: e
A82: =ROW()-2 -> 80 | J82: 01_指標 | K82: =_xlfn.XLOOKUP(L82,'99_マスタ'!$D$5:$D$18,'99_マスタ'!$C$5:$C$18,"") -> 01_財務・業績指標 | L82: 04_利益・損失 | M82: 営業利益 | N82: ー | O82: 売上総利益から物流費・人件費（工場以外）・広告宣伝費・その他一般管理費を引いた金額 | P82: 売上総利益 － （物流費＋人件費（工場以外）＋広告宣伝費＋その他一般経費） | Q82: 円 | R82: — | S82: — | T82: — | U82: ロッテ業績超簡易版 | V82: — | W82: — | X82: — | Y82: — | Z82: ロッテ業績超簡易版 | AA82: — | AI82: e
A83: =ROW()-2 -> 81 | J83: 01_指標 | K83: =_xlfn.XLOOKUP(L83,'99_マスタ'!$D$5:$D$18,'99_マスタ'!$C$5:$C$18,"") -> 01_財務・業績指標 | L83: 04_利益・損失 | M83: 営業利益 | N83: OP | O83: 売上から売上原価・販管費を控除した本業の利益。事業ベースの最終利益指標。 | P83: 純売 − 売上原価 − 販管費 | Q83: 円 | R83: 営業政策, 月次品目別営業利益 | S83: 営業利益増減分析 | T83: — | U83: — | V83: 収益企画社長報告、KK定例会長報告、個別決算、本部KPI | W83: 営政, 全営 | X83: プランニング実績,損益共有MTG | Y83: — | Z83: — | AA83: 収益企画社長報告, KK定例会長報告、2月個別決算、本部KPI確認 | AI83: e
A84: =ROW()-2 -> 82 | J84: 01_指標 | K84: =_xlfn.XLOOKUP(L84,'99_マスタ'!$D$5:$D$18,'99_マスタ'!$C$5:$C$18,"") -> 01_財務・業績指標 | L84: 04_利益・損失 | M84: 営業利益率 | N84: ー | O84: 総売上に占める営業利益の割合 | P84: 営業利益 ÷ 総売上 | Q84: ％ | R84: — | S84: — | T84: — | U84: — | V84: 収益性分析 | W84: — | X84: — | Y84: — | Z84: — | AA84: 2月個別決算 | AB84: ・％と金額どちらが指標になるかは要確認 | AI84: e
A85: =ROW()-2 -> 83 | J85: 01_指標 | K85: =_xlfn.XLOOKUP(L85,'99_マスタ'!$D$5:$D$18,'99_マスタ'!$C$5:$C$18,"") -> 01_財務・業績指標 | L85: 04_利益・損失 | M85: 粗利 | N85: 売上総利益 | O85: 純売上高から売上原価（製造にかかる原材料費や工場の人件費など）を差し引いた利益。いわゆる「粗利」。 | P85: 純売上高 − 売上原価 | Q85: 円 | R85: — | S85: — | T85: — | U85: ロッテ業績超簡易版 | V85: 損益計算書（P/L）、本部KPI | W85: — | X85: — | Y85: — | Z85: ロッテ業績超簡易版 | AA85: 2月個別決算、本部KPI確認 | AI85: e
A86: =ROW()-2 -> 84 | J86: 01_指標 | K86: =_xlfn.XLOOKUP(L86,'99_マスタ'!$D$5:$D$18,'99_マスタ'!$C$5:$C$18,"") -> 01_財務・業績指標 | L86: 04_利益・損失 | M86: 卸粗利 | N86: ー | O86: 卸店の仕入価格（最終NET）と小売業への納価の差額 | P86: 卸粗利 ＝ 定番納価 − 最終NET ／ 小売粗利 ＝ 定番売価 − 定番納価 | Q86: 円, % | R86: 商談（定番・特売価格設定） | S86: — | T86: — | U86: — | V86: — | W86: 菓初, 氷初 | X86: — | Y86: — | Z86: — | AA86: — | AI86: e
A87: =ROW()-2 -> 85 | J87: 01_指標 | K87: =_xlfn.XLOOKUP(L87,'99_マスタ'!$D$5:$D$18,'99_マスタ'!$C$5:$C$18,"") -> 01_財務・業績指標 | L87: 04_利益・損失 | M87: 小売粗利 | N87: ー | O87: 小売業の仕入価格（納価）と店頭売価の差額。商談における価格設定の基準となる | P87: 卸粗利 ＝ 定番納価 − 最終NET ／ 小売粗利 ＝ 定番売価 − 定番納価 | Q87: 円, % | R87: 商談（定番・特売価格設定） | S87: — | T87: — | U87: — | V87: — | W87: 菓初, 氷初 | X87: — | Y87: — | Z87: — | AA87: — | AI87: e
A88: =ROW()-2 -> 86 | J88: 01_指標 | K88: =_xlfn.XLOOKUP(L88,'99_マスタ'!$D$5:$D$18,'99_マスタ'!$C$5:$C$18,"") -> 01_財務・業績指標 | L88: 04_利益・損失 | M88: 粗利率 | N88: ー | O88: 小売店が商品を販売した際に得られる利益の、売価に対する割合。売価から納価を差し引いた粗利額を売価で割った値。定番・特売それぞれで算出される。 | P88: （売価 − 納価） ÷ 売価 × 100 | Q88: % | R88: — | S88: — | T88: — | U88: — | V88: — | W88: — | X88: — | Y88: — | Z88: — | AA88: — | AI88: e
A89: =ROW()-2 -> 87 | J89: 01_指標 | K89: =_xlfn.XLOOKUP(L89,'99_マスタ'!$D$5:$D$18,'99_マスタ'!$C$5:$C$18,"") -> 01_財務・業績指標 | L89: 04_利益・損失 | M89: 定番粗利率 | N89: ー | O89: 定番販売時における小売店の粗利率。定番売価と定番納価の差額を定番売価で除した値。得意先の求める粗利率の目安はおおむね25〜30%前後。 | P89: （定番売価 − 定番納価） ÷ 定番売価 × 100 | Q89: % | R89: — | S89: — | T89: — | U89: — | V89: — | W89: — | X89: — | Y89: — | Z89: — | AA89: — | AI89: e
A90: =ROW()-2 -> 88 | J90: 01_指標 | K90: =_xlfn.XLOOKUP(L90,'99_マスタ'!$D$5:$D$18,'99_マスタ'!$C$5:$C$18,"") -> 01_財務・業績指標 | L90: 04_利益・損失 | M90: 特売粗利率 | N90: ー | O90: 特売販売時における小売店の粗利率。特売売価と特売納価の差額を特売売価で除した値。定番粗利率より低くなる傾向があり、得意先の求める粗利率の目安はおおむね20%前後。 | P90: （特売売価 − 特売納価） ÷ 特売売価 × 100 | Q90: % | R90: — | S90: — | T90: — | U90: — | V90: — | W90: — | X90: — | Y90: — | Z90: — | AA90: — | AI90: e
A91: =ROW()-2 -> 89 | J91: 01_指標 | K91: =_xlfn.XLOOKUP(L91,'99_マスタ'!$D$5:$D$18,'99_マスタ'!$C$5:$C$18,"") -> 01_財務・業績指標 | L91: 04_利益・損失 | M91: 総売比利益率 | N91: — | O91: 総売上に対する営業利益率。営業政策表で多用される独自表現。 | P91: 営業利益 ÷ 総売上高 × 100 | Q91: % | R91: 営業政策の予算表 | S91: — | T91: — | U91: — | V91: — | W91: 営政 | X91: — | Y91: — | Z91: — | AA91: — | AI91: e
A92: =ROW()-2 -> 90 | J92: 01_指標 | K92: =_xlfn.XLOOKUP(L92,'99_マスタ'!$D$5:$D$18,'99_マスタ'!$C$5:$C$18,"") -> 01_財務・業績指標 | L92: 04_利益・損失 | M92: 企業利益 | N92: — | O92: 営業活動で運用可能な費用のみを控除した利益。営業活動でコントロール可能な範囲の損益。 | P92: 売上 − 戦略原価 − フィ − 支店特売費 − 運賃（直取） | Q92: 円 | R92: 企業別予算, アクションプラン | S92: — | T92: — | U92: — | V92: — | W92: 推進M | X92: — | Y92: — | Z92: — | AA92: — | AI92: e
A93: =ROW()-2 -> 91 | J93: 01_指標 | K93: =_xlfn.XLOOKUP(L93,'99_マスタ'!$D$5:$D$18,'99_マスタ'!$C$5:$C$18,"") -> 01_財務・業績指標 | L93: 04_利益・損失 | M93: 経常利益 | N93: — | O93: 営業利益に営業外損益（金利・為替等）を加減した利益。 | P93: 営業利益 ± 営業外損益 | Q93: 円 | R93: 月次営業利益（全営） | S93: — | T93: — | U93: — | V93: KK定例会長報告、損益計算書 | W93: 全営 | X93: — | Y93: — | Z93: — | AA93: KK定例会長報告、2月個別決算 | AI93: e
A94: =ROW()-2 -> 92 | J94: 01_指標 | K94: =_xlfn.XLOOKUP(L94,'99_マスタ'!$D$5:$D$18,'99_マスタ'!$C$5:$C$18,"") -> 01_財務・業績指標 | L94: 04_利益・損失 | M94: 見なし利益 | N94: — | O94: 企業別ローリングで使う、商品別実際原価＋物流費にて算出する利益。営業独自の概念。 | P94: 売上 − 商品別実際原価 − 物流費（実額ベース） | Q94: 円 | R94: 企業商品別収益構造改革（営業政策） | S94: — | T94: — | U94: — | V94: — | W94: 営政 | X94: — | Y94: — | Z94: — | AA94: — | AI94: e
A95: =ROW()-2 -> 93 | J95: 01_指標 | K95: =_xlfn.XLOOKUP(L95,'99_マスタ'!$D$5:$D$18,'99_マスタ'!$C$5:$C$18,"") -> 01_財務・業績指標 | L95: 04_利益・損失 | M95: 限界利益 | N95: — | O95: 売上から変動費を引いた利益。商品別販売戦略の主軸KPI（限界利益率）。 | P95: 売上 − 変動費 | Q95: 円 | R95: 商品別限界利益率分析（営業政策に多数登場） | S95: 損益概況 | T95: — | U95: SCM会議（商品別限界利益率分析・VC改革検討）, S&OP分析（SCM効率化KGI） | V95: KK定例会長報告,収益企画社長報告（PLツリー） | W95: 営政, 全営 | X95: プランニング実績,損益共有MTG | Y95: — | Z95: SCM会議, 第3回SCM議事録, 第1回SCM議事録, 第2回SCM議事録, S&OP事例 | AA95: KK定例会長報告,収益企画社長報告 | AB95: 2025/5/12 SCM会議議事録にて、「営業利益から固定費を除いた限界利益率は～」というご発言があり別定義がないかはご確認いただきたい | AI95: e
A96: =ROW()-2 -> 94 | J96: 01_指標 | K96: =_xlfn.XLOOKUP(L96,'99_マスタ'!$D$5:$D$18,'99_マスタ'!$C$5:$C$18,"") -> 01_財務・業績指標 | L96: 04_利益・損失 | M96: 限界利益率 | N96: ー | O96: 総売上高に占める限界利益の割合 | P96: 限界利益 ÷ 総売上 × 100 | Q96: % | R96: — | S96: — | T96: — | U96: SCM会議（商品別限界利益率分析・VC改革検討） | V96: 本部KPI | W96: — | X96: — | Y96: — | Z96: 第1回SCM議事録 | AA96: 本部KPI確認 | AI96: e
A97: =ROW()-2 -> 95 | J97: 01_指標 | K97: =_xlfn.XLOOKUP(L97,'99_マスタ'!$D$5:$D$18,'99_マスタ'!$C$5:$C$18,"") -> 01_財務・業績指標 | L97: 04_利益・損失 | M97: 工場利益金額 | N97: 工場利益 | O97: 各工場の生産活動による利益。生産本部の最重要KPI。工場別（浦和・狭山・九州・滋賀）に設定・管理される。 | Q97: 円 | R97: — | S97: — | T97: 目標管理実績（工場別KPI管理）・年度KPI | U97: — | V97: 会長報告・経営会議、本部KPI | W97: — | X97: — | Y97: 目標管理実績, 会長報告生産3月 | Z97: — | AA97: 本部KPI確認 | AI97: e
A98: =ROW()-2 -> 96 | J98: 01_指標 | K98: =_xlfn.XLOOKUP(L98,'99_マスタ'!$D$5:$D$18,'99_マスタ'!$C$5:$C$18,"") -> 01_財務・業績指標 | L98: 04_利益・損失 | M98: 貢献利益 | N98: — | O98: 企業利益から、本社販売費・物流費・広告宣伝費・人件費・一般管理費を控除した利益。事業営業利益に最も近い。 | P98: 企業利益 − 本社販売費（特売費・拡売費）− 物流費 − 広告宣伝費 − 人件費/一般管理費 | Q98: 円 | R98: 貢献利益月別、企業別ローリング | S98: — | T98: — | U98: — | V98: — | W98: 推進M | X98: — | Y98: — | Z98: — | AA98: — | AI98: e
A99: =ROW()-2 -> 97 | J99: 01_指標 | K99: =_xlfn.XLOOKUP(L99,'99_マスタ'!$D$5:$D$18,'99_マスタ'!$C$5:$C$18,"") -> 01_財務・業績指標 | L99: 04_利益・損失 | M99: 支店利益 | N99: — | O99: 企業利益から支店レベルの拡売費（資材費・ディスプレイ費）を控除した利益。 | P99: 企業利益 − 資材費 − ディスプレイ費 | Q99: 円 | R99: 支店PL | S99: — | T99: — | U99: — | V99: — | W99: 推進M | X99: — | Y99: — | Z99: — | AA99: — | AI99: e
A100: =ROW()-2 -> 98 | J100: 01_指標 | K100: =_xlfn.XLOOKUP(L100,'99_マスタ'!$D$5:$D$18,'99_マスタ'!$C$5:$C$18,"") -> 01_財務・業績指標 | L100: 04_利益・損失 | M100: 統括利益 | N100: — | O100: 支店利益から統括支店管理費用を控除した利益。統括支店の最終損益。 | P100: 支店利益 − 統括支店管理費用 | Q100: 円 | R100: 統括支店予算編成会議 | S100: — | T100: — | U100: — | V100: — | W100: 推進M | X100: — | Y100: — | Z100: — | AA100: — | AI100: e
...

Sheet 99_マスタ
B2: プルダウン用マスタ
B4: 指標大分類 | C4: 指標タイプ | D4: 概念
B5: 01_指標 | C5: 01_財務・業績指標 | D5: 01_売上
B6: 02_マスタ | C6: 01_財務・業績指標 | D6: 02_原価
B7: 03_その他 | C7: 01_財務・業績指標 | D7: 03_販管費
C8: 01_財務・業績指標 | D8: 04_利益・損失
C9: 01_財務・業績指標 | D9: 05_資産・負債
C10: 02_生販在 | D10: 06_生産
C11: 02_生販在 | D11: 07_販売
C12: 02_生販在 | D12: 08_SCM
C13: 02_生販在 | D13: 09_商品名・ブランド
C14: 03_会社運営 | D14: 10_システム
C15: 03_会社運営 | D15: 11_組織
C16: 03_会社運営 | D16: 12_人材
C17: 03_会社運営 | D17: 13_業務・プロジェクト
C18: 03_会社運営 | D18: 14_その他
